Workbook

Sheet 대상
A1: 순번 | B1: 과제번호 | C1: 공고 | D1: 공고구분 | E1: 대표자명 | F1: 성별 | G1: 생년월일 | H1: 청/중장년 | I1: 매출액 | J1: 사원수(명) | K1: 과제명 | L1: 창업(희망)지역 | M1: 지원분야 | N1: 전문기술분야 | O1: 평가기준 | P1: 분과 | Q1: 평가일자 | R1: 요건검토 | S1: 재창업 청년 창업기업 | T1: 25년 린스타트업 우수자 | U1: 25년 창업중심대학 최우수 판정기업 | V1: 가점 | W1: 25년 대학창업 아이디어 챌린지(대상, 최우수상) | X1: 25년 린스타트업 우수자 | Y1: 도전!k-스타트업 왕중왕전 | Z1: 협력기관 추천(10개) | AA1: 지역특화 레전드50+ | AB1: 사전검토 | AC1: 특이사항
A2: 1 | B2: 20396065 | C2: 2026년도 창업중심대학 지역기반 (예비)창업기업 모집 공고 | D2: 지역기반 | E2: 심성진 | F2: 남 | G2: 1989-11-11 | H2: 청년 | I2: 0 | J2: 0 | K2: AI경대 미용실 | L2: 서울 | M2: 제조 | N2: 공예ㆍ디자인 | O2: 예비 | P2: 공예ㆍ디자인 | Q2: =TODAY() -> 46120 | R2: 요건탈락 | S2: 0 | T2: 0 | U2: 0 | V2: =IF(OR(S2="○",T2="○",U2="○"),2,0) -> 0 | W2: 0 | X2: 0 | Y2: 0 | Z2: 0 | AA2: 0 | AB2: =IF(OR(W2="○",X2="○",Y2="○",Z2="○",AA2="○"),"면제",$R2) -> 요건탈락
A3: 2 | B3: 20399405 | C3: 2026년도 창업중심대학 지역기반 (예비)창업기업 모집 공고 | D3: 지역기반 | E3: 박준용 | F3: 남 | G3: 1983-03-25 | H3: 중장년 | I3: 101,000,000 | J3: 4 | K3: AI Agent 기술을 활용한 CFM(고객 피드백 관리) 서비스 | L3: 경기 | M3: 지식서비스 | N3: 정보ㆍ통신 | O3: 초기 | P3: 정보ㆍ통신5 | Q3: =TODAY() -> 46120 | R3: 0 | S3: 0 | T3: 0 | U3: 0 | V3: =IF(OR(S3="○",T3="○",U3="○"),2,0) -> 0 | W3: 0 | X3: 0 | Y3: 0 | Z3: 0 | AA3: 0 | AB3: =IF(OR(W3="○",X3="○",Y3="○",Z3="○",AA3="○"),"면제",$R3) -> 0
A4: 3 | B4: 20399435 | C4: 2026년도 창업중심대학 지역기반 (예비)창업기업 모집 공고 | D4: 지역기반 | E4: 이희정 | F4: 여 | G4: 1968-07-11 | H4: 중장년 | I4: 7,600 | J4: 0 | K4: IHI(상호작용 건전성 지수) 기반 AI 부모코칭 SaaS 플랫폼 | L4: 경기 | M4: 지식서비스 | N4: 정보ㆍ통신 | O4: 초기 | P4: 정보ㆍ통신6 | Q4: =TODAY() -> 46120 | R4: 0 | S4: 0 | T4: 0 | U4: 0 | V4: =IF(OR(S4="○",T4="○",U4="○"),2,0) -> 0 | W4: 0 | X4: 0 | Y4: 0 | Z4: 0 | AA4: 0 | AB4: =IF(OR(W4="○",X4="○",Y4="○",Z4="○",AA4="○"),"면제",$R4) -> 0
A5: 4 | B5: 20399536 | C5: 2026년도 창업중심대학 지역기반 (예비)창업기업 모집 공고 | D5: 지역기반 | E5: 김지형 | F5: 여 | G5: 1999-09-06 | H5: 청년 | I5: 0 | J5: 0 | K5: 웹에서 디자인하고 실시간으로 주문하는 레터링 케이크 플랫폼 ‘케끄’ | L5: 서울 | M5: 지식서비스 | N5: 정보ㆍ통신 | O5: 예비 | P5: 정보ㆍ통신3 | Q5: =TODAY() -> 46120 | R5: 0 | S5: 0 | T5: 0 | U5: 0 | V5: =IF(OR(S5="○",T5="○",U5="○"),2,0) -> 0 | W5: 0 | X5: 0 | Y5: 0 | Z5: 0 | AA5: 0 | AB5: =IF(OR(W5="○",X5="○",Y5="○",Z5="○",AA5="○"),"면제",$R5) -> 0
A6: 5 | B6: 20399570 | C6: 2026년도 창업중심대학 지역기반 (예비)창업기업 모집 공고 | D6: 지역기반 | E6: 전준형 | F6: 남 | G6: 2001-08-06 | H6: 청년 | I6: 0 | J6: 0 | K6: 실시간 감정 공유 기능으로 콘텐츠를 200% 더 재미있게 시청할 수 있는 동시시청 플랫폼 ‘비욘드’ | L6: 경기 | M6: 지식서비스 | N6: 정보ㆍ통신 | O6: 예비 | P6: 정보ㆍ통신2 | Q6: =TODAY() -> 46120 | R6: 0 | S6: 0 | T6: 0 | U6: 0 | V6: =IF(OR(S6="○",T6="○",U6="○"),2,0) -> 0 | W6: 0 | X6: 0 | Y6: 0 | Z6: 0 | AA6: 0 | AB6: =IF(OR(W6="○",X6="○",Y6="○",Z6="○",AA6="○"),"면제",$R6) -> 0
A7: 6 | B7: 20399602 | C7: 2026년도 창업중심대학 지역기반 (예비)창업기업 모집 공고 | D7: 지역기반 | E7: 황명희 | F7: 여 | G7: 1975-08-26 | H7: 중장년 | I7: 0 | J7: 0 | K7: 임상 기반 기능성 아로마 바디케어 제품 개발 및 브랜드 사업화 | L7: 경기 | M7: 제조 | N7: 화공ㆍ섬유 | O7: 예비 | P7: 화공ㆍ섬유 | Q7: =TODAY() -> 46120 | R7: 0 | S7: 0 | T7: 0 | U7: 0 | V7: =IF(OR(S7="○",T7="○",U7="○"),2,0) -> 0 | W7: 0 | X7: 0 | Y7: 0 | Z7: 0 | AA7: 0 | AB7: =IF(OR(W7="○",X7="○",Y7="○",Z7="○",AA7="○"),"면제",$R7) -> 0
A8: 7 | B8: 20399632 | C8: 2026년도 창업중심대학 지역기반 (예비)창업기업 모집 공고 | D8: 지역기반 | E8: 최겸 | F8: 남 | G8: 2000-10-04 | H8: 청년 | I8: 0 | J8: 0 | K8: AI(LLM) 기반 시니어 음성 인터랙티브 자서전 자동 제작 플랫폼 | L8: 경기 | M8: 제조 | N8: 정보ㆍ통신 | O8: 예비 | P8: 정보ㆍ통신4 | Q8: =TODAY() -> 46120 | R8: 0 | S8: ○ | T8: 0 | U8: 0 | V8: =IF(OR(S8="○",T8="○",U8="○"),2,0) -> 2 | W8: 0 | X8: 0 | Y8: 0 | Z8: 0 | AA8: 0 | AB8: =IF(OR(W8="○",X8="○",Y8="○",Z8="○",AA8="○"),"면제",$R8) -> 0
A9: 8 | B9: 20399678 | C9: 2026년도 창업중심대학 지역기반 (예비)창업기업 모집 공고 | D9: 지역기반 | E9: 박영찬 | F9: 남 | G9: 1981-07-16 | H9: 중장년 | I9: 0 | J9: 0 | K9: AI 기술이 적용된 기술자 중심 하이퍼 로컬 시공 중개 플랫폼, 우리동네기술자(WOOGI) | L9: 경기 | M9: 지식서비스 | N9: 정보ㆍ통신 | O9: 예비 | P9: 정보ㆍ통신4 | Q9: =TODAY() -> 46120 | R9: 0 | S9: 0 | T9: 0 | U9: 0 | V9: =IF(OR(S9="○",T9="○",U9="○"),2,0) -> 0 | W9: 0 | X9: 0 | Y9: 0 | Z9: 0 | AA9: 0 | AB9: =IF(OR(W9="○",X9="○",Y9="○",Z9="○",AA9="○"),"면제",$R9) -> 0
A10: 9 | B10: 20399729 | C10: 2026년도 창업중심대학 지역기반 (예비)창업기업 모집 공고 | D10: 지역기반 | E10: 심명훈 | F10: 남 | G10: 1994-05-20 | H10: 청년 | I10: 0 | J10: 0 | K10: 연 1,894만 명 방한 외래관광객 시장에서, 현지인과의 로컬 경험의 신뢰·탐색·언어 장벽 문제를 LLM 기반 AI 코스 추천과 역경매 호스트 매칭으로 해결하는 초개인화 여행 경험 커머스 (MVP지표: 파일럿 매출 48만원, 사용자 277명) | L10: 인천 | M10: 지식서비스 | N10: 정보ㆍ통신 | O10: 예비 | P10: 정보ㆍ통신6 | Q10: =TODAY() -> 46120 | R10: 0 | S10: ○ | T10: 0 | U10: 0 | V10: =IF(OR(S10="○",T10="○",U10="○"),2,0) -> 2 | W10: 0 | X10: 0 | Y10: 0 | Z10: 0 | AA10: 0 | AB10: =IF(OR(W10="○",X10="○",Y10="○",Z10="○",AA10="○"),"면제",$R10) -> 0
A11: 10 | B11: 20399730 | C11: 2026년도 창업중심대학 지역기반 (예비)창업기업 모집 공고 | D11: 지역기반 | E11: 심우정 | F11: 여 | G11: 1990-01-30 | H11: 청년 | I11: 0 | J11: 0 | K11: 위험도 산출 알고리즘 기술이 적용된 임신·수유부의 개인맞춤형(임신주수 및 월령별) 복약 안전 정보 모바일 앱 ‘필버스’ | L11: 경기 | M11: 지식서비스 | N11: 정보ㆍ통신 | O11: 예비 | P11: 정보ㆍ통신5 | Q11: =TODAY() -> 46120 | R11: 0 | S11: ○ | T11: 0 | U11: 0 | V11: =IF(OR(S11="○",T11="○",U11="○"),2,0) -> 2 | W11: 0 | X11: 0 | Y11: 0 | Z11: 0 | AA11: 0 | AB11: =IF(OR(W11="○",X11="○",Y11="○",Z11="○",AA11="○"),"면제",$R11) -> 0
A12: 11 | B12: 20399860 | C12: 2026년도 창업중심대학 지역기반 (예비)창업기업 모집 공고 | D12: 지역기반 | E12: 김승영 | F12: 남 | G12: 1987-06-26 | H12: 청년 | I12: 0 | J12: 0 | K12: 예비창업자의 시장 수요 검증을 위한 신뢰도 기반 타겟 매칭·AI 분석 시장검증 서비스 개발 | L12: 서울 | M12: 지식서비스 | N12: 정보ㆍ통신 | O12: 예비 | P12: 정보ㆍ통신5 | Q12: =TODAY() -> 46120 | R12: 0 | S12: 0 | T12: 0 | U12: 0 | V12: =IF(OR(S12="○",T12="○",U12="○"),2,0) -> 0 | W12: 0 | X12: 0 | Y12: 0 | Z12: 0 | AA12: 0 | AB12: =IF(OR(W12="○",X12="○",Y12="○",Z12="○",AA12="○"),"면제",$R12) -> 0
A13: 12 | B13: 20399910 | C13: 2026년도 창업중심대학 지역기반 (예비)창업기업 모집 공고 | D13: 지역기반 | E13: 윤여준 | F13: 남 | G13: 1985-07-24 | H13: 중장년 | I13: 267,181,182 | J13: 2 | K13: 심박데이터 기반 개인 맞춤형 운동결과 분석·추천 서비스 고도화 및 상용화 | L13: 서울 | M13: 지식서비스 | N13: 정보ㆍ통신 | O13: 초기 | P13: 정보ㆍ통신3 | Q13: =TODAY() -> 46120 | R13: 0 | S13: 0 | T13: 0 | U13: 0 | V13: =IF(OR(S13="○",T13="○",U13="○"),2,0) -> 0 | W13: 0 | X13: 0 | Y13: 0 | Z13: 0 | AA13: 0 | AB13: =IF(OR(W13="○",X13="○",Y13="○",Z13="○",AA13="○"),"면제",$R13) -> 0
A14: 13 | B14: 20400081 | C14: 2026년도 창업중심대학 지역기반 (예비)창업기업 모집 공고 | D14: 지역기반 | E14: 임성현 | F14: 남 | G14: 1981-09-20 | H14: 중장년 | I14: 0 | J14: 0 | K14: 나들목 | L14: 경기 | M14: 지식서비스 | N14: 정보ㆍ통신 | O14: 초기 | P14: 정보ㆍ통신6 | Q14: =TODAY() -> 46120 | R14: 0 | S14: 0 | T14: 0 | U14: 0 | V14: =IF(OR(S14="○",T14="○",U14="○"),2,0) -> 0 | W14: 0 | X14: 0 | Y14: 0 | Z14: 0 | AA14: 0 | AB14: =IF(OR(W14="○",X14="○",Y14="○",Z14="○",AA14="○"),"면제",$R14) -> 0
A15: 14 | B15: 20400184 | C15: 2026년도 창업중심대학 지역기반 (예비)창업기업 모집 공고 | D15: 지역기반 | E15: 신주일 | F15: 남 | G15: 1984-10-14 | H15: 중장년 | I15: 2,101,282,727 | J15: 11 | K15: 디지털 스컬핑 기술을 활용한 조형 기반 웨어러블 스컬프처 브랜드 'VAXINE' | L15: 경기 | M15: 제조 | N15: 공예ㆍ디자인 | O15: 초기 | P15: 공예ㆍ디자인 | Q15: =TODAY() -> 46120 | R15: 0 | S15: 0 | T15: 0 | U15: 0 | V15: =IF(OR(S15="○",T15="○",U15="○"),2,0) -> 0 | W15: 0 | X15: 0 | Y15: 0 | Z15: 0 | AA15: 0 | AB15: =IF(OR(W15="○",X15="○",Y15="○",Z15="○",AA15="○"),"면제",$R15) -> 0
A16: 15 | B16: 20400322 | C16: 2026년도 창업중심대학 지역기반 (예비)창업기업 모집 공고 | D16: 지역기반 | E16: 주이나 | F16: 여 | G16: 1991-11-27 | H16: 청년 | I16: 138,076,812 | J16: 2 | K16: AI 비전 인식 기반 시니어 신체 데이터 분석을 통한 개인 맞춤형 방문 이미용 케어 플랫폼 | L16: 경기 | M16: 지식서비스 | N16: 정보ㆍ통신 | O16: 도약 | P16: 정보ㆍ통신3 | Q16: =TODAY() -> 46120 | R16: 0 | S16: 0 | T16: 0 | U16: 0 | V16: =IF(OR(S16="○",T16="○",U16="○"),2,0) -> 0 | W16: 0 | X16: 0 | Y16: 0 | Z16: 0 | AA16: 0 | AB16: =IF(OR(W16="○",X16="○",Y16="○",Z16="○",AA16="○"),"면제",$R16) -> 0
A17: 16 | B17: 20400325 | C17: 2026년도 창업중심대학 지역기반 (예비)창업기업 모집 공고 | D17: 지역기반 | E17: 이언봉 | F17: 남 | G17: 1983-06-20 | H17: 중장년 | I17: 0 | J17: 0 | K17: AI 데이터센터용 고성능 반도체 신뢰성 확보를 위한 실시간 수명 예측 온칩 모니터링 프로토타입 개발 | L17: 경기 | M17: 제조 | N17: 전기ㆍ전자 | O17: 예비 | P17: 전기ㆍ전자 | Q17: =TODAY() -> 46120 | R17: 0 | S17: 0 | T17: 0 | U17: 0 | V17: =IF(OR(S17="○",T17="○",U17="○"),2,0) -> 0 | W17: 0 | X17: 0 | Y17: 0 | Z17: 0 | AA17: 0 | AB17: =IF(OR(W17="○",X17="○",Y17="○",Z17="○",AA17="○"),"면제",$R17) -> 0
A18: 17 | B18: 20400332 | C18: 2026년도 창업중심대학 지역기반 (예비)창업기업 모집 공고 | D18: 지역기반 | E18: 이상달 | F18: 남 | G18: 1965-03-22 | H18: 중장년 | I18: 94,328,000 | J18: 2 | K18: AI 기반 병원동행 서비스 플랫폼(MD에스코트) | L18: 서울 | M18: 지식서비스 | N18: 정보ㆍ통신 | O18: 도약 | P18: 정보ㆍ통신7 | Q18: =TODAY() -> 46120 | R18: 0 | S18: 0 | T18: 0 | U18: 0 | V18: =IF(OR(S18="○",T18="○",U18="○"),2,0) -> 0 | W18: 0 | X18: 0 | Y18: 0 | Z18: 0 | AA18: 0 | AB18: =IF(OR(W18="○",X18="○",Y18="○",Z18="○",AA18="○"),"면제",$R18) -> 0
A19: 18 | B19: 20400348 | C19: 2026년도 창업중심대학 지역기반 (예비)창업기업 모집 공고 | D19: 지역기반 | E19: 이학용 | F19: 남 | G19: 1989-07-12 | H19: 청년 | I19: 287,324,936 | J19: 1 | K19: 출산 후 아이의 성장과 함께하는 육아 라이프사이클 렌탈 플랫폼 | L19: 서울 | M19: 지식서비스 | N19: 정보ㆍ통신 | O19: 초기 | P19: 정보ㆍ통신2 | Q19: =TODAY() -> 46120 | R19: 0 | S19: 0 | T19: 0 | U19: 0 | V19: =IF(OR(S19="○",T19="○",U19="○"),2,0) -> 0 | W19: 0 | X19: 0 | Y19: 0 | Z19: 0 | AA19: 0 | AB19: =IF(OR(W19="○",X19="○",Y19="○",Z19="○",AA19="○"),"면제",$R19) -> 0
A20: 19 | B20: 20400362 | C20: 2026년도 창업중심대학 지역기반 (예비)창업기업 모집 공고 | D20: 지역기반 | E20: 이승주 | F20: 남 | G20: 1997-05-21 | H20: 청년 | I20: 1,600 | J20: 1 | K20: 고기능성 반려견 퀵-레이스 하네스 | L20: 경기 | M20: 제조 | N20: 화공ㆍ섬유 | O20: 초기 | P20: 화공ㆍ섬유 | Q20: =TODAY() -> 46120 | R20: 0 | S20: 0 | T20: 0 | U20: 0 | V20: =IF(OR(S20="○",T20="○",U20="○"),2,0) -> 0 | W20: 0 | X20: 0 | Y20: 0 | Z20: 0 | AA20: 0 | AB20: =IF(OR(W20="○",X20="○",Y20="○",Z20="○",AA20="○"),"면제",$R20) -> 0
A21: 20 | B21: 20400729 | C21: 2026년도 창업중심대학 지역기반 (예비)창업기업 모집 공고 | D21: 지역기반 | E21: 김수빈 | F21: 여 | G21: 1995-08-29 | H21: 청년 | I21: 0 | J21: 0 | K21: 1인 기업가의 매출 및 생산성 극대화를 위한 업무 시간 최적화 SaaS | L21: 경기 | M21: 지식서비스 | N21: 정보ㆍ통신 | O21: 예비 | P21: 정보ㆍ통신2 | Q21: =TODAY() -> 46120 | R21: 요건탈락 | S21: 0 | T21: 0 | U21: 0 | V21: =IF(OR(S21="○",T21="○",U21="○"),2,0) -> 0 | W21: 0 | X21: 0 | Y21: 0 | Z21: 0 | AA21: 0 | AB21: =IF(OR(W21="○",X21="○",Y21="○",Z21="○",AA21="○"),"면제",$R21) -> 요건탈락
A22: 21 | B22: 20400898 | C22: 2026년도 창업중심대학 지역기반 (예비)창업기업 모집 공고 | D22: 지역기반 | E22: 고윤제 | F22: 남 | G22: 1994-05-09 | H22: 청년 | I22: 33,716,363 | J22: 0 | K22: 기업의 SaaS 도입비용을 개선하는 SaaS 온보딩 서비스(RAG/커뮤니티 데이터 기반) | L22: 서울 | M22: 지식서비스 | N22: 정보ㆍ통신 | O22: 초기 | P22: 정보ㆍ통신3 | Q22: =TODAY() -> 46120 | R22: 0 | S22: ○ | T22: 0 | U22: 0 | V22: =IF(OR(S22="○",T22="○",U22="○"),2,0) -> 2 | W22: 0 | X22: 0 | Y22: 0 | Z22: 0 | AA22: 0 | AB22: =IF(OR(W22="○",X22="○",Y22="○",Z22="○",AA22="○"),"면제",$R22) -> 0
A23: 22 | B23: 20400906 | C23: 2026년도 창업중심대학 지역기반 (예비)창업기업 모집 공고 | D23: 지역기반 | E23: 김민선 | F23: 여 | G23: 1991-01-15 | H23: 청년 | I23: 0 | J23: 0 | K23: 평택 주한미군 및 가족 5만 명 대상 지역 특산 쌀·배 전통주 체험존 | L23: 경기 | M23: 제조 | N23: 공예ㆍ디자인 | O23: 예비 | P23: 공예ㆍ디자인 | Q23: =TODAY() -> 46120 | R23: 0 | S23: ○ | T23: 0 | U23: 0 | V23: =IF(OR(S23="○",T23="○",U23="○"),2,0) -> 2 | W23: 0 | X23: 0 | Y23: 0 | Z23: 0 | AA23: 0 | AB23: =IF(OR(W23="○",X23="○",Y23="○",Z23="○",AA23="○"),"면제",$R23) -> 0
A24: 23 | B24: 20401026 | C24: 2026년도 창업중심대학 지역기반 (예비)창업기업 모집 공고 | D24: 지역기반 | E24: 이동권 | F24: 남 | G24: 1989-01-28 | H24: 청년 | I24: 5,000,000,000 | J24: 3 | K24: 대규모 진료데이터 활용한 병원 운영 AI 플랫폼 구축 : 포텐셜부터 개선방안 제안까지 | L24: 경기 | M24: 지식서비스 | N24: 정보ㆍ통신 | O24: 도약 | P24: 정보ㆍ통신4 | Q24: =TODAY() -> 46120 | R24: 0 | S24: 0 | T24: 0 | U24: 0 | V24: =IF(OR(S24="○",T24="○",U24="○"),2,0) -> 0 | W24: 0 | X24: 0 | Y24: 0 | Z24: 0 | AA24: 0 | AB24: =IF(OR(W24="○",X24="○",Y24="○",Z24="○",AA24="○"),"면제",$R24) -> 0
A25: 24 | B25: 20401050 | C25: 2026년도 창업중심대학 지역기반 (예비)창업기업 모집 공고 | D25: 지역기반 | E25: 황설아 | F25: 여 | G25: 1993-05-02 | H25: 청년 | I25: 0 | J25: 0 | K25: AI 기반 환자맞춤형 글로벌 의료관광 원스톱 플랫폼, 메디럭스AI(MediLuxeAI) | L25: 서울 | M25: 지식서비스 | N25: 바이오ㆍ의료ㆍ생명 | O25: 예비 | P25: 바이오ㆍ의료ㆍ생명1 | Q25: =TODAY() -> 46120 | R25: 0 | S25: ○ | T25: 0 | U25: 0 | V25: =IF(OR(S25="○",T25="○",U25="○"),2,0) -> 2 | W25: 0 | X25: 0 | Y25: 0 | Z25: 0 | AA25: 0 | AB25: =IF(OR(W25="○",X25="○",Y25="○",Z25="○",AA25="○"),"면제",$R25) -> 0
A26: 25 | B26: 20401269 | C26: 2026년도 창업중심대학 지역기반 (예비)창업기업 모집 공고 | D26: 지역기반 | E26: 윤수정 | F26: 여 | G26: 1992-02-17 | H26: 청년 | I26: 41,352,356 | J26: 0 | K26: 수상 스포츠 이후 아로마테라피를 활용한 ‘After-Water Ritual’ 스킨케어 브랜드 | L26: 서울 | M26: 제조 | N26: 화공ㆍ섬유 | O26: 초기 | P26: 화공ㆍ섬유 | Q26: =TODAY() -> 46120 | R26: 0 | S26: 0 | T26: 0 | U26: 0 | V26: =IF(OR(S26="○",T26="○",U26="○"),2,0) -> 0 | W26: 0 | X26: 0 | Y26: 0 | Z26: 0 | AA26: ○ | AB26: =IF(OR(W26="○",X26="○",Y26="○",Z26="○",AA26="○"),"면제",$R26) -> 면제
A27: 26 | B27: 20401280 | C27: 2026년도 창업중심대학 지역기반 (예비)창업기업 모집 공고 | D27: 지역기반 | E27: 변윤경 | F27: 여 | G27: 1987-04-28 | H27: 청년 | I27: 5,600,000 | J27: 3 | K27: 한국 전통 문양(IP) 기반 하이엔드 텍스타일 PB상품 제조·판매 | L27: 서울 | M27: 제조 | N27: 공예ㆍ디자인 | O27: 초기 | P27: 공예ㆍ디자인 | Q27: =TODAY() -> 46120 | R27: 0 | S27: ○ | T27: 0 | U27: 0 | V27: =IF(OR(S27="○",T27="○",U27="○"),2,0) -> 2 | W27: 0 | X27: 0 | Y27: 0 | Z27: 0 | AA27: 0 | AB27: =IF(OR(W27="○",X27="○",Y27="○",Z27="○",AA27="○"),"면제",$R27) -> 0
A28: 27 | B28: 20401288 | C28: 2026년도 창업중심대학 지역기반 (예비)창업기업 모집 공고 | D28: 지역기반 | E28: 이강민 | F28: 남 | G28: 1970-01-28 | H28: 중장년 | I28: 0 | J28: 0 | K28: 중소 제조기업 기술자산 기반 기술질의·애로 처리시간 단축 AX 솔루션 | L28: 경기 | M28: 지식서비스 | N28: 정보ㆍ통신 | O28: 예비 | P28: 정보ㆍ통신3 | Q28: =TODAY() -> 46120 | R28: 0 | S28: 0 | T28: 0 | U28: 0 | V28: =IF(OR(S28="○",T28="○",U28="○"),2,0) -> 0 | W28: 0 | X28: 0 | Y28: 0 | Z28: 0 | AA28: 0 | AB28: =IF(OR(W28="○",X28="○",Y28="○",Z28="○",AA28="○"),"면제",$R28) -> 0
A29: 28 | B29: 20401289 | C29: 2026년도 창업중심대학 지역기반 (예비)창업기업 모집 공고 | D29: 지역기반 | E29: 유승훈 | F29: 남 | G29: 1996-07-30 | H29: 청년 | I29: 0 | J29: 0 | K29: 커피박(커피찌꺼기) 수거-제조-판매 통합 밸류체인 구축을 통한 바이오매스 연료탄 생산 및 순환경제 플랫폼 운영 | L29: 서울 | M29: 제조 | N29: 정보ㆍ통신 | O29: 초기 | P29: 정보ㆍ통신7 | Q29: =TODAY() -> 46120 | R29: 0 | S29: 0 | T29: 0 | U29: 0 | V29: =IF(OR(S29="○",T29="○",U29="○"),2,0) -> 0 | W29: 0 | X29: 0 | Y29: 0 | Z29: 0 | AA29: 0 | AB29: =IF(OR(W29="○",X29="○",Y29="○",Z29="○",AA29="○"),"면제",$R29) -> 0
A30: 29 | B30: 20401317 | C30: 2026년도 창업중심대학 지역기반 (예비)창업기업 모집 공고 | D30: 지역기반 | E30: 신유경 | F30: 여 | G30: 1998-09-01 | H30: 청년 | I30: 0 | J30: 0 | K30: 한글 자음 • 모음 조형 구조 기반 패션 디자인 시스템 개발 및 의류 제품 사업화 | L30: 서울 | M30: 제조 | N30: 공예ㆍ디자인 | O30: 예비 | P30: 공예ㆍ디자인 | Q30: =TODAY() -> 46120 | R30: 요건탈락 | S30: 0 | T30: 0 | U30: 0 | V30: =IF(OR(S30="○",T30="○",U30="○"),2,0) -> 0 | W30: 0 | X30: 0 | Y30: 0 | Z30: 0 | AA30: 0 | AB30: =IF(OR(W30="○",X30="○",Y30="○",Z30="○",AA30="○"),"면제",$R30) -> 요건탈락
A31: 30 | B31: 20401337 | C31: 2026년도 창업중심대학 지역기반 (예비)창업기업 모집 공고 | D31: 지역기반 | E31: 박미란 | F31: 여 | G31: 1985-01-23 | H31: 중장년 | I31: 53,200,000 | J31: 0 | K31: 햇썹?왓썹! : 식품 위생과 안전을 위한 AI 기반 디지털 전산화 플랫폼 | L31: 경기 | M31: 지식서비스 | N31: 정보ㆍ통신 | O31: 초기 | P31: 정보ㆍ통신7 | Q31: =TODAY() -> 46120 | R31: 0 | S31: 0 | T31: 0 | U31: 0 | V31: =IF(OR(S31="○",T31="○",U31="○"),2,0) -> 0 | W31: 0 | X31: 0 | Y31: 0 | Z31: 0 | AA31: 0 | AB31: =IF(OR(W31="○",X31="○",Y31="○",Z31="○",AA31="○"),"면제",$R31) -> 0
A32: 31 | B32: 20401363 | C32: 2026년도 창업중심대학 지역기반 (예비)창업기업 모집 공고 | D32: 지역기반 | E32: 김양아 | F32: 여 | G32: 1977-01-11 | H32: 중장년 | I32: 537,669,966 | J32: 1 | K32: AI·데이터 기반 K-브랜드 글로벌 진출 통합 플랫폼 (AMAZE GLOBAL INNOVATING SOLUTION) | L32: 서울 | M32: 지식서비스 | N32: 정보ㆍ통신 | O32: 초기 | P32: 정보ㆍ통신7 | Q32: =TODAY() -> 46120 | R32: 0 | S32: 0 | T32: 0 | U32: 0 | V32: =IF(OR(S32="○",T32="○",U32="○"),2,0) -> 0 | W32: 0 | X32: 0 | Y32: 0 | Z32: 0 | AA32: 0 | AB32: =IF(OR(W32="○",X32="○",Y32="○",Z32="○",AA32="○"),"면제",$R32) -> 0
A33: 32 | B33: 20401381 | C33: 2026년도 창업중심대학 지역기반 (예비)창업기업 모집 공고 | D33: 지역기반 | E33: 김영성 | F33: 남 | G33: 1994-04-19 | H33: 청년 | I33: 9,080,000 | J33: 0 | K33: AI SyncBoard[온디바이스 AI 기반 스마트에듀 실시간 양방향 판서솔루션] | L33: 인천 | M33: 지식서비스 | N33: 정보ㆍ통신 | O33: 초기 | P33: 정보ㆍ통신5 | Q33: =TODAY() -> 46120 | R33: 0 | S33: ○ | T33: 0 | U33: 0 | V33: =IF(OR(S33="○",T33="○",U33="○"),2,0) -> 2 | W33: 0 | X33: 0 | Y33: 0 | Z33: 0 | AA33: 0 | AB33: =IF(OR(W33="○",X33="○",Y33="○",Z33="○",AA33="○"),"면제",$R33) -> 0
A34: 33 | B34: 20401390 | C34: 2026년도 창업중심대학 지역기반 (예비)창업기업 모집 공고 | D34: 지역기반 | E34: 한동용 | F34: 남 | G34: 1989-05-29 | H34: 청년 | I34: 436,000,000 | J34: 2 | K34: 서술형 학습데이터 기반 개념 이해 판별 AI 분석엔진(Concept Note Lab) 개발 및 교육기관 확산(B2B SaaS) | L34: 경기 | M34: 지식서비스 | N34: 정보ㆍ통신 | O34: 초기 | P34: 정보ㆍ통신5 | Q34: =TODAY() -> 46120 | R34: 0 | S34: 0 | T34: 0 | U34: 0 | V34: =IF(OR(S34="○",T34="○",U34="○"),2,0) -> 0 | W34: 0 | X34: 0 | Y34: 0 | Z34: 0 | AA34: 0 | AB34: =IF(OR(W34="○",X34="○",Y34="○",Z34="○",AA34="○"),"면제",$R34) -> 0
A35: 34 | B35: 20401396 | C35: 2026년도 창업중심대학 지역기반 (예비)창업기업 모집 공고 | D35: 지역기반 | E35: 장용원 | F35: 남 | G35: 1990-05-19 | H35: 청년 | I35: 30,000,000 | J35: 2 | K35: 제작사 브랜딩 기반 B2C 콘텐츠 제작사 | L35: 경기 | M35: 지식서비스 | N35: 정보ㆍ통신 | O35: 초기 | P35: 정보ㆍ통신6 | Q35: =TODAY() -> 46120 | R35: 0 | S35: 0 | T35: 0 | U35: 0 | V35: =IF(OR(S35="○",T35="○",U35="○"),2,0) -> 0 | W35: 0 | X35: 0 | Y35: 0 | Z35: 0 | AA35: 0 | AB35: =IF(OR(W35="○",X35="○",Y35="○",Z35="○",AA35="○"),"면제",$R35) -> 0
A36: 35 | B36: 20401399 | C36: 2026년도 창업중심대학 지역기반 (예비)창업기업 모집 공고 | D36: 지역기반 | E36: 이진 | F36: 여 | G36: 1993-05-31 | H36: 청년 | I36: 0 | J36: 0 | K36: 당뇨인들을 위한 병아리콩 앙금과 못난이 고구마 기반의 밀가루 없는 고단백·저당 구움과자 | L36: 경기 | M36: 제조 | N36: 에너지ㆍ자원 | O36: 예비 | P36: 에너지ㆍ자원 | Q36: =TODAY() -> 46120 | R36: 0 | S36: 0 | T36: 0 | U36: 0 | V36: =IF(OR(S36="○",T36="○",U36="○"),2,0) -> 0 | W36: 0 | X36: 0 | Y36: 0 | Z36: 0 | AA36: 0 | AB36: =IF(OR(W36="○",X36="○",Y36="○",Z36="○",AA36="○"),"면제",$R36) -> 0
A37: 36 | B37: 20401505 | C37: 2026년도 창업중심대학 지역기반 (예비)창업기업 모집 공고 | D37: 지역기반 | E37: 이장우 | F37: 남 | G37: 1973-08-30 | H37: 중장년 | I37: 0 | J37: 0 | K37: 명당AI | L37: 서울 | M37: 지식서비스 | N37: 정보ㆍ통신 | O37: 예비 | P37: 정보ㆍ통신4 | Q37: =TODAY() -> 46120 | R37: 0 | S37: 0 | T37: 0 | U37: 0 | V37: =IF(OR(S37="○",T37="○",U37="○"),2,0) -> 0 | W37: 0 | X37: 0 | Y37: 0 | Z37: 0 | AA37: 0 | AB37: =IF(OR(W37="○",X37="○",Y37="○",Z37="○",AA37="○"),"면제",$R37) -> 0
A38: 37 | B38: 20401527 | C38: 2026년도 창업중심대학 지역기반 (예비)창업기업 모집 공고 | D38: 지역기반 | E38: 유현욱 | F38: 남 | G38: 1995-02-13 | H38: 청년 | I38: 0 | J38: 0 | K38: 대화가 곧 일기가 되는 자동 라이프로깅 메신저, ‘라타톡(Ratatoc)‘ 상용화 | L38: 경기 | M38: 지식서비스 | N38: 정보ㆍ통신 | O38: 예비 | P38: 정보ㆍ통신6 | Q38: =TODAY() -> 46120 | R38: 0 | S38: 0 | T38: 0 | U38: 0 | V38: =IF(OR(S38="○",T38="○",U38="○"),2,0) -> 0 | W38: 0 | X38: 0 | Y38: 0 | Z38: 0 | AA38: 0 | AB38: =IF(OR(W38="○",X38="○",Y38="○",Z38="○",AA38="○"),"면제",$R38) -> 0
A39: 38 | B39: 20401528 | C39: 2026년도 창업중심대학 지역기반 (예비)창업기업 모집 공고 | D39: 지역기반 | E39: 고태욱 | F39: 남 | G39: 1993-01-05 | H39: 청년 | I39: 0 | J39: 0 | K39: 자율 비행 및 AI 꽃 인식 기술이 적용된 초소형 드론 기반 인공수분 서비스 | L39: 경기 | M39: 제조 | N39: 전기ㆍ전자 | O39: 예비 | P39: 전기ㆍ전자 | Q39: =TODAY() -> 46120 | R39: 0 | S39: 0 | T39: 0 | U39: 0 | V39: =IF(OR(S39="○",T39="○",U39="○"),2,0) -> 0 | W39: 0 | X39: 0 | Y39: 0 | Z39: 0 | AA39: 0 | AB39: =IF(OR(W39="○",X39="○",Y39="○",Z39="○",AA39="○"),"면제",$R39) -> 0
A40: 39 | B40: 20401529 | C40: 2026년도 창업중심대학 지역기반 (예비)창업기업 모집 공고 | D40: 지역기반 | E40: 이수연 | F40: 여 | G40: 1995-07-23 | H40: 청년 | I40: 0 | J40: 0 | K40: AI 패턴 분석 기술이 적용된 게이미피케이션 자기탐색 기능의 (비치료적 자기이해 경험을 제공하는) 나로소 AI 앱 서비스 | L40: 서울 | M40: 지식서비스 | N40: 정보ㆍ통신 | O40: 예비 | P40: 정보ㆍ통신6 | Q40: =TODAY() -> 46120 | R40: 0 | S40: 0 | T40: 0 | U40: 0 | V40: =IF(OR(S40="○",T40="○",U40="○"),2,0) -> 0 | W40: 0 | X40: 0 | Y40: 0 | Z40: 0 | AA40: 0 | AB40: =IF(OR(W40="○",X40="○",Y40="○",Z40="○",AA40="○"),"면제",$R40) -> 0
A41: 40 | B41: 20401574 | C41: 2026년도 창업중심대학 지역기반 (예비)창업기업 모집 공고 | D41: 지역기반 | E41: 정윤경 | F41: 여 | G41: 1971-07-12 | H41: 중장년 | I41: 0 | J41: 3 | K41: 옷장 연결 가구형 빌트인 의류 케어기기 개발 | L41: 서울 | M41: 제조 | N41: 전기ㆍ전자 | O41: 초기 | P41: 전기ㆍ전자 | Q41: =TODAY() -> 46120 | R41: 0 | S41: 0 | T41: 0 | U41: 0 | V41: =IF(OR(S41="○",T41="○",U41="○"),2,0) -> 0 | W41: 0 | X41: 0 | Y41: 0 | Z41: 0 | AA41: 0 | AB41: =IF(OR(W41="○",X41="○",Y41="○",Z41="○",AA41="○"),"면제",$R41) -> 0
A42: 41 | B42: 20401622 | C42: 2026년도 창업중심대학 지역기반 (예비)창업기업 모집 공고 | D42: 지역기반 | E42: 윤동주 | F42: 남 | G42: 1991-08-20 | H42: 청년 | I42: 100,000 | J42: 3 | K42: 공간·소비 빅데이터 기반 외식업 점포개발 시뮬레이션 생성형 AI엔진 '슈바툴' | L42: 경기 | M42: 지식서비스 | N42: 정보ㆍ통신 | O42: 초기 | P42: 정보ㆍ통신3 | Q42: =TODAY() -> 46120 | R42: 0 | S42: 0 | T42: 0 | U42: 0 | V42: =IF(OR(S42="○",T42="○",U42="○"),2,0) -> 0 | W42: 0 | X42: 0 | Y42: 0 | Z42: 0 | AA42: 0 | AB42: =IF(OR(W42="○",X42="○",Y42="○",Z42="○",AA42="○"),"면제",$R42) -> 0
A43: 42 | B43: 20401633 | C43: 2026년도 창업중심대학 지역기반 (예비)창업기업 모집 공고 | D43: 지역기반 | E43: DEGUCHI HANA | F43: 여 | G43: 1995-07-03 | H43: 청년 | I43: 20,000,000 | J43: 2 | K43: 수면 시간을 관리하는 수면 뷰티 솔루션 네루미인 제품 사업화 | L43: 서울 | M43: 제조 | N43: 화공ㆍ섬유 | O43: 도약 | P43: 화공ㆍ섬유 | Q43: =TODAY() -> 46120 | R43: 0 | S43: 0 | T43: 0 | U43: 0 | V43: =IF(OR(S43="○",T43="○",U43="○"),2,0) -> 0 | W43: 0 | X43: 0 | Y43: 0 | Z43: 0 | AA43: 0 | AB43: =IF(OR(W43="○",X43="○",Y43="○",Z43="○",AA43="○"),"면제",$R43) -> 0
A44: 43 | B44: 20401646 | C44: 2026년도 창업중심대학 지역기반 (예비)창업기업 모집 공고 | D44: 지역기반 | E44: 심영화 | F44: 남 | G44: 1997-09-26 | H44: 청년 | I44: 0 | J44: 0 | K44: 생성형 AI 기반 라이프스토리 아카이빙 서비스를 활용한 장례·추모 콘텐츠 제공 솔루션 | L44: 서울 | M44: 제조 | N44: 정보ㆍ통신 | O44: 초기 | P44: 정보ㆍ통신6 | Q44: =TODAY() -> 46120 | R44: 0 | S44: ○ | T44: 0 | U44: 0 | V44: =IF(OR(S44="○",T44="○",U44="○"),2,0) -> 2 | W44: 0 | X44: 0 | Y44: 0 | Z44: 0 | AA44: 0 | AB44: =IF(OR(W44="○",X44="○",Y44="○",Z44="○",AA44="○"),"면제",$R44) -> 0
A45: 44 | B45: 20401665 | C45: 2026년도 창업중심대학 지역기반 (예비)창업기업 모집 공고 | D45: 지역기반 | E45: 강종원 | F45: 남 | G45: 1993-06-22 | H45: 청년 | I45: 1,438,704,000 | J45: 2 | K45: AI 기반 체형분석 맞춤운동 처방 플랫폼(AI BodyMap) 및 하이브리드 체형교정 밴드 | L45: 경기 | M45: 지식서비스 | N45: 정보ㆍ통신 | O45: 초기 | P45: 정보ㆍ통신4 | Q45: =TODAY() -> 46120 | R45: 0 | S45: 0 | T45: 0 | U45: 0 | V45: =IF(OR(S45="○",T45="○",U45="○"),2,0) -> 0 | W45: 0 | X45: 0 | Y45: 0 | Z45: 0 | AA45: 0 | AB45: =IF(OR(W45="○",X45="○",Y45="○",Z45="○",AA45="○"),"면제",$R45) -> 0
A46: 45 | B46: 20401701 | C46: 2026년도 창업중심대학 지역기반 (예비)창업기업 모집 공고 | D46: 지역기반 | E46: 이주희 | F46: 여 | G46: 1989-01-04 | H46: 청년 | I46: 0 | J46: 0 | K46: '이리온 베이비 키트' 및 '이리온B' 어플리케이션 | L46: 경기 | M46: 제조 | N46: 바이오ㆍ의료ㆍ생명 | O46: 예비 | P46: 바이오ㆍ의료ㆍ생명1 | Q46: =TODAY() -> 46120 | R46: 0 | S46: 0 | T46: 0 | U46: 0 | V46: =IF(OR(S46="○",T46="○",U46="○"),2,0) -> 0 | W46: 0 | X46: 0 | Y46: 0 | Z46: 0 | AA46: 0 | AB46: =IF(OR(W46="○",X46="○",Y46="○",Z46="○",AA46="○"),"면제",$R46) -> 0
A47: 46 | B47: 20401706 | C47: 2026년도 창업중심대학 지역기반 (예비)창업기업 모집 공고 | D47: 지역기반 | E47: 최승훈 | F47: 남 | G47: 1991-08-03 | H47: 청년 | I47: 599,403,796 | J47: 3 | K47: 생성형 AI 기반 초개인화 가상 피팅 솔루션 '롤링스튜디오 모션 핏' | L47: 서울 | M47: 지식서비스 | N47: 정보ㆍ통신 | O47: 도약 | P47: 정보ㆍ통신2 | Q47: =TODAY() -> 46120 | R47: 0 | S47: 0 | T47: 0 | U47: 0 | V47: =IF(OR(S47="○",T47="○",U47="○"),2,0) -> 0 | W47: 0 | X47: 0 | Y47: 0 | Z47: 0 | AA47: 0 | AB47: =IF(OR(W47="○",X47="○",Y47="○",Z47="○",AA47="○"),"면제",$R47) -> 0
A48: 47 | B48: 20401711 | C48: 2026년도 창업중심대학 지역기반 (예비)창업기업 모집 공고 | D48: 지역기반 | E48: 성문주 | F48: 여 | G48: 1983-02-28 | H48: 중장년 | I48: 0 | J48: 1 | K48: AI기술이 적용된 서비스 플랫폼 기능의 온라인 커뮤니티 /온라인 건강기능식품 셀렉트샵 원스톱 쇼핑서비스 | L48: 경기 | M48: 지식서비스 | N48: 정보ㆍ통신 | O48: 초기 | P48: 정보ㆍ통신1 | Q48: =TODAY() -> 46120 | R48: 0 | S48: 0 | T48: 0 | U48: 0 | V48: =IF(OR(S48="○",T48="○",U48="○"),2,0) -> 0 | W48: 0 | X48: 0 | Y48: 0 | Z48: 0 | AA48: 0 | AB48: =IF(OR(W48="○",X48="○",Y48="○",Z48="○",AA48="○"),"면제",$R48) -> 0
A49: 48 | B49: 20401725 | C49: 2026년도 창업중심대학 지역기반 (예비)창업기업 모집 공고 | D49: 지역기반 | E49: 송진욱 | F49: 남 | G49: 1983-02-06 | H49: 중장년 | I49: 42,000,000 | J49: 0 | K49: 멀티모달·RAG 기반 초개인화 뷰티 AI, 'Dermo-Brain' | L49: 경기 | M49: 지식서비스 | N49: 정보ㆍ통신 | O49: 도약 | P49: 정보ㆍ통신1 | Q49: =TODAY() -> 46120 | R49: 0 | S49: 0 | T49: 0 | U49: 0 | V49: =IF(OR(S49="○",T49="○",U49="○"),2,0) -> 0 | W49: 0 | X49: 0 | Y49: 0 | Z49: 0 | AA49: 0 | AB49: =IF(OR(W49="○",X49="○",Y49="○",Z49="○",AA49="○"),"면제",$R49) -> 0
A50: 49 | B50: 20401736 | C50: 2026년도 창업중심대학 지역기반 (예비)창업기업 모집 공고 | D50: 지역기반 | E50: 이인성 | F50: 남 | G50: 1973-01-21 | H50: 중장년 | I50: 17,922,727 | J50: 0 | K50: 자동화장비(FA) 설계 생산성 50% 향상을 위한 AI 기계원리 콘텐츠 앱스토어 (업무자동화를 위한 RPA앱과 AI 설계학습 콘텐츠가 통합 유통되는 플랫폼) | L50: 경기 | M50: 지식서비스 | N50: 정보ㆍ통신 | O50: 초기 | P50: 정보ㆍ통신4 | Q50: =TODAY() -> 46120 | R50: 0 | S50: 0 | T50: 0 | U50: 0 | V50: =IF(OR(S50="○",T50="○",U50="○"),2,0) -> 0 | W50: 0 | X50: 0 | Y50: 0 | Z50: 0 | AA50: 0 | AB50: =IF(OR(W50="○",X50="○",Y50="○",Z50="○",AA50="○"),"면제",$R50) -> 0
A51: 50 | B51: 20401777 | C51: 2026년도 창업중심대학 지역기반 (예비)창업기업 모집 공고 | D51: 지역기반 | E51: 최지호 | F51: 여 | G51: 1999-02-07 | H51: 청년 | I51: 0 | J51: 0 | K51: 천연 저자극·항균·진정 스킨케어 (904m 해양 광천수 기반) | L51: 서울 | M51: 제조 | N51: 바이오ㆍ의료ㆍ생명 | O51: 예비 | P51: 바이오ㆍ의료ㆍ생명2 | Q51: =TODAY() -> 46120 | R51: 0 | S51: 0 | T51: 0 | U51: 0 | V51: =IF(OR(S51="○",T51="○",U51="○"),2,0) -> 0 | W51: 0 | X51: 0 | Y51: 0 | Z51: 0 | AA51: 0 | AB51: =IF(OR(W51="○",X51="○",Y51="○",Z51="○",AA51="○"),"면제",$R51) -> 0
A52: 51 | B52: 20401779 | C52: 2026년도 창업중심대학 지역기반 (예비)창업기업 모집 공고 | D52: 지역기반 | E52: 김병만 | F52: 남 | G52: 1977-08-30 | H52: 중장년 | I52: 208,378,702 | J52: 0 | K52: 안자극이 없는 수경 안티포그액 | L52: 경기 | M52: 제조 | N52: 화공ㆍ섬유 | O52: 초기 | P52: 화공ㆍ섬유 | Q52: =TODAY() -> 46120 | R52: 0 | S52: 0 | T52: 0 | U52: 0 | V52: =IF(OR(S52="○",T52="○",U52="○"),2,0) -> 0 | W52: 0 | X52: 0 | Y52: 0 | Z52: 0 | AA52: 0 | AB52: =IF(OR(W52="○",X52="○",Y52="○",Z52="○",AA52="○"),"면제",$R52) -> 0
A53: 52 | B53: 20401786 | C53: 2026년도 창업중심대학 지역기반 (예비)창업기업 모집 공고 | D53: 지역기반 | E53: 김우종 | F53: 남 | G53: 1970-02-10 | H53: 중장년 | I53: 0 | J53: 1 | K53: 머신비전 전용 데이터합성플랫폼 개발 | L53: 경기 | M53: 제조 | N53: 정보ㆍ통신 | O53: 초기 | P53: 정보ㆍ통신3 | Q53: =TODAY() -> 46120 | R53: 0 | S53: 0 | T53: 0 | U53: 0 | V53: =IF(OR(S53="○",T53="○",U53="○"),2,0) -> 0 | W53: 0 | X53: 0 | Y53: 0 | Z53: 0 | AA53: 0 | AB53: =IF(OR(W53="○",X53="○",Y53="○",Z53="○",AA53="○"),"면제",$R53) -> 0
A54: 53 | B54: 20401839 | C54: 2026년도 창업중심대학 지역기반 (예비)창업기업 모집 공고 | D54: 지역기반 | E54: 오승현 | F54: 남 | G54: 1989-09-07 | H54: 청년 | I54: 1,240,000,000 | J54: 4 | K54: AI기반 장기렌트카 계약 의사결정 및 중개 플랫폼 : 카즘(Carzm) | L54: 서울 | M54: 지식서비스 | N54: 정보ㆍ통신 | O54: 초기 | P54: 정보ㆍ통신4 | Q54: =TODAY() -> 46120 | R54: 0 | S54: 0 | T54: 0 | U54: 0 | V54: =IF(OR(S54="○",T54="○",U54="○"),2,0) -> 0 | W54: 0 | X54: 0 | Y54: 0 | Z54: 0 | AA54: 0 | AB54: =IF(OR(W54="○",X54="○",Y54="○",Z54="○",AA54="○"),"면제",$R54) -> 0
A55: 54 | B55: 20401903 | C55: 2026년도 창업중심대학 지역기반 (예비)창업기업 모집 공고 | D55: 지역기반 | E55: 김마지 | F55: 여 | G55: 1979-07-10 | H55: 중장년 | I55: 0 | J55: 0 | K55: 반복구매/리텐션 CRM 자동화 기술 적용된 주간 식생활 운영형 공동구매 서비스 개발 | L55: 경기 | M55: 지식서비스 | N55: 정보ㆍ통신 | O55: 예비 | P55: 정보ㆍ통신3 | Q55: =TODAY() -> 46120 | R55: 0 | S55: 0 | T55: 0 | U55: 0 | V55: =IF(OR(S55="○",T55="○",U55="○"),2,0) -> 0 | W55: 0 | X55: 0 | Y55: 0 | Z55: 0 | AA55: 0 | AB55: =IF(OR(W55="○",X55="○",Y55="○",Z55="○",AA55="○"),"면제",$R55) -> 0
A56: 55 | B56: 20401974 | C56: 2026년도 창업중심대학 지역기반 (예비)창업기업 모집 공고 | D56: 지역기반 | E56: 권령진 | F56: 여 | G56: 1993-04-28 | H56: 청년 | I56: 0 | J56: 0 | K56: 2030 저당식품 소비자를 위한 AI 성분 분석을 통해 숨은당을 검출·등급화하는 푸드테크 식품 신뢰 플랫폼 노잇 | L56: 경기 | M56: 지식서비스 | N56: 정보ㆍ통신 | O56: 예비 | P56: 정보ㆍ통신1 | Q56: =TODAY() -> 46120 | R56: 0 | S56: 0 | T56: 0 | U56: 0 | V56: =IF(OR(S56="○",T56="○",U56="○"),2,0) -> 0 | W56: 0 | X56: 0 | Y56: 0 | Z56: 0 | AA56: 0 | AB56: =IF(OR(W56="○",X56="○",Y56="○",Z56="○",AA56="○"),"면제",$R56) -> 0
A57: 56 | B57: 20401993 | C57: 2026년도 창업중심대학 지역기반 (예비)창업기업 모집 공고 | D57: 지역기반 | E57: 이준호 | F57: 남 | G57: 1995-12-09 | H57: 청년 | I57: 1,200,000,000 | J57: 7 | K57: AI 기반 운동 지속 최적화 스포츠·웰니스 보조 기능 식품 브랜드, “레드뉴트리션” | L57: 경기 | M57: 제조 | N57: 바이오ㆍ의료ㆍ생명 | O57: 초기 | P57: 바이오ㆍ의료ㆍ생명1 | Q57: =TODAY() -> 46120 | R57: 0 | S57: 0 | T57: 0 | U57: 0 | V57: =IF(OR(S57="○",T57="○",U57="○"),2,0) -> 0 | W57: 0 | X57: 0 | Y57: 0 | Z57: 0 | AA57: 0 | AB57: =IF(OR(W57="○",X57="○",Y57="○",Z57="○",AA57="○"),"면제",$R57) -> 0
A58: 57 | B58: 20402033 | C58: 2026년도 창업중심대학 지역기반 (예비)창업기업 모집 공고 | D58: 지역기반 | E58: 박재민 | F58: 남 | G58: 1994-05-19 | H58: 청년 | I58: 0 | J58: 0 | K58: 케어큐브 ( 다직군 Gig Economy 인력 매칭·관리 AI 기반 SW 플랫폼 ) | L58: 서울 | M58: 지식서비스 | N58: 정보ㆍ통신 | O58: 예비 | P58: 정보ㆍ통신6 | Q58: =TODAY() -> 46120 | R58: 0 | S58: ○ | T58: 0 | U58: 0 | V58: =IF(OR(S58="○",T58="○",U58="○"),2,0) -> 2 | W58: 0 | X58: 0 | Y58: 0 | Z58: 0 | AA58: 0 | AB58: =IF(OR(W58="○",X58="○",Y58="○",Z58="○",AA58="○"),"면제",$R58) -> 0
A59: 58 | B59: 20402057 | C59: 2026년도 창업중심대학 지역기반 (예비)창업기업 모집 공고 | D59: 지역기반 | E59: 신근철 | F59: 남 | G59: 1981-01-16 | H59: 중장년 | I59: 0 | J59: 0 | K59: CODEBI 러닝·퍼포먼스 기능성 의류 (쇼츠, 상의, 타이즈, 액세서리) | L59: 경기 | M59: 제조 | N59: 화공ㆍ섬유 | O59: 예비 | P59: 화공ㆍ섬유 | Q59: =TODAY() -> 46120 | R59: 0 | S59: 0 | T59: 0 | U59: 0 | V59: =IF(OR(S59="○",T59="○",U59="○"),2,0) -> 0 | W59: 0 | X59: 0 | Y59: 0 | Z59: 0 | AA59: 0 | AB59: =IF(OR(W59="○",X59="○",Y59="○",Z59="○",AA59="○"),"면제",$R59) -> 0
A60: 59 | B60: 20402074 | C60: 2026년도 창업중심대학 지역기반 (예비)창업기업 모집 공고 | D60: 지역기반 | E60: 안재근 | F60: 남 | G60: 1988-10-27 | H60: 청년 | I60: 21,851,200 | J60: 4 | K60: AI/AR 공간 데이터 및 K-셀럽 스타일 데이터 기반 초개인화 K-Funiture 맞춤제작 및 글로벌 수출 플랫폼 개발 | L60: 경기 | M60: 제조 | N60: 정보ㆍ통신 | O60: 초기 | P60: 정보ㆍ통신6 | Q60: =TODAY() -> 46120 | R60: 0 | S60: 0 | T60: 0 | U60: 0 | V60: =IF(OR(S60="○",T60="○",U60="○"),2,0) -> 0 | W60: 0 | X60: 0 | Y60: 0 | Z60: 0 | AA60: 0 | AB60: =IF(OR(W60="○",X60="○",Y60="○",Z60="○",AA60="○"),"면제",$R60) -> 0
A61: 60 | B61: 20402078 | C61: 2026년도 창업중심대학 지역기반 (예비)창업기업 모집 공고 | D61: 지역기반 | E61: 이윤진 | F61: 여 | G61: 1992-01-23 | H61: 청년 | I61: 128,835,710 | J61: 2 | K61: [글로벌 타겟] AI 톤적응 마이크로캡슐 기반 스킨케어형 컬러체인지 커버선크림 개발 및 사업화 | L61: 경기 | M61: 제조 | N61: 화공ㆍ섬유 | O61: 초기 | P61: 화공ㆍ섬유 | Q61: =TODAY() -> 46120 | R61: 0 | S61: ○ | T61: 0 | U61: 0 | V61: =IF(OR(S61="○",T61="○",U61="○"),2,0) -> 2 | W61: 0 | X61: 0 | Y61: 0 | Z61: 0 | AA61: 0 | AB61: =IF(OR(W61="○",X61="○",Y61="○",Z61="○",AA61="○"),"면제",$R61) -> 0
A62: 61 | B62: 20402125 | C62: 2026년도 창업중심대학 지역기반 (예비)창업기업 모집 공고 | D62: 지역기반 | E62: 최희범 | F62: 남 | G62: 1992-01-10 | H62: 청년 | I62: 0 | J62: 0 | K62: 한국 전통 도자기 기반 프리미엄 위스키 인퓨저 ‘LUCE’ 개발 및 글로벌 홈바 시장 진출 | L62: 경기 | M62: 제조 | N62: 공예ㆍ디자인 | O62: 초기 | P62: 공예ㆍ디자인 | Q62: =TODAY() -> 46120 | R62: 0 | S62: 0 | T62: 0 | U62: 0 | V62: =IF(OR(S62="○",T62="○",U62="○"),2,0) -> 0 | W62: 0 | X62: 0 | Y62: 0 | Z62: 0 | AA62: 0 | AB62: =IF(OR(W62="○",X62="○",Y62="○",Z62="○",AA62="○"),"면제",$R62) -> 0
A63: 62 | B63: 20402134 | C63: 2026년도 창업중심대학 지역기반 (예비)창업기업 모집 공고 | D63: 지역기반 | E63: 김은혜 | F63: 여 | G63: 1987-03-10 | H63: 청년 | I63: 0 | J63: 0 | K63: AI로 부모목소리를 학습하여 자장가와 동화를 들려주는 오디오 앱 | L63: 서울 | M63: 지식서비스 | N63: 정보ㆍ통신 | O63: 예비 | P63: 정보ㆍ통신7 | Q63: =TODAY() -> 46120 | R63: 0 | S63: 0 | T63: 0 | U63: 0 | V63: =IF(OR(S63="○",T63="○",U63="○"),2,0) -> 0 | W63: 0 | X63: 0 | Y63: 0 | Z63: 0 | AA63: 0 | AB63: =IF(OR(W63="○",X63="○",Y63="○",Z63="○",AA63="○"),"면제",$R63) -> 0
A64: 63 | B64: 20402149 | C64: 2026년도 창업중심대학 지역기반 (예비)창업기업 모집 공고 | D64: 지역기반 | E64: 김한솔 | F64: 여 | G64: 1994-02-25 | H64: 청년 | I64: 0 | J64: 0 | K64: 차량 하부 공조 결합형 향·탈취 관리 제품 | L64: 인천 | M64: 제조 | N64: 공예ㆍ디자인 | O64: 예비 | P64: 공예ㆍ디자인 | Q64: =TODAY() -> 46120 | R64: 요건탈락 | S64: 0 | T64: 0 | U64: 0 | V64: =IF(OR(S64="○",T64="○",U64="○"),2,0) -> 0 | W64: 0 | X64: 0 | Y64: 0 | Z64: 0 | AA64: 0 | AB64: =IF(OR(W64="○",X64="○",Y64="○",Z64="○",AA64="○"),"면제",$R64) -> 요건탈락
A65: 64 | B65: 20402154 | C65: 2026년도 창업중심대학 지역기반 (예비)창업기업 모집 공고 | D65: 지역기반 | E65: 안우철 | F65: 남 | G65: 1976-01-17 | H65: 중장년 | I65: 54,725,977 | J65: 2 | K65: AI 기반 실물자산 생애주기 최적화 기술이 적용된 수익형 내구소비재 자유대여 플랫폼, ZELO | L65: 서울 | M65: 지식서비스 | N65: 정보ㆍ통신 | O65: 도약 | P65: 정보ㆍ통신7 | Q65: =TODAY() -> 46120 | R65: 0 | S65: 0 | T65: 0 | U65: 0 | V65: =IF(OR(S65="○",T65="○",U65="○"),2,0) -> 0 | W65: 0 | X65: 0 | Y65: 0 | Z65: 0 | AA65: 0 | AB65: =IF(OR(W65="○",X65="○",Y65="○",Z65="○",AA65="○"),"면제",$R65) -> 0
A66: 65 | B66: 20402196 | C66: 2026년도 창업중심대학 지역기반 (예비)창업기업 모집 공고 | D66: 지역기반 | E66: 조영민 | F66: 남 | G66: 1974-04-03 | H66: 중장년 | I66: 0 | J66: 0 | K66: 차세대 반도체 패키징용 40um 이하 건식 마이크로 범프 형성 기술, 특허 번호 10-2025-00188250) | L66: 경기 | M66: 제조 | N66: 기계ㆍ소재 | O66: 예비 | P66: 기계ㆍ소재 | Q66: =TODAY() -> 46120 | R66: 0 | S66: 0 | T66: 0 | U66: 0 | V66: =IF(OR(S66="○",T66="○",U66="○"),2,0) -> 0 | W66: 0 | X66: 0 | Y66: 0 | Z66: 0 | AA66: 0 | AB66: =IF(OR(W66="○",X66="○",Y66="○",Z66="○",AA66="○"),"면제",$R66) -> 0
A67: 66 | B67: 20402204 | C67: 2026년도 창업중심대학 지역기반 (예비)창업기업 모집 공고 | D67: 지역기반 | E67: 정다솔 | F67: 여 | G67: 1995-03-14 | H67: 청년 | I67: 0 | J67: 0 | K67: 영아 부모를 위한 기질 기반 전문가·AI 하이브리드 양육 코칭 서비스 | L67: 서울 | M67: 지식서비스 | N67: 정보ㆍ통신 | O67: 예비 | P67: 정보ㆍ통신7 | Q67: =TODAY() -> 46120 | R67: 0 | S67: ○ | T67: 0 | U67: 0 | V67: =IF(OR(S67="○",T67="○",U67="○"),2,0) -> 2 | W67: 0 | X67: 0 | Y67: 0 | Z67: 0 | AA67: 0 | AB67: =IF(OR(W67="○",X67="○",Y67="○",Z67="○",AA67="○"),"면제",$R67) -> 0
A68: 67 | B68: 20402217 | C68: 2026년도 창업중심대학 지역기반 (예비)창업기업 모집 공고 | D68: 지역기반 | E68: 박성훈 | F68: 남 | G68: 1976-12-13 | H68: 중장년 | I68: 254,707,012 | J68: 6 | K68: 삼육대학교 앱북 플랫폼(SU Libaray) | L68: 서울 | M68: 지식서비스 | N68: 정보ㆍ통신 | O68: 도약 | P68: 정보ㆍ통신3 | Q68: =TODAY() -> 46120 | R68: 0 | S68: 0 | T68: 0 | U68: 0 | V68: =IF(OR(S68="○",T68="○",U68="○"),2,0) -> 0 | W68: 0 | X68: 0 | Y68: 0 | Z68: 0 | AA68: 0 | AB68: =IF(OR(W68="○",X68="○",Y68="○",Z68="○",AA68="○"),"면제",$R68) -> 0
A69: 68 | B69: 20402232 | C69: 2026년도 창업중심대학 지역기반 (예비)창업기업 모집 공고 | D69: 지역기반 | E69: 이강돈 | F69: 남 | G69: 1971-09-22 | H69: 중장년 | I69: 132,422,727 | J69: 2 | K69: 특허 기반 대한민국 가족의 디지털 안심 지킴이 ‘디펜스넷(DefenseNet)' | L69: 경기 | M69: 제조 | N69: 정보ㆍ통신 | O69: 초기 | P69: 정보ㆍ통신4 | Q69: =TODAY() -> 46120 | R69: 0 | S69: 0 | T69: 0 | U69: 0 | V69: =IF(OR(S69="○",T69="○",U69="○"),2,0) -> 0 | W69: 0 | X69: 0 | Y69: 0 | Z69: 0 | AA69: 0 | AB69: =IF(OR(W69="○",X69="○",Y69="○",Z69="○",AA69="○"),"면제",$R69) -> 0
A70: 69 | B70: 20402243 | C70: 2026년도 창업중심대학 지역기반 (예비)창업기업 모집 공고 | D70: 지역기반 | E70: 장근복 | F70: 남 | G70: 1964-10-24 | H70: 중장년 | I70: 0 | J70: 0 | K70: FIRE-ZERO 무화염 전기 가열식 금속 배관 접합 솔루션 (히트리 + 히트링) | L70: 경기 | M70: 제조 | N70: 기계ㆍ소재 | O70: 예비 | P70: 기계ㆍ소재 | Q70: =TODAY() -> 46120 | R70: 0 | S70: 0 | T70: 0 | U70: 0 | V70: =IF(OR(S70="○",T70="○",U70="○"),2,0) -> 0 | W70: 0 | X70: 0 | Y70: 0 | Z70: 0 | AA70: 0 | AB70: =IF(OR(W70="○",X70="○",Y70="○",Z70="○",AA70="○"),"면제",$R70) -> 0
A71: 70 | B71: 20402470 | C71: 2026년도 창업중심대학 지역기반 (예비)창업기업 모집 공고 | D71: 지역기반 | E71: 정재영 | F71: 남 | G71: 1991-01-02 | H71: 청년 | I71: 242,437,000 | J71: 1 | K71: 피지컬 AI 제어 적용 물류 공정 최적화 가변 테이핑 시스템 | L71: 경기 | M71: 제조 | N71: 기계ㆍ소재 | O71: 초기 | P71: 기계ㆍ소재 | Q71: =TODAY() -> 46120 | R71: 0 | S71: 0 | T71: 0 | U71: 0 | V71: =IF(OR(S71="○",T71="○",U71="○"),2,0) -> 0 | W71: 0 | X71: 0 | Y71: 0 | Z71: 0 | AA71: 0 | AB71: =IF(OR(W71="○",X71="○",Y71="○",Z71="○",AA71="○"),"면제",$R71) -> 0
A72: 71 | B72: 20402492 | C72: 2026년도 창업중심대학 지역기반 (예비)창업기업 모집 공고 | D72: 지역기반 | E72: 이혜민 | F72: 여 | G72: 1996-09-09 | H72: 청년 | I72: 0 | J72: 0 | K72: 굿퀘스천 | L72: 서울 | M72: 지식서비스 | N72: 정보ㆍ통신 | O72: 예비 | P72: 정보ㆍ통신2 | Q72: =TODAY() -> 46120 | R72: 0 | S72: 0 | T72: 0 | U72: 0 | V72: =IF(OR(S72="○",T72="○",U72="○"),2,0) -> 0 | W72: 0 | X72: 0 | Y72: 0 | Z72: 0 | AA72: 0 | AB72: =IF(OR(W72="○",X72="○",Y72="○",Z72="○",AA72="○"),"면제",$R72) -> 0
A73: 72 | B73: 20402600 | C73: 2026년도 창업중심대학 지역기반 (예비)창업기업 모집 공고 | D73: 지역기반 | E73: 안세호 | F73: 남 | G73: 1984-10-22 | H73: 중장년 | I73: 1,000,000 | J73: 1 | K73: 인공지능 대화분석 기술을 활용한 양육자-아이 맞춤형 육아 코칭 솔루션 개발 | L73: 서울 | M73: 지식서비스 | N73: 정보ㆍ통신 | O73: 초기 | P73: 정보ㆍ통신6 | Q73: =TODAY() -> 46120 | R73: 0 | S73: 0 | T73: 0 | U73: 0 | V73: =IF(OR(S73="○",T73="○",U73="○"),2,0) -> 0 | W73: 0 | X73: 0 | Y73: 0 | Z73: 0 | AA73: 0 | AB73: =IF(OR(W73="○",X73="○",Y73="○",Z73="○",AA73="○"),"면제",$R73) -> 0
A74: 73 | B74: 20402604 | C74: 2026년도 창업중심대학 지역기반 (예비)창업기업 모집 공고 | D74: 지역기반 | E74: 권재성 | F74: 남 | G74: 1996-11-01 | H74: 청년 | I74: 117,757,497 | J74: 3 | K74: 360AI | L74: 서울 | M74: 지식서비스 | N74: 정보ㆍ통신 | O74: 도약 | P74: 정보ㆍ통신2 | Q74: =TODAY() -> 46120 | R74: 0 | S74: 0 | T74: 0 | U74: 0 | V74: =IF(OR(S74="○",T74="○",U74="○"),2,0) -> 0 | W74: 0 | X74: 0 | Y74: 0 | Z74: 0 | AA74: 0 | AB74: =IF(OR(W74="○",X74="○",Y74="○",Z74="○",AA74="○"),"면제",$R74) -> 0
A75: 74 | B75: 20402837 | C75: 2026년도 창업중심대학 지역기반 (예비)창업기업 모집 공고 | D75: 지역기반 | E75: 박상현 | F75: 남 | G75: 1993-01-19 | H75: 청년 | I75: 0 | J75: 0 | K75: 1,024만 시니어(만 65세 이상)를 위한 라이프(병원 동행, 스마트 디바이스 학습 등)개선 어플리케이션 | L75: 서울 | M75: 지식서비스 | N75: 정보ㆍ통신 | O75: 예비 | P75: 정보ㆍ통신3 | Q75: =TODAY() -> 46120 | R75: 0 | S75: 0 | T75: 0 | U75: 0 | V75: =IF(OR(S75="○",T75="○",U75="○"),2,0) -> 0 | W75: 0 | X75: 0 | Y75: 0 | Z75: 0 | AA75: 0 | AB75: =IF(OR(W75="○",X75="○",Y75="○",Z75="○",AA75="○"),"면제",$R75) -> 0
A76: 75 | B76: 20402840 | C76: 2026년도 창업중심대학 지역기반 (예비)창업기업 모집 공고 | D76: 지역기반 | E76: 윤상현 | F76: 남 | G76: 1988-12-01 | H76: 청년 | I76: 0 | J76: 0 | K76: 유소년 스포츠선수 AI·데이터 융합 식물성 단백질 에이전트 푸드테크 솔루션 | L76: 경기 | M76: 제조 | N76: 바이오ㆍ의료ㆍ생명 | O76: 예비 | P76: 바이오ㆍ의료ㆍ생명2 | Q76: =TODAY() -> 46120 | R76: 0 | S76: ○ | T76: 0 | U76: 0 | V76: =IF(OR(S76="○",T76="○",U76="○"),2,0) -> 2 | W76: 0 | X76: 0 | Y76: 0 | Z76: 0 | AA76: 0 | AB76: =IF(OR(W76="○",X76="○",Y76="○",Z76="○",AA76="○"),"면제",$R76) -> 0
A77: 76 | B77: 20402979 | C77: 2026년도 창업중심대학 지역기반 (예비)창업기업 모집 공고 | D77: 지역기반 | E77: 안미연 | F77: 여 | G77: 1993-08-13 | H77: 청년 | I77: 279,333,285 | J77: 2 | K77: 광학조건 최적화·AI 불량검출 통합 비전검사 패키지 | L77: 경기 | M77: 제조 | N77: 기계ㆍ소재 | O77: 초기 | P77: 기계ㆍ소재 | Q77: =TODAY() -> 46120 | R77: 0 | S77: 0 | T77: 0 | U77: 0 | V77: =IF(OR(S77="○",T77="○",U77="○"),2,0) -> 0 | W77: 0 | X77: 0 | Y77: 0 | Z77: 0 | AA77: 0 | AB77: =IF(OR(W77="○",X77="○",Y77="○",Z77="○",AA77="○"),"면제",$R77) -> 0
A78: 77 | B78: 20403109 | C78: 2026년도 창업중심대학 지역기반 (예비)창업기업 모집 공고 | D78: 지역기반 | E78: 최상은 | F78: 여 | G78: 1993-08-21 | H78: 청년 | I78: 360,000,000 | J78: 4 | K78: 2026년도 창업중심대학 지역기반 (예비)창업기업 모집 공고 | L78: 인천 | M78: 제조 | N78: 바이오ㆍ의료ㆍ생명 | O78: 초기 | P78: 바이오ㆍ의료ㆍ생명2 | Q78: =TODAY() -> 46120 | R78: 0 | S78: 0 | T78: 0 | U78: 0 | V78: =IF(OR(S78="○",T78="○",U78="○"),2,0) -> 0 | W78: 0 | X78: 0 | Y78: 0 | Z78: 0 | AA78: 0 | AB78: =IF(OR(W78="○",X78="○",Y78="○",Z78="○",AA78="○"),"면제",$R78) -> 0
A79: 78 | B79: 20403115 | C79: 2026년도 창업중심대학 지역기반 (예비)창업기업 모집 공고 | D79: 지역기반 | E79: 김진찬 | F79: 남 | G79: 1979-08-15 | H79: 중장년 | I79: 0 | J79: 0 | K79: Tarotva (타로바) | L79: 경기 | M79: 지식서비스 | N79: 정보ㆍ통신 | O79: 초기 | P79: 정보ㆍ통신7 | Q79: =TODAY() -> 46120 | R79: 0 | S79: 0 | T79: 0 | U79: 0 | V79: =IF(OR(S79="○",T79="○",U79="○"),2,0) -> 0 | W79: 0 | X79: 0 | Y79: 0 | Z79: 0 | AA79: 0 | AB79: =IF(OR(W79="○",X79="○",Y79="○",Z79="○",AA79="○"),"면제",$R79) -> 0
A80: 79 | B80: 20403159 | C80: 2026년도 창업중심대학 지역기반 (예비)창업기업 모집 공고 | D80: 지역기반 | E80: 채유정 | F80: 여 | G80: 1997-12-27 | H80: 청년 | I80: 328,000,000 | J80: 2 | K80: 저당 식물성 바인딩 기술 기반 당알코올 프리 스피루리나 그래놀라 바 개발 및 사업화 | L80: 인천 | M80: 제조 | N80: 바이오ㆍ의료ㆍ생명 | O80: 초기 | P80: 바이오ㆍ의료ㆍ생명1 | Q80: =TODAY() -> 46120 | R80: 0 | S80: 0 | T80: 0 | U80: 0 | V80: =IF(OR(S80="○",T80="○",U80="○"),2,0) -> 0 | W80: 0 | X80: 0 | Y80: 0 | Z80: 0 | AA80: 0 | AB80: =IF(OR(W80="○",X80="○",Y80="○",Z80="○",AA80="○"),"면제",$R80) -> 0
A81: 80 | B81: 20403168 | C81: 2026년도 창업중심대학 지역기반 (예비)창업기업 모집 공고 | D81: 지역기반 | E81: 김소연 | F81: 여 | G81: 2002-07-28 | H81: 청년 | I81: 0 | J81: 0 | K81: 아빠가 놀이를 통해 아이의 발달을 관찰·이해하도록 돕는 육아 솔루션 | L81: 서울 | M81: 제조 | N81: 정보ㆍ통신 | O81: 예비 | P81: 정보ㆍ통신6 | Q81: =TODAY() -> 46120 | R81: 0 | S81: 0 | T81: 0 | U81: 0 | V81: =IF(OR(S81="○",T81="○",U81="○"),2,0) -> 0 | W81: 0 | X81: 0 | Y81: 0 | Z81: 0 | AA81: 0 | AB81: =IF(OR(W81="○",X81="○",Y81="○",Z81="○",AA81="○"),"면제",$R81) -> 0
A82: 81 | B82: 20403257 | C82: 2026년도 창업중심대학 지역기반 (예비)창업기업 모집 공고 | D82: 지역기반 | E82: 황의성 | F82: 남 | G82: 1978-02-23 | H82: 중장년 | I82: 443,454,546 | J82: 2 | K82: 환경 오염 90% 저감형 모듈러 공법 및 스마트 계측 기술이 적용된 고강도 내진 복합말뚝 (K-PILE) | L82: 서울 | M82: 제조 | N82: 기계ㆍ소재 | O82: 도약 | P82: 기계ㆍ소재 | Q82: =TODAY() -> 46120 | R82: 0 | S82: 0 | T82: 0 | U82: 0 | V82: =IF(OR(S82="○",T82="○",U82="○"),2,0) -> 0 | W82: 0 | X82: 0 | Y82: 0 | Z82: 0 | AA82: 0 | AB82: =IF(OR(W82="○",X82="○",Y82="○",Z82="○",AA82="○"),"면제",$R82) -> 0
A83: 82 | B83: 20403260 | C83: 2026년도 창업중심대학 지역기반 (예비)창업기업 모집 공고 | D83: 지역기반 | E83: 이정훈 | F83: 남 | G83: 1996-03-31 | H83: 청년 | I83: 2,506,260,588 | J83: 4 | K83: 항공 이동 환경 구조 설계 기술이 적용된 반려동물 이동 안전 솔루션 | L83: 경기 | M83: 제조 | N83: 기계ㆍ소재 | O83: 도약 | P83: 기계ㆍ소재 | Q83: =TODAY() -> 46120 | R83: 0 | S83: 0 | T83: 0 | U83: 0 | V83: =IF(OR(S83="○",T83="○",U83="○"),2,0) -> 0 | W83: 0 | X83: 0 | Y83: 0 | Z83: 0 | AA83: 0 | AB83: =IF(OR(W83="○",X83="○",Y83="○",Z83="○",AA83="○"),"면제",$R83) -> 0
A84: 83 | B84: 20403285 | C84: 2026년도 창업중심대학 지역기반 (예비)창업기업 모집 공고 | D84: 지역기반 | E84: 김성훈 | F84: 남 | G84: 1977-05-19 | H84: 중장년 | I84: 0 | J84: 0 | K84: 뽀로로와 영어로 놀아요 | L84: 서울 | M84: 제조 | N84: 정보ㆍ통신 | O84: 초기 | P84: 정보ㆍ통신6 | Q84: =TODAY() -> 46120 | R84: 0 | S84: 0 | T84: 0 | U84: 0 | V84: =IF(OR(S84="○",T84="○",U84="○"),2,0) -> 0 | W84: 0 | X84: 0 | Y84: 0 | Z84: 0 | AA84: 0 | AB84: =IF(OR(W84="○",X84="○",Y84="○",Z84="○",AA84="○"),"면제",$R84) -> 0
A85: 84 | B85: 20403298 | C85: 2026년도 창업중심대학 지역기반 (예비)창업기업 모집 공고 | D85: 지역기반 | E85: 이준서 | F85: 남 | G85: 1968-01-09 | H85: 중장년 | I85: 9,000,000 | J85: 1 | K85: 정부지원사업 신청서 작성 지원 서비스 ‘GF-Link&quot; | L85: 서울 | M85: 지식서비스 | N85: 정보ㆍ통신 | O85: 초기 | P85: 정보ㆍ통신6 | Q85: =TODAY() -> 46120 | R85: 0 | S85: 0 | T85: 0 | U85: 0 | V85: =IF(OR(S85="○",T85="○",U85="○"),2,0) -> 0 | W85: 0 | X85: 0 | Y85: 0 | Z85: 0 | AA85: 0 | AB85: =IF(OR(W85="○",X85="○",Y85="○",Z85="○",AA85="○"),"면제",$R85) -> 0
A86: 85 | B86: 20403307 | C86: 2026년도 창업중심대학 지역기반 (예비)창업기업 모집 공고 | D86: 지역기반 | E86: 황용하 | F86: 남 | G86: 1988-08-02 | H86: 청년 | I86: 0 | J86: 0 | K86: AI 대화 분석 기술을 적용한 고립 해소 및 1:1 관계 회복 플랫폼 ‘ReLink’ | L86: 경기 | M86: 지식서비스 | N86: 정보ㆍ통신 | O86: 예비 | P86: 정보ㆍ통신2 | Q86: =TODAY() -> 46120 | R86: 0 | S86: 0 | T86: 0 | U86: 0 | V86: =IF(OR(S86="○",T86="○",U86="○"),2,0) -> 0 | W86: 0 | X86: 0 | Y86: 0 | Z86: 0 | AA86: 0 | AB86: =IF(OR(W86="○",X86="○",Y86="○",Z86="○",AA86="○"),"면제",$R86) -> 0
A87: 86 | B87: 20403448 | C87: 2026년도 창업중심대학 지역기반 (예비)창업기업 모집 공고 | D87: 지역기반 | E87: 임지선 | F87: 여 | G87: 1979-02-25 | H87: 중장년 | I87: 345,000 | J87: 1 | K87: 브리엘 아트 인텔리전스: 미술 감상 기반 메타인지 역량개발 솔루션 | L87: 서울 | M87: 지식서비스 | N87: 정보ㆍ통신 | O87: 초기 | P87: 정보ㆍ통신5 | Q87: =TODAY() -> 46120 | R87: 0 | S87: 0 | T87: 0 | U87: 0 | V87: =IF(OR(S87="○",T87="○",U87="○"),2,0) -> 0 | W87: 0 | X87: 0 | Y87: 0 | Z87: 0 | AA87: 0 | AB87: =IF(OR(W87="○",X87="○",Y87="○",Z87="○",AA87="○"),"면제",$R87) -> 0
A88: 87 | B88: 20403467 | C88: 2026년도 창업중심대학 지역기반 (예비)창업기업 모집 공고 | D88: 지역기반 | E88: 최화숙 | F88: 여 | G88: 1976-04-06 | H88: 중장년 | I88: 0 | J88: 0 | K88: 스마트 무인상점(건강을 자동화하다) | L88: 인천 | M88: 지식서비스 | N88: 정보ㆍ통신 | O88: 예비 | P88: 정보ㆍ통신5 | Q88: =TODAY() -> 46120 | R88: 요건탈락 | S88: 0 | T88: 0 | U88: 0 | V88: =IF(OR(S88="○",T88="○",U88="○"),2,0) -> 0 | W88: 0 | X88: 0 | Y88: 0 | Z88: 0 | AA88: 0 | AB88: =IF(OR(W88="○",X88="○",Y88="○",Z88="○",AA88="○"),"면제",$R88) -> 요건탈락
A89: 88 | B89: 20403507 | C89: 2026년도 창업중심대학 지역기반 (예비)창업기업 모집 공고 | D89: 지역기반 | E89: 강병훈 | F89: 남 | G89: 1984-10-12 | H89: 중장년 | I89: 0 | J89: 0 | K89: 실시간 여론조사 플랫폼 '모두의 투표’ | L89: 경기 | M89: 지식서비스 | N89: 정보ㆍ통신 | O89: 예비 | P89: 정보ㆍ통신2 | Q89: =TODAY() -> 46120 | R89: 0 | S89: 0 | T89: 0 | U89: 0 | V89: =IF(OR(S89="○",T89="○",U89="○"),2,0) -> 0 | W89: 0 | X89: 0 | Y89: 0 | Z89: 0 | AA89: 0 | AB89: =IF(OR(W89="○",X89="○",Y89="○",Z89="○",AA89="○"),"면제",$R89) -> 0
A90: 89 | B90: 20403581 | C90: 2026년도 창업중심대학 지역기반 (예비)창업기업 모집 공고 | D90: 지역기반 | E90: 조하영 | F90: 여 | G90: 1995-08-14 | H90: 청년 | I90: 172,000,000 | J90: 3 | K90: 멀티 LLM 에이전트를 활용한 AI시대 미래역량 진단 서비스, 디큐 | L90: 서울 | M90: 지식서비스 | N90: 정보ㆍ통신 | O90: 도약 | P90: 정보ㆍ통신6 | Q90: =TODAY() -> 46120 | R90: 0 | S90: 0 | T90: 0 | U90: 0 | V90: =IF(OR(S90="○",T90="○",U90="○"),2,0) -> 0 | W90: 0 | X90: 0 | Y90: 0 | Z90: 0 | AA90: 0 | AB90: =IF(OR(W90="○",X90="○",Y90="○",Z90="○",AA90="○"),"면제",$R90) -> 0
A91: 90 | B91: 20403598 | C91: 2026년도 창업중심대학 지역기반 (예비)창업기업 모집 공고 | D91: 지역기반 | E91: 이혜진 | F91: 여 | G91: 1984-01-09 | H91: 중장년 | I91: 0 | J91: 0 | K91: 리텐션 고도화형 B2B 글로벌 수출 K-뷰티 속눈썹·글루 제품 | L91: 인천 | M91: 제조 | N91: 화공ㆍ섬유 | O91: 초기 | P91: 화공ㆍ섬유 | Q91: =TODAY() -> 46120 | R91: 0 | S91: 0 | T91: 0 | U91: 0 | V91: =IF(OR(S91="○",T91="○",U91="○"),2,0) -> 0 | W91: 0 | X91: 0 | Y91: 0 | Z91: 0 | AA91: 0 | AB91: =IF(OR(W91="○",X91="○",Y91="○",Z91="○",AA91="○"),"면제",$R91) -> 0
A92: 91 | B92: 20403600 | C92: 2026년도 창업중심대학 지역기반 (예비)창업기업 모집 공고 | D92: 지역기반 | E92: 박에셀 | F92: 남 | G92: 1996-11-17 | H92: 청년 | I92: 3,265,072 | J92: 0 | K92: 반려동물 출입 관련 위생 운영기준 설계기술 기반 업종별 위생관리 B2B 구독 서비스 | L92: 인천 | M92: 제조 | N92: 정보ㆍ통신 | O92: 초기 | P92: 정보ㆍ통신4 | Q92: =TODAY() -> 46120 | R92: 0 | S92: 0 | T92: 0 | U92: 0 | V92: =IF(OR(S92="○",T92="○",U92="○"),2,0) -> 0 | W92: 0 | X92: 0 | Y92: 0 | Z92: 0 | AA92: 0 | AB92: =IF(OR(W92="○",X92="○",Y92="○",Z92="○",AA92="○"),"면제",$R92) -> 0
A93: 92 | B93: 20403659 | C93: 2026년도 창업중심대학 지역기반 (예비)창업기업 모집 공고 | D93: 지역기반 | E93: 권미림 | F93: 여 | G93: 1986-12-02 | H93: 청년 | I93: 14,398,399 | J93: 1 | K93: 고효능 원료 안정화 기술 기반의 워터리스 탄력 파우더 화장품 | L93: 서울 | M93: 제조 | N93: 바이오ㆍ의료ㆍ생명 | O93: 초기 | P93: 바이오ㆍ의료ㆍ생명1 | Q93: =TODAY() -> 46120 | R93: 0 | S93: 0 | T93: 0 | U93: 0 | V93: =IF(OR(S93="○",T93="○",U93="○"),2,0) -> 0 | W93: 0 | X93: 0 | Y93: 0 | Z93: 0 | AA93: 0 | AB93: =IF(OR(W93="○",X93="○",Y93="○",Z93="○",AA93="○"),"면제",$R93) -> 0
A94: 93 | B94: 20403810 | C94: 2026년도 창업중심대학 지역기반 (예비)창업기업 모집 공고 | D94: 지역기반 | E94: 김홍표 | F94: 남 | G94: 1992-01-01 | H94: 청년 | I94: 0 | J94: 0 | K94: SEE-SAY | L94: 경기 | M94: 지식서비스 | N94: 정보ㆍ통신 | O94: 예비 | P94: 정보ㆍ통신2 | Q94: =TODAY() -> 46120 | R94: 0 | S94: 0 | T94: 0 | U94: 0 | V94: =IF(OR(S94="○",T94="○",U94="○"),2,0) -> 0 | W94: 0 | X94: 0 | Y94: 0 | Z94: 0 | AA94: 0 | AB94: =IF(OR(W94="○",X94="○",Y94="○",Z94="○",AA94="○"),"면제",$R94) -> 0
A95: 94 | B95: 20403824 | C95: 2026년도 창업중심대학 지역기반 (예비)창업기업 모집 공고 | D95: 지역기반 | E95: 곽지혜 | F95: 여 | G95: 1997-12-14 | H95: 청년 | I95: 229,875,281 | J95: 0 | K95: 공예형 전통기념품 개발과 양산화·모듈화를 통한 시장 수요 충족 | L95: 서울 | M95: 제조 | N95: 공예ㆍ디자인 | O95: 도약 | P95: 공예ㆍ디자인 | Q95: =TODAY() -> 46120 | R95: 0 | S95: 0 | T95: 0 | U95: 0 | V95: =IF(OR(S95="○",T95="○",U95="○"),2,0) -> 0 | W95: 0 | X95: 0 | Y95: 0 | Z95: 0 | AA95: 0 | AB95: =IF(OR(W95="○",X95="○",Y95="○",Z95="○",AA95="○"),"면제",$R95) -> 0
A96: 95 | B96: 20403842 | C96: 2026년도 창업중심대학 지역기반 (예비)창업기업 모집 공고 | D96: 지역기반 | E96: 조나라 | F96: 여 | G96: 1984-01-02 | H96: 중장년 | I96: 0 | J96: 0 | K96: 차세대 태양전지용 설계 자유도 보존형 저독성 정공물질 잉크 키트, ’퓨어플로우’ | L96: 경기 | M96: 제조 | N96: 에너지ㆍ자원 | O96: 예비 | P96: 에너지ㆍ자원 | Q96: =TODAY() -> 46120 | R96: 0 | S96: 0 | T96: 0 | U96: 0 | V96: =IF(OR(S96="○",T96="○",U96="○"),2,0) -> 0 | W96: 0 | X96: 0 | Y96: 0 | Z96: 0 | AA96: 0 | AB96: =IF(OR(W96="○",X96="○",Y96="○",Z96="○",AA96="○"),"면제",$R96) -> 0
A97: 96 | B97: 20403852 | C97: 2026년도 창업중심대학 지역기반 (예비)창업기업 모집 공고 | D97: 지역기반 | E97: 김수성 | F97: 남 | G97: 1982-02-01 | H97: 중장년 | I97: 69,000,000 | J97: 0 | K97: 고압 송풍 기술 기반 우산 표면 수분 제거 기능의 친환경 “ 우산 건조기 “ | L97: 경기 | M97: 제조 | N97: 기계ㆍ소재 | O97: 도약 | P97: 기계ㆍ소재 | Q97: =TODAY() -> 46120 | R97: 0 | S97: 0 | T97: 0 | U97: 0 | V97: =IF(OR(S97="○",T97="○",U97="○"),2,0) -> 0 | W97: 0 | X97: 0 | Y97: 0 | Z97: 0 | AA97: 0 | AB97: =IF(OR(W97="○",X97="○",Y97="○",Z97="○",AA97="○"),"면제",$R97) -> 0
A98: 97 | B98: 20403910 | C98: 2026년도 창업중심대학 지역기반 (예비)창업기업 모집 공고 | D98: 지역기반 | E98: 장동호 | F98: 남 | G98: 1984-04-20 | H98: 중장년 | I98: 250,000,000 | J98: 2 | K98: 지역 특산 해산물의 풍미를 고농도로 구현한 프리미엄 씨푸드 향미오일 | L98: 경기 | M98: 제조 | N98: 에너지ㆍ자원 | O98: 도약 | P98: 에너지ㆍ자원 | Q98: =TODAY() -> 46120 | R98: 0 | S98: 0 | T98: 0 | U98: 0 | V98: =IF(OR(S98="○",T98="○",U98="○"),2,0) -> 0 | W98: 0 | X98: 0 | Y98: 0 | Z98: 0 | AA98: 0 | AB98: =IF(OR(W98="○",X98="○",Y98="○",Z98="○",AA98="○"),"면제",$R98) -> 0
A99: 98 | B99: 20403969 | C99: 2026년도 창업중심대학 지역기반 (예비)창업기업 모집 공고 | D99: 지역기반 | E99: 채동훈 | F99: 남 | G99: 1983-09-09 | H99: 중장년 | I99: 0 | J99: 0 | K99: K-굿즈 글로벌 유통·신뢰 플랫폼 마이셋(MySet) | L99: 서울 | M99: 지식서비스 | N99: 정보ㆍ통신 | O99: 예비 | P99: 정보ㆍ통신6 | Q99: =TODAY() -> 46120 | R99: 0 | S99: 0 | T99: 0 | U99: 0 | V99: =IF(OR(S99="○",T99="○",U99="○"),2,0) -> 0 | W99: 0 | X99: 0 | Y99: 0 | Z99: 0 | AA99: 0 | AB99: =IF(OR(W99="○",X99="○",Y99="○",Z99="○",AA99="○"),"면제",$R99) -> 0
A100: 99 | B100: 20404073 | C100: 2026년도 창업중심대학 지역기반 (예비)창업기업 모집 공고 | D100: 지역기반 | E100: 박세욱 | F100: 남 | G100: 1995-05-25 | H100: 청년 | I100: 0 | J100: 0 | K100: 기출닥터 | L100: 서울 | M100: 지식서비스 | N100: 정보ㆍ통신 | O100: 예비 | P100: 정보ㆍ통신2 | Q100: =TODAY() -> 46120 | R100: 0 | S100: 0 | T100: 0 | U100: 0 | V100: =IF(OR(S100="○",T100="○",U100="○"),2,0) -> 0 | W100: 0 | X100: 0 | Y100: 0 | Z100: 0 | AA100: 0 | AB100: =IF(OR(W100="○",X100="○",Y100="○",Z100="○",AA100="○"),"면제",$R100) -> 0
...

Sheet 집계
A1: 평가대상 | H1: 1 | I1: 1 | J1: 1 | K1: 2 | N1: 3 | Q1: 4 | T1: 5 | W1: 평가종합 | AE1: 대학발 지역주력 | AF1: 지역주력 일치의견
A2: 순번 | B2: 과제번호 | C2: 공고구분 | D2: 대표자명 | E2: 분과 | F2: 과제명 | G2: 특이사항 | H2: ="검토"&H1 -> 검토1 | I2: ="위원"&H1 -> 위원1 | J2: ="순위"&H1 -> 순위1 | K2: ="검토"&K1 -> 검토2 | L2: ="위원"&K1 -> 위원2 | M2: ="순위"&K1 -> 순위2 | N2: ="검토"&N1 -> 검토3 | O2: ="위원"&N1 -> 위원3 | P2: ="순위"&N1 -> 순위3 | Q2: ="검토"&Q1 -> 검토4 | R2: ="위원"&Q1 -> 위원4 | S2: ="순위"&Q1 -> 순위4 | T2: ="검토"&T1 -> 검토5 | U2: ="위원"&T1 -> 위원5 | V2: ="순위"&T1 -> 순위5 | W2: 사전검토 | X2: 평가자수 | Y2: 평점 | Z2: 가점 | AA2: 점수 | AB2: 과락 | AC2: 순위 | AD2: 평가의견 | AE2: 일치여부 | AF2: 지역주력 일치의견
A3: 154 | B3: 20415817 | C3: =IFERROR(VLOOKUP($B3,대상!$B:$AC,MATCH(C$2,대상!$1:$1,0)-1,FALSE),"") -> 지역기반 | D3: =IFERROR(VLOOKUP($B3,대상!$B:$AC,MATCH(D$2,대상!$1:$1,0)-1,FALSE),"") -> 조만희 | E3: =IFERROR(VLOOKUP($B3,대상!$B:$AC,MATCH(E$2,대상!$1:$1,0)-1,FALSE),"") -> 정보ㆍ통신3 | F3: =IFERROR(VLOOKUP($B3,대상!$B:$AC,MATCH(F$2,대상!$1:$1,0)-1,FALSE),"") -> AI 기반 인재 역량 데이터 분석 및 교육·채용·재교육 연계 플랫폼 | G3: =IFERROR(VLOOKUP($B3,대상!$B:$AC,MATCH(G$2,대상!$1:$1,0)-1,FALSE),"") | H3: =IFERROR(VLOOKUP($B3,[1]평가!$B:$Z,MATCH(LEFT(H$2,2),[1]평가!$7:$7,0)-1,FALSE),"") -> 면제 | I3: =IFERROR(VLOOKUP($B3,[1]평가!$B:$Z,MATCH(LEFT(I$2,2),[1]평가!$7:$7,0)-1,FALSE),"") | J3: =IFERROR(VLOOKUP($B3,[1]평가!$B:$Z,MATCH(LEFT(J$2,2),[1]평가!$7:$7,0)-1,FALSE),"") | K3: =IFERROR(VLOOKUP($B3,[2]평가!$B:$Z,MATCH(LEFT(K$2,2),[2]평가!$7:$7,0)-1,FALSE),"") -> 면제 | L3: =IFERROR(VLOOKUP($B3,[2]평가!$B:$Z,MATCH(LEFT(L$2,2),[2]평가!$7:$7,0)-1,FALSE),"") | M3: =IFERROR(VLOOKUP($B3,[2]평가!$B:$Z,MATCH(LEFT(M$2,2),[2]평가!$7:$7,0)-1,FALSE),"") | N3: =IFERROR(VLOOKUP($B3,[3]평가!$B:$Z,MATCH(LEFT(N$2,2),[3]평가!$7:$7,0)-1,FALSE),"") -> 면제 | O3: =IFERROR(VLOOKUP($B3,[3]평가!$B:$Z,MATCH(LEFT(O$2,2),[3]평가!$7:$7,0)-1,FALSE),"") | P3: =IFERROR(VLOOKUP($B3,[3]평가!$B:$Z,MATCH(LEFT(P$2,2),[3]평가!$7:$7,0)-1,FALSE),"") | Q3: =IFERROR(VLOOKUP($B3,[4]평가!$B:$Z,MATCH(LEFT(Q$2,2),[4]평가!$7:$7,0)-1,FALSE),"") -> 면제 | R3: =IFERROR(VLOOKUP($B3,[4]평가!$B:$Z,MATCH(LEFT(R$2,2),[4]평가!$7:$7,0)-1,FALSE),"") | S3: =IFERROR(VLOOKUP($B3,[4]평가!$B:$Z,MATCH(LEFT(S$2,2),[4]평가!$7:$7,0)-1,FALSE),"") | T3: =IFERROR(VLOOKUP($B3,[5]평가!$B:$Z,MATCH(LEFT(T$2,2),[5]평가!$7:$7,0)-1,FALSE),"") -> 면제 | U3: =IFERROR(VLOOKUP($B3,[5]평가!$B:$Z,MATCH(LEFT(U$2,2),[5]평가!$7:$7,0)-1,FALSE),"") | V3: =IFERROR(VLOOKUP($B3,[5]평가!$B:$Z,MATCH(LEFT(V$2,2),[5]평가!$7:$7,0)-1,FALSE),"") | W3: =IFERROR(VLOOKUP($B3,대상!$B:$AD,MATCH(W$2,대상!$1:$1,0)-1,FALSE),"") -> 면제 | X3: =IF(ISBLANK(B3),"",T$1-COUNTIF(H3:V3,"회피")) -> 5 | Y3: =IF($T$1=X3,(SUM(I3,L3,O3,R3,U3)-MIN(I3,L3,O3,R3,U3)-MAX(I3,L3,O3,R3,U3))/($T$1-2),SUM(I3,L3,O3,R3,U3/X3)) -> 0 | Z3: =IFERROR(VLOOKUP($B3,대상!$B:$AD,MATCH(Z$2,대상!$1:$1,0)-1,FALSE),0) -> 0 | AA3: =IFERROR(IF(W3="면제","100"+Z3,Y3+Z3),"") -> 100 | AB3: =IF(OR(W3="면제",N(Y3)=0),"",IF(AA3<60,"과락","")) | AC3: =IF(N(AA3)=0,"",RANK(AA3,AA$3:AA$202)) -> 1 | AD3: =IFERROR(TEXT(VLOOKUP($B3,[1]평가!$B:$Z,MATCH(AD$2,[1]평가!$6:$6,0)-1,FALSE),"①@ ") & CHAR(13) & TEXT(VLOOKUP($B3,[2]평가!$B:$Z,MATCH(AD$2,[2]평가!$6:$6,0)-1,FALSE),"②@ ") & CHAR(13) & TEXT(VLOOKUP($B3,[3]평가!$B:$Z,MATCH(AD$2,[3]평가!$6:$6,0)-1,FALSE),"③@ ") & CHAR(13) & TEXT(VLOOKUP($B3,[4]평가!$B:$Z,MATCH(AD$2,[4]평가!$6:$6,0)-1,FALSE),"④@ ") & CHAR(13) & TEXT(VLOOKUP($B3,[5]평가!$B:$Z,MATCH(AD$2,[5]평가!$6:$6,0)-1,FALSE),"⑤@ "),"") -> 0_x000D_②서류 면제 _x000D_0_x000D_0_x000D_0 | AE3: =IFERROR(TEXT(VLOOKUP($B3,[1]평가!$B:$Z,MATCH(AE$2,[1]평가!$7:$7,0)-1,FALSE),"①@ ") & CHAR(13) & TEXT(VLOOKUP($B3,[2]평가!$B:$Z,MATCH(AE$2,[2]평가!$7:$7,0)-1,FALSE),"②@ ") & CHAR(13) & TEXT(VLOOKUP($B3,[3]평가!$B:$Z,MATCH(AE$2,[3]평가!$7:$7,0)-1,FALSE),"③@ ") & CHAR(13) & TEXT(VLOOKUP($B3,[4]평가!$B:$Z,MATCH(AE$2,[4]평가!$7:$7,0)-1,FALSE),"④@ ") & CHAR(13) & TEXT(VLOOKUP($B3,[5]평가!$B:$Z,MATCH(AE$2,[5]평가!$7:$7,0)-1,FALSE),"⑤@ "),"") -> 0_x000D_0_x000D_0_x000D_0_x000D_0 | AF3: =IFERROR(TEXT(VLOOKUP($B3,[1]평가!$B:$Z,MATCH(AF$2,[1]평가!$6:$6,0)-1,FALSE),"①@ ") & CHAR(13) & TEXT(VLOOKUP($B3,[2]평가!$B:$Z,MATCH(AF$2,[2]평가!$6:$6,0)-1,FALSE),"②@ ") & CHAR(13) & TEXT(VLOOKUP($B3,[3]평가!$B:$Z,MATCH(AF$2,[3]평가!$6:$6,0)-1,FALSE),"③@ ") & CHAR(13) & TEXT(VLOOKUP($B3,[4]평가!$B:$Z,MATCH(AF$2,[4]평가!$6:$6,0)-1,FALSE),"④@ ") & CHAR(13) & TEXT(VLOOKUP($B3,[5]평가!$B:$Z,MATCH(AF$2,[5]평가!$6:$6,0)-1,FALSE),"⑤@ "),"") -> 0_x000D_0_x000D_0_x000D_0_x000D_0
A4: 152 | B4: 20414883 | C4: =IFERROR(VLOOKUP($B4,대상!$B:$AC,MATCH(C$2,대상!$1:$1,0)-1,FALSE),"") -> 지역기반 | D4: =IFERROR(VLOOKUP($B4,대상!$B:$AC,MATCH(D$2,대상!$1:$1,0)-1,FALSE),"") -> 윤상민 | E4: =IFERROR(VLOOKUP($B4,대상!$B:$AC,MATCH(E$2,대상!$1:$1,0)-1,FALSE),"") -> 정보ㆍ통신3 | F4: =IFERROR(VLOOKUP($B4,대상!$B:$AC,MATCH(F$2,대상!$1:$1,0)-1,FALSE),"") -> A.I.기술 기반 몸캠피싱 영상 유포방지 솔루션 | G4: =IFERROR(VLOOKUP($B4,대상!$B:$AC,MATCH(G$2,대상!$1:$1,0)-1,FALSE),"") -> 매출실적우수 | H4: =IFERROR(VLOOKUP($B4,[1]평가!$B:$Z,MATCH(LEFT(H$2,2),[1]평가!$7:$7,0)-1,FALSE),"") -> 0 | I4: =IFERROR(VLOOKUP($B4,[1]평가!$B:$Z,MATCH(LEFT(I$2,2),[1]평가!$7:$7,0)-1,FALSE),"") -> 90 | J4: =IFERROR(VLOOKUP($B4,[1]평가!$B:$Z,MATCH(LEFT(J$2,2),[1]평가!$7:$7,0)-1,FALSE),"") -> 1 | K4: =IFERROR(VLOOKUP($B4,[2]평가!$B:$Z,MATCH(LEFT(K$2,2),[2]평가!$7:$7,0)-1,FALSE),"") -> 0 | L4: =IFERROR(VLOOKUP($B4,[2]평가!$B:$Z,MATCH(LEFT(L$2,2),[2]평가!$7:$7,0)-1,FALSE),"") -> 89 | M4: =IFERROR(VLOOKUP($B4,[2]평가!$B:$Z,MATCH(LEFT(M$2,2),[2]평가!$7:$7,0)-1,FALSE),"") -> 8 | N4: =IFERROR(VLOOKUP($B4,[3]평가!$B:$Z,MATCH(LEFT(N$2,2),[3]평가!$7:$7,0)-1,FALSE),"") -> 0 | O4: =IFERROR(VLOOKUP($B4,[3]평가!$B:$Z,MATCH(LEFT(O$2,2),[3]평가!$7:$7,0)-1,FALSE),"") -> 94 | P4: =IFERROR(VLOOKUP($B4,[3]평가!$B:$Z,MATCH(LEFT(P$2,2),[3]평가!$7:$7,0)-1,FALSE),"") -> 1 | Q4: =IFERROR(VLOOKUP($B4,[4]평가!$B:$Z,MATCH(LEFT(Q$2,2),[4]평가!$7:$7,0)-1,FALSE),"") -> 0 | R4: =IFERROR(VLOOKUP($B4,[4]평가!$B:$Z,MATCH(LEFT(R$2,2),[4]평가!$7:$7,0)-1,FALSE),"") -> 92 | S4: =IFERROR(VLOOKUP($B4,[4]평가!$B:$Z,MATCH(LEFT(S$2,2),[4]평가!$7:$7,0)-1,FALSE),"") -> 2 | T4: =IFERROR(VLOOKUP($B4,[5]평가!$B:$Z,MATCH(LEFT(T$2,2),[5]평가!$7:$7,0)-1,FALSE),"") -> 0 | U4: =IFERROR(VLOOKUP($B4,[5]평가!$B:$Z,MATCH(LEFT(U$2,2),[5]평가!$7:$7,0)-1,FALSE),"") -> 93 | V4: =IFERROR(VLOOKUP($B4,[5]평가!$B:$Z,MATCH(LEFT(V$2,2),[5]평가!$7:$7,0)-1,FALSE),"") -> 1 | W4: =IFERROR(VLOOKUP($B4,대상!$B:$AD,MATCH(W$2,대상!$1:$1,0)-1,FALSE),"") -> 0 | X4: =IF(ISBLANK(B4),"",T$1-COUNTIF(H4:V4,"회피")) -> 5 | Y4: =IF($T$1=X4,(SUM(I4,L4,O4,R4,U4)-MIN(I4,L4,O4,R4,U4)-MAX(I4,L4,O4,R4,U4))/($T$1-2),SUM(I4,L4,O4,R4,U4/X4)) -> 91.666667 | Z4: =IFERROR(VLOOKUP($B4,대상!$B:$AD,MATCH(Z$2,대상!$1:$1,0)-1,FALSE),0) -> 2 | AA4: =IFERROR(IF(W4="면제","100"+Z4,Y4+Z4),"") -> 93.666667 | AB4: =IF(OR(W4="면제",N(Y4)=0),"",IF(AA4<60,"과락","")) | AC4: =IF(N(AA4)=0,"",RANK(AA4,AA$3:AA$202)) -> 2 | AD4: =IFERROR(TEXT(VLOOKUP($B4,[1]평가!$B:$Z,MATCH(AD$2,[1]평가!$6:$6,0)-1,FALSE),"①@ ") & CHAR(13) & TEXT(VLOOKUP($B4,[2]평가!$B:$Z,MATCH(AD$2,[2]평가!$6:$6,0)-1,FALSE),"②@ ") & CHAR(13) & TEXT(VLOOKUP($B4,[3]평가!$B:$Z,MATCH(AD$2,[3]평가!$6:$6,0)-1,FALSE),"③@ ") & CHAR(13) & TEXT(VLOOKUP($B4,[4]평가!$B:$Z,MATCH(AD$2,[4]평가!$6:$6,0)-1,FALSE),"④@ ") & CHAR(13) & TEXT(VLOOKUP($B4,[5]평가!$B:$Z,MATCH(AD$2,[5]평가!$6:$6,0)-1,FALSE),"⑤@ "),"") -> ①투자유치관련 IR로드맵 구체화 필요함.시장확장위한 마케팅 채널 확보방안 수립 요망 _x000D_②실제 해당 분야에서의 매출이 발생하고 있는 상황으로 솔루션 고도화를 통한 글로벌 진출도 가능해 보임 _x000D_③목표 시장의 설정과 수익 모델의 구조가 명확하게 제시되어 사업의 실질적인 수익 창출 가능성이 높음. 전반적인 사업 계획의 흐름과 방향성이 적정하게 설계되었으며, 시장 안착을 위한 논리적 근거가 충분히 마련되었음. _x000D_④AI기반 몸캠피싱 유포방지 솔루션 기획단계이며 특화부분, 기술력 입증 평가하기 위한 경쟁자분석과 벤치마킹이 부족하며 수익에 대한 구체적 보완이 필요함, 사회적 문제를 개선하는 모델의 수익으로 매출입증 및 기술차별화를 실현하고 있음 _x000D_⑤경쟁사 분석으로 통한 핵심기술 도출에 대한 내용이 제시되었음. 전반적으로 사업 추진의 완성도가 양호하다고 판단됨. | AE4: =IFERROR(TEXT(VLOOKUP($B4,[1]평가!$B:$Z,MATCH(AE$2,[1]평가!$7:$7,0)-1,FALSE),"①@ ") & CHAR(13) & TEXT(VLOOKUP($B4,[2]평가!$B:$Z,MATCH(AE$2,[2]평가!$7:$7,0)-1,FALSE),"②@ ") & CHAR(13) & TEXT(VLOOKUP($B4,[3]평가!$B:$Z,MATCH(AE$2,[3]평가!$7:$7,0)-1,FALSE),"③@ ") & CHAR(13) & TEXT(VLOOKUP($B4,[4]평가!$B:$Z,MATCH(AE$2,[4]평가!$7:$7,0)-1,FALSE),"④@ ") & CHAR(13) & TEXT(VLOOKUP($B4,[5]평가!$B:$Z,MATCH(AE$2,[5]평가!$7:$7,0)-1,FALSE),"⑤@ "),"") -> 0_x000D_0_x000D_0_x000D_0_x000D_0 | AF4: =IFERROR(TEXT(VLOOKUP($B4,[1]평가!$B:$Z,MATCH(AF$2,[1]평가!$6:$6,0)-1,FALSE),"①@ ") & CHAR(13) & TEXT(VLOOKUP($B4,[2]평가!$B:$Z,MATCH(AF$2,[2]평가!$6:$6,0)-1,FALSE),"②@ ") & CHAR(13) & TEXT(VLOOKUP($B4,[3]평가!$B:$Z,MATCH(AF$2,[3]평가!$6:$6,0)-1,FALSE),"③@ ") & CHAR(13) & TEXT(VLOOKUP($B4,[4]평가!$B:$Z,MATCH(AF$2,[4]평가!$6:$6,0)-1,FALSE),"④@ ") & CHAR(13) & TEXT(VLOOKUP($B4,[5]평가!$B:$Z,MATCH(AF$2,[5]평가!$6:$6,0)-1,FALSE),"⑤@ "),"") -> 0_x000D_0_x000D_0_x000D_0_x000D_0
A5: 67 | B5: 20426148 | C5: =IFERROR(VLOOKUP($B5,대상!$B:$AC,MATCH(C$2,대상!$1:$1,0)-1,FALSE),"") -> 지역기반 | D5: =IFERROR(VLOOKUP($B5,대상!$B:$AC,MATCH(D$2,대상!$1:$1,0)-1,FALSE),"") -> 강경민 | E5: =IFERROR(VLOOKUP($B5,대상!$B:$AC,MATCH(E$2,대상!$1:$1,0)-1,FALSE),"") -> 정보ㆍ통신3 | F5: =IFERROR(VLOOKUP($B5,대상!$B:$AC,MATCH(F$2,대상!$1:$1,0)-1,FALSE),"") -> 소상공인에게는 매출전환 콘텐츠를, 청년에게는 실무·수익화를 연결하는 양면 콘텐츠 운영 플랫폼, 컨테니파이 | G5: =IFERROR(VLOOKUP($B5,대상!$B:$AC,MATCH(G$2,대상!$1:$1,0)-1,FALSE),"") | H5: =IFERROR(VLOOKUP($B5,[1]평가!$B:$Z,MATCH(LEFT(H$2,2),[1]평가!$7:$7,0)-1,FALSE),"") -> 0 | I5: =IFERROR(VLOOKUP($B5,[1]평가!$B:$Z,MATCH(LEFT(I$2,2),[1]평가!$7:$7,0)-1,FALSE),"") -> 88 | J5: =IFERROR(VLOOKUP($B5,[1]평가!$B:$Z,MATCH(LEFT(J$2,2),[1]평가!$7:$7,0)-1,FALSE),"") -> 2 | K5: =IFERROR(VLOOKUP($B5,[2]평가!$B:$Z,MATCH(LEFT(K$2,2),[2]평가!$7:$7,0)-1,FALSE),"") -> 0 | L5: =IFERROR(VLOOKUP($B5,[2]평가!$B:$Z,MATCH(LEFT(L$2,2),[2]평가!$7:$7,0)-1,FALSE),"") -> 91 | M5: =IFERROR(VLOOKUP($B5,[2]평가!$B:$Z,MATCH(LEFT(M$2,2),[2]평가!$7:$7,0)-1,FALSE),"") -> 3 | N5: =IFERROR(VLOOKUP($B5,[3]평가!$B:$Z,MATCH(LEFT(N$2,2),[3]평가!$7:$7,0)-1,FALSE),"") -> 0 | O5: =IFERROR(VLOOKUP($B5,[3]평가!$B:$Z,MATCH(LEFT(O$2,2),[3]평가!$7:$7,0)-1,FALSE),"") -> 91 | P5: =IFERROR(VLOOKUP($B5,[3]평가!$B:$Z,MATCH(LEFT(P$2,2),[3]평가!$7:$7,0)-1,FALSE),"") -> 2 | Q5: =IFERROR(VLOOKUP($B5,[4]평가!$B:$Z,MATCH(LEFT(Q$2,2),[4]평가!$7:$7,0)-1,FALSE),"") -> 0 | R5: =IFERROR(VLOOKUP($B5,[4]평가!$B:$Z,MATCH(LEFT(R$2,2),[4]평가!$7:$7,0)-1,FALSE),"") -> 89 | S5: =IFERROR(VLOOKUP($B5,[4]평가!$B:$Z,MATCH(LEFT(S$2,2),[4]평가!$7:$7,0)-1,FALSE),"") -> 4 | T5: =IFERROR(VLOOKUP($B5,[5]평가!$B:$Z,MATCH(LEFT(T$2,2),[5]평가!$7:$7,0)-1,FALSE),"") -> 0 | U5: =IFERROR(VLOOKUP($B5,[5]평가!$B:$Z,MATCH(LEFT(U$2,2),[5]평가!$7:$7,0)-1,FALSE),"") -> 84 | V5: =IFERROR(VLOOKUP($B5,[5]평가!$B:$Z,MATCH(LEFT(V$2,2),[5]평가!$7:$7,0)-1,FALSE),"") -> 20 | W5: =IFERROR(VLOOKUP($B5,대상!$B:$AD,MATCH(W$2,대상!$1:$1,0)-1,FALSE),"") -> 0 | X5: =IF(ISBLANK(B5),"",T$1-COUNTIF(H5:V5,"회피")) -> 5 | Y5: =IF($T$1=X5,(SUM(I5,L5,O5,R5,U5)-MIN(I5,L5,O5,R5,U5)-MAX(I5,L5,O5,R5,U5))/($T$1-2),SUM(I5,L5,O5,R5,U5/X5)) -> 89.333333 | Z5: =IFERROR(VLOOKUP($B5,대상!$B:$AD,MATCH(Z$2,대상!$1:$1,0)-1,FALSE),0) -> 2 | AA5: =IFERROR(IF(W5="면제","100"+Z5,Y5+Z5),"") -> 91.333333 | AB5: =IF(OR(W5="면제",N(Y5)=0),"",IF(AA5<60,"과락","")) | AC5: =IF(N(AA5)=0,"",RANK(AA5,AA$3:AA$202)) -> 3 | AD5: =IFERROR(TEXT(VLOOKUP($B5,[1]평가!$B:$Z,MATCH(AD$2,[1]평가!$6:$6,0)-1,FALSE),"①@ ") & CHAR(13) & TEXT(VLOOKUP($B5,[2]평가!$B:$Z,MATCH(AD$2,[2]평가!$6:$6,0)-1,FALSE),"②@ ") & CHAR(13) & TEXT(VLOOKUP($B5,[3]평가!$B:$Z,MATCH(AD$2,[3]평가!$6:$6,0)-1,FALSE),"③@ ") & CHAR(13) & TEXT(VLOOKUP($B5,[4]평가!$B:$Z,MATCH(AD$2,[4]평가!$6:$6,0)-1,FALSE),"④@ ") & CHAR(13) & TEXT(VLOOKUP($B5,[5]평가!$B:$Z,MATCH(AD$2,[5]평가!$6:$6,0)-1,FALSE),"⑤@ "),"") -> ①시장의 수요가 존재함을 인지하나 구체화된 시장규모의 분석이 필요하며 향후 시장확대위한 서비스 포트폴리오의 다양화방안 수립 필요함 _x000D_②콘텐츠 제작완료 등 검증 진행중으로 보이고 시장성 있어 보임. 검증 내용 기반 시장성 분석에 대한 내용과 이를 어떻게 활용할지에 대한 전략적인 부분들이 보완되면 더욱 좋을 것임 _x000D_③명확한 목표 시장과 수익 구조를 갖추고 있어, 사업의 실질적인 수익 창출 가능성이 높게 평가됨. 사업 계획의 흐름과 방향성이 논리적으로 설계되어 있어 안정적인 사업 추진 기반을 확보하였음. _x000D_④AI기반 교육플랫폼과 홍보물 고객 매칭 플랫폼 기획단계이며 일자리 창출, 기술기반 데이터 연동형으로 수익에 대한 구조화 보완이 필요함, 자금 계획을 지원사업 위주로 잡는다면 사업이 좌초될 위험성이 너무 크며 지속경영과 생존을 위한 초기수익 모델이 필요함 _x000D_⑤경쟁사 분석을 통해 차별점을 제시하고 있음. 특허 출원을 통해 기술보호를 추진하고 있음. 조직구성이 일부되어 있으며 협약기간내 고용 계획을 가지고 있음. | AE5: =IFERROR(TEXT(VLOOKUP($B5,[1]평가!$B:$Z,MATCH(AE$2,[1]평가!$7:$7,0)-1,FALSE),"①@ ") & CHAR(13) & TEXT(VLOOKUP($B5,[2]평가!$B:$Z,MATCH(AE$2,[2]평가!$7:$7,0)-1,FALSE),"②@ ") & CHAR(13) & TEXT(VLOOKUP($B5,[3]평가!$B:$Z,MATCH(AE$2,[3]평가!$7:$7,0)-1,FALSE),"③@ ") & CHAR(13) & TEXT(VLOOKUP($B5,[4]평가!$B:$Z,MATCH(AE$2,[4]평가!$7:$7,0)-1,FALSE),"④@ ") & CHAR(13) & TEXT(VLOOKUP($B5,[5]평가!$B:$Z,MATCH(AE$2,[5]평가!$7:$7,0)-1,FALSE),"⑤@ "),"") -> 0_x000D_0_x000D_0_x000D_0_x000D_0 | AF5: =IFERROR(TEXT(VLOOKUP($B5,[1]평가!$B:$Z,MATCH(AF$2,[1]평가!$6:$6,0)-1,FALSE),"①@ ") & CHAR(13) & TEXT(VLOOKUP($B5,[2]평가!$B:$Z,MATCH(AF$2,[2]평가!$6:$6,0)-1,FALSE),"②@ ") & CHAR(13) & TEXT(VLOOKUP($B5,[3]평가!$B:$Z,MATCH(AF$2,[3]평가!$6:$6,0)-1,FALSE),"③@ ") & CHAR(13) & TEXT(VLOOKUP($B5,[4]평가!$B:$Z,MATCH(AF$2,[4]평가!$6:$6,0)-1,FALSE),"④@ ") & CHAR(13) & TEXT(VLOOKUP($B5,[5]평가!$B:$Z,MATCH(AF$2,[5]평가!$6:$6,0)-1,FALSE),"⑤@ "),"") -> 0_x000D_0_x000D_0_x000D_0_x000D_0
A6: 156 | B6: 20412041 | C6: =IFERROR(VLOOKUP($B6,대상!$B:$AC,MATCH(C$2,대상!$1:$1,0)-1,FALSE),"") -> 지역기반 | D6: =IFERROR(VLOOKUP($B6,대상!$B:$AC,MATCH(D$2,대상!$1:$1,0)-1,FALSE),"") -> 문정호 | E6: =IFERROR(VLOOKUP($B6,대상!$B:$AC,MATCH(E$2,대상!$1:$1,0)-1,FALSE),"") -> 정보ㆍ통신3 | F6: =IFERROR(VLOOKUP($B6,대상!$B:$AC,MATCH(F$2,대상!$1:$1,0)-1,FALSE),"") -> AI기반 맞춤형 점술 서비스 중개 플랫폼, ‘맞점’ | G6: =IFERROR(VLOOKUP($B6,대상!$B:$AC,MATCH(G$2,대상!$1:$1,0)-1,FALSE),"") | H6: =IFERROR(VLOOKUP($B6,[1]평가!$B:$Z,MATCH(LEFT(H$2,2),[1]평가!$7:$7,0)-1,FALSE),"") -> 0 | I6: =IFERROR(VLOOKUP($B6,[1]평가!$B:$Z,MATCH(LEFT(I$2,2),[1]평가!$7:$7,0)-1,FALSE),"") -> 90 | J6: =IFERROR(VLOOKUP($B6,[1]평가!$B:$Z,MATCH(LEFT(J$2,2),[1]평가!$7:$7,0)-1,FALSE),"") -> 2 | K6: =IFERROR(VLOOKUP($B6,[2]평가!$B:$Z,MATCH(LEFT(K$2,2),[2]평가!$7:$7,0)-1,FALSE),"") -> 0 | L6: =IFERROR(VLOOKUP($B6,[2]평가!$B:$Z,MATCH(LEFT(L$2,2),[2]평가!$7:$7,0)-1,FALSE),"") -> 92 | M6: =IFERROR(VLOOKUP($B6,[2]평가!$B:$Z,MATCH(LEFT(M$2,2),[2]평가!$7:$7,0)-1,FALSE),"") -> 4 | N6: =IFERROR(VLOOKUP($B6,[3]평가!$B:$Z,MATCH(LEFT(N$2,2),[3]평가!$7:$7,0)-1,FALSE),"") -> 0 | O6: =IFERROR(VLOOKUP($B6,[3]평가!$B:$Z,MATCH(LEFT(O$2,2),[3]평가!$7:$7,0)-1,FALSE),"") -> 91 | P6: =IFERROR(VLOOKUP($B6,[3]평가!$B:$Z,MATCH(LEFT(P$2,2),[3]평가!$7:$7,0)-1,FALSE),"") -> 9 | Q6: =IFERROR(VLOOKUP($B6,[4]평가!$B:$Z,MATCH(LEFT(Q$2,2),[4]평가!$7:$7,0)-1,FALSE),"") -> 0 | R6: =IFERROR(VLOOKUP($B6,[4]평가!$B:$Z,MATCH(LEFT(R$2,2),[4]평가!$7:$7,0)-1,FALSE),"") -> 95 | S6: =IFERROR(VLOOKUP($B6,[4]평가!$B:$Z,MATCH(LEFT(S$2,2),[4]평가!$7:$7,0)-1,FALSE),"") -> 1 | T6: =IFERROR(VLOOKUP($B6,[5]평가!$B:$Z,MATCH(LEFT(T$2,2),[5]평가!$7:$7,0)-1,FALSE),"") -> 0 | U6: =IFERROR(VLOOKUP($B6,[5]평가!$B:$Z,MATCH(LEFT(U$2,2),[5]평가!$7:$7,0)-1,FALSE),"") -> 88 | V6: =IFERROR(VLOOKUP($B6,[5]평가!$B:$Z,MATCH(LEFT(V$2,2),[5]평가!$7:$7,0)-1,FALSE),"") -> 13 | W6: =IFERROR(VLOOKUP($B6,대상!$B:$AD,MATCH(W$2,대상!$1:$1,0)-1,FALSE),"") -> 0 | X6: =IF(ISBLANK(B6),"",T$1-COUNTIF(H6:V6,"회피")) -> 5 | Y6: =IF($T$1=X6,(SUM(I6,L6,O6,R6,U6)-MIN(I6,L6,O6,R6,U6)-MAX(I6,L6,O6,R6,U6))/($T$1-2),SUM(I6,L6,O6,R6,U6/X6)) -> 91 | Z6: =IFERROR(VLOOKUP($B6,대상!$B:$AD,MATCH(Z$2,대상!$1:$1,0)-1,FALSE),0) -> 0 | AA6: =IFERROR(IF(W6="면제","100"+Z6,Y6+Z6),"") -> 91 | AB6: =IF(OR(W6="면제",N(Y6)=0),"",IF(AA6<60,"과락","")) | AC6: =IF(N(AA6)=0,"",RANK(AA6,AA$3:AA$202)) -> 4 | AD6: =IFERROR(TEXT(VLOOKUP($B6,[1]평가!$B:$Z,MATCH(AD$2,[1]평가!$6:$6,0)-1,FALSE),"①@ ") & CHAR(13) & TEXT(VLOOKUP($B6,[2]평가!$B:$Z,MATCH(AD$2,[2]평가!$6:$6,0)-1,FALSE),"②@ ") & CHAR(13) & TEXT(VLOOKUP($B6,[3]평가!$B:$Z,MATCH(AD$2,[3]평가!$6:$6,0)-1,FALSE),"③@ ") & CHAR(13) & TEXT(VLOOKUP($B6,[4]평가!$B:$Z,MATCH(AD$2,[4]평가!$6:$6,0)-1,FALSE),"④@ ") & CHAR(13) & TEXT(VLOOKUP($B6,[5]평가!$B:$Z,MATCH(AD$2,[5]평가!$6:$6,0)-1,FALSE),"⑤@ "),"") -> ①기존 시장에 메이저사업자로 존재하는 기업과의 브랜딩 및 고객 수용성관점에서 지속적 경쟁력 확보방안 수립필요. IR로드맵 구체화 요망함. _x000D_②mau 15만명 및 매출 성과를 보여주고 있으며, 향후 글로벌 진출까지 고려된 사업화가 추진되면 좋을 것으로 보임 _x000D_③목표 시장의 설정과 수익 모델의 구조가 명확하게 제시되어 사업의 실질적인 수익 창출 가능성이 높음. 전반적인 사업 계획의 흐름과 방향성이 적정하게 설계되었으며, 시장 안착을 위한 논리적 근거가 충분히 마련되었음. _x000D_④23년예창패 장려상선정기업으로 구성원이 탄탄하고 쿠팡 리워드 전환으로 AI운세풀이로 수익성을 확보하였으며 시장 점유율을 높이 성장시키는 쾌거를 기록 중 투자유치도 성공함, 시장의 효용성과 성장성을 매출과 정량지표로 보여주고 있는 창업기업으로 보여짐 _x000D_⑤시장 진입 대상과 수익구조가 비교적 명확하게 제시 되었음. 사업 추진일정도 단계별로 구성되어 있음. | AE6: =IFERROR(TEXT(VLOOKUP($B6,[1]평가!$B:$Z,MATCH(AE$2,[1]평가!$7:$7,0)-1,FALSE),"①@ ") & CHAR(13) & TEXT(VLOOKUP($B6,[2]평가!$B:$Z,MATCH(AE$2,[2]평가!$7:$7,0)-1,FALSE),"②@ ") & CHAR(13) & TEXT(VLOOKUP($B6,[3]평가!$B:$Z,MATCH(AE$2,[3]평가!$7:$7,0)-1,FALSE),"③@ ") & CHAR(13) & TEXT(VLOOKUP($B6,[4]평가!$B:$Z,MATCH(AE$2,[4]평가!$7:$7,0)-1,FALSE),"④@ ") & CHAR(13) & TEXT(VLOOKUP($B6,[5]평가!$B:$Z,MATCH(AE$2,[5]평가!$7:$7,0)-1,FALSE),"⑤@ "),"") -> 0_x000D_0_x000D_0_x000D_0_x000D_0 | AF6: =IFERROR(TEXT(VLOOKUP($B6,[1]평가!$B:$Z,MATCH(AF$2,[1]평가!$6:$6,0)-1,FALSE),"①@ ") & CHAR(13) & TEXT(VLOOKUP($B6,[2]평가!$B:$Z,MATCH(AF$2,[2]평가!$6:$6,0)-1,FALSE),"②@ ") & CHAR(13) & TEXT(VLOOKUP($B6,[3]평가!$B:$Z,MATCH(AF$2,[3]평가!$6:$6,0)-1,FALSE),"③@ ") & CHAR(13) & TEXT(VLOOKUP($B6,[4]평가!$B:$Z,MATCH(AF$2,[4]평가!$6:$6,0)-1,FALSE),"④@ ") & CHAR(13) & TEXT(VLOOKUP($B6,[5]평가!$B:$Z,MATCH(AF$2,[5]평가!$6:$6,0)-1,FALSE),"⑤@ "),"") -> 0_x000D_0_x000D_0_x000D_0_x000D_0
A7: 160 | B7: 20428945 | C7: =IFERROR(VLOOKUP($B7,대상!$B:$AC,MATCH(C$2,대상!$1:$1,0)-1,FALSE),"") -> 지역기반 | D7: =IFERROR(VLOOKUP($B7,대상!$B:$AC,MATCH(D$2,대상!$1:$1,0)-1,FALSE),"") -> 이건희 | E7: =IFERROR(VLOOKUP($B7,대상!$B:$AC,MATCH(E$2,대상!$1:$1,0)-1,FALSE),"") -> 정보ㆍ통신3 | F7: =IFERROR(VLOOKUP($B7,대상!$B:$AC,MATCH(F$2,대상!$1:$1,0)-1,FALSE),"") -> 캐릭터 IP를 살아 말하게 하는 감성 AI 보이스 솔루션 개발 및 IP 사업자 공급형 사업화 (On the Voice — 캐릭터 온톨로지 기반 범용 SaaS) | G7: =IFERROR(VLOOKUP($B7,대상!$B:$AC,MATCH(G$2,대상!$1:$1,0)-1,FALSE),"") | H7: =IFERROR(VLOOKUP($B7,[1]평가!$B:$Z,MATCH(LEFT(H$2,2),[1]평가!$7:$7,0)-1,FALSE),"") -> 0 | I7: =IFERROR(VLOOKUP($B7,[1]평가!$B:$Z,MATCH(LEFT(I$2,2),[1]평가!$7:$7,0)-1,FALSE),"") -> 90 | J7: =IFERROR(VLOOKUP($B7,[1]평가!$B:$Z,MATCH(LEFT(J$2,2),[1]평가!$7:$7,0)-1,FALSE),"") -> 2 | K7: =IFERROR(VLOOKUP($B7,[2]평가!$B:$Z,MATCH(LEFT(K$2,2),[2]평가!$7:$7,0)-1,FALSE),"") -> 0 | L7: =IFERROR(VLOOKUP($B7,[2]평가!$B:$Z,MATCH(LEFT(L$2,2),[2]평가!$7:$7,0)-1,FALSE),"") -> 92 | M7: =IFERROR(VLOOKUP($B7,[2]평가!$B:$Z,MATCH(LEFT(M$2,2),[2]평가!$7:$7,0)-1,FALSE),"") -> 4 | N7: =IFERROR(VLOOKUP($B7,[3]평가!$B:$Z,MATCH(LEFT(N$2,2),[3]평가!$7:$7,0)-1,FALSE),"") -> 0 | O7: =IFERROR(VLOOKUP($B7,[3]평가!$B:$Z,MATCH(LEFT(O$2,2),[3]평가!$7:$7,0)-1,FALSE),"") -> 92 | P7: =IFERROR(VLOOKUP($B7,[3]평가!$B:$Z,MATCH(LEFT(P$2,2),[3]평가!$7:$7,0)-1,FALSE),"") -> 5 | Q7: =IFERROR(VLOOKUP($B7,[4]평가!$B:$Z,MATCH(LEFT(Q$2,2),[4]평가!$7:$7,0)-1,FALSE),"") -> 0 | R7: =IFERROR(VLOOKUP($B7,[4]평가!$B:$Z,MATCH(LEFT(R$2,2),[4]평가!$7:$7,0)-1,FALSE),"") -> 91 | S7: =IFERROR(VLOOKUP($B7,[4]평가!$B:$Z,MATCH(LEFT(S$2,2),[4]평가!$7:$7,0)-1,FALSE),"") -> 4 | T7: =IFERROR(VLOOKUP($B7,[5]평가!$B:$Z,MATCH(LEFT(T$2,2),[5]평가!$7:$7,0)-1,FALSE),"") -> 0 | U7: =IFERROR(VLOOKUP($B7,[5]평가!$B:$Z,MATCH(LEFT(U$2,2),[5]평가!$7:$7,0)-1,FALSE),"") -> 88 | V7: =IFERROR(VLOOKUP($B7,[5]평가!$B:$Z,MATCH(LEFT(V$2,2),[5]평가!$7:$7,0)-1,FALSE),"") -> 13 | W7: =IFERROR(VLOOKUP($B7,대상!$B:$AD,MATCH(W$2,대상!$1:$1,0)-1,FALSE),"") -> 0 | X7: =IF(ISBLANK(B7),"",T$1-COUNTIF(H7:V7,"회피")) -> 5 | Y7: =IF($T$1=X7,(SUM(I7,L7,O7,R7,U7)-MIN(I7,L7,O7,R7,U7)-MAX(I7,L7,O7,R7,U7))/($T$1-2),SUM(I7,L7,O7,R7,U7/X7)) -> 91 | Z7: =IFERROR(VLOOKUP($B7,대상!$B:$AD,MATCH(Z$2,대상!$1:$1,0)-1,FALSE),0) -> 0 | AA7: =IFERROR(IF(W7="면제","100"+Z7,Y7+Z7),"") -> 91 | AB7: =IF(OR(W7="면제",N(Y7)=0),"",IF(AA7<60,"과락","")) | AC7: =IF(N(AA7)=0,"",RANK(AA7,AA$3:AA$202)) -> 4 | AD7: =IFERROR(TEXT(VLOOKUP($B7,[1]평가!$B:$Z,MATCH(AD$2,[1]평가!$6:$6,0)-1,FALSE),"①@ ") & CHAR(13) & TEXT(VLOOKUP($B7,[2]평가!$B:$Z,MATCH(AD$2,[2]평가!$6:$6,0)-1,FALSE),"②@ ") & CHAR(13) & TEXT(VLOOKUP($B7,[3]평가!$B:$Z,MATCH(AD$2,[3]평가!$6:$6,0)-1,FALSE),"③@ ") & CHAR(13) & TEXT(VLOOKUP($B7,[4]평가!$B:$Z,MATCH(AD$2,[4]평가!$6:$6,0)-1,FALSE),"④@ ") & CHAR(13) & TEXT(VLOOKUP($B7,[5]평가!$B:$Z,MATCH(AD$2,[5]평가!$6:$6,0)-1,FALSE),"⑤@ "),"") -> ①선재적으로 개발리스크를 발굴하여 헤징방안을 수립하고 투자유치위한 구체화된 IR로드맵 수립 요망함. _x000D_②시장 포지셔닝과 차별성은 잘 가져가고 있음. 개발 아이템에 대한 구체적인 개발 및 구현, 서비스 제공 등에 대한 내용이 세세하게 설명될 필요는 있음 _x000D_③아이템의 기술 개요와 개발방향은 이해하기 쉽게 작성되었음. 그리고 사업계획의 방향성은 적절한것으로 판단됨. 시장전략의 구체성이 다소 부족하다고 판단됨. _x000D_④아이돌, 사이버캐릭터, 캐릭터들의 IP의 펜덤들과 온라인 소통을 위하여 온더보이스를 통한 사업구성으로 과금 복합형 수익구조와 시장의 필요를 검증하며 매출 13억을 달성함(부가세증명원) _x000D_⑤시장 진입 대상과 수익구조가 명확하게 제시되었음. 아이템 개발 및 추진을 위한 기본 역량도 갖춘것으로 보임. | AE7: =IFERROR(TEXT(VLOOKUP($B7,[1]평가!$B:$Z,MATCH(AE$2,[1]평가!$7:$7,0)-1,FALSE),"①@ ") & CHAR(13) & TEXT(VLOOKUP($B7,[2]평가!$B:$Z,MATCH(AE$2,[2]평가!$7:$7,0)-1,FALSE),"②@ ") & CHAR(13) & TEXT(VLOOKUP($B7,[3]평가!$B:$Z,MATCH(AE$2,[3]평가!$7:$7,0)-1,FALSE),"③@ ") & CHAR(13) & TEXT(VLOOKUP($B7,[4]평가!$B:$Z,MATCH(AE$2,[4]평가!$7:$7,0)-1,FALSE),"④@ ") & CHAR(13) & TEXT(VLOOKUP($B7,[5]평가!$B:$Z,MATCH(AE$2,[5]평가!$7:$7,0)-1,FALSE),"⑤@ "),"") -> 0_x000D_0_x000D_0_x000D_0_x000D_0 | AF7: =IFERROR(TEXT(VLOOKUP($B7,[1]평가!$B:$Z,MATCH(AF$2,[1]평가!$6:$6,0)-1,FALSE),"①@ ") & CHAR(13) & TEXT(VLOOKUP($B7,[2]평가!$B:$Z,MATCH(AF$2,[2]평가!$6:$6,0)-1,FALSE),"②@ ") & CHAR(13) & TEXT(VLOOKUP($B7,[3]평가!$B:$Z,MATCH(AF$2,[3]평가!$6:$6,0)-1,FALSE),"③@ ") & CHAR(13) & TEXT(VLOOKUP($B7,[4]평가!$B:$Z,MATCH(AF$2,[4]평가!$6:$6,0)-1,FALSE),"④@ ") & CHAR(13) & TEXT(VLOOKUP($B7,[5]평가!$B:$Z,MATCH(AF$2,[5]평가!$6:$6,0)-1,FALSE),"⑤@ "),"") -> 0_x000D_0_x000D_0_x000D_0_x000D_0
A8: 181 | B8: 20426671 | C8: =IFERROR(VLOOKUP($B8,대상!$B:$AC,MATCH(C$2,대상!$1:$1,0)-1,FALSE),"") -> 지역기반 | D8: =IFERROR(VLOOKUP($B8,대상!$B:$AC,MATCH(D$2,대상!$1:$1,0)-1,FALSE),"") -> 이해섭 | E8: =IFERROR(VLOOKUP($B8,대상!$B:$AC,MATCH(E$2,대상!$1:$1,0)-1,FALSE),"") -> 정보ㆍ통신3 | F8: =IFERROR(VLOOKUP($B8,대상!$B:$AC,MATCH(F$2,대상!$1:$1,0)-1,FALSE),"") -> 모아블 OS — 비아파트 주거공간 AI 관리 자동화 플랫폼 (Agent as a Service) | G8: =IFERROR(VLOOKUP($B8,대상!$B:$AC,MATCH(G$2,대상!$1:$1,0)-1,FALSE),"") | H8: =IFERROR(VLOOKUP($B8,[1]평가!$B:$Z,MATCH(LEFT(H$2,2),[1]평가!$7:$7,0)-1,FALSE),"") -> 0 | I8: =IFERROR(VLOOKUP($B8,[1]평가!$B:$Z,MATCH(LEFT(I$2,2),[1]평가!$7:$7,0)-1,FALSE),"") -> 90 | J8: =IFERROR(VLOOKUP($B8,[1]평가!$B:$Z,MATCH(LEFT(J$2,2),[1]평가!$7:$7,0)-1,FALSE),"") -> 2 | K8: =IFERROR(VLOOKUP($B8,[2]평가!$B:$Z,MATCH(LEFT(K$2,2),[2]평가!$7:$7,0)-1,FALSE),"") -> 0 | L8: =IFERROR(VLOOKUP($B8,[2]평가!$B:$Z,MATCH(LEFT(L$2,2),[2]평가!$7:$7,0)-1,FALSE),"") -> 95 | M8: =IFERROR(VLOOKUP($B8,[2]평가!$B:$Z,MATCH(LEFT(M$2,2),[2]평가!$7:$7,0)-1,FALSE),"") -> 1 | N8: =IFERROR(VLOOKUP($B8,[3]평가!$B:$Z,MATCH(LEFT(N$2,2),[3]평가!$7:$7,0)-1,FALSE),"") -> 0 | O8: =IFERROR(VLOOKUP($B8,[3]평가!$B:$Z,MATCH(LEFT(O$2,2),[3]평가!$7:$7,0)-1,FALSE),"") -> 93 | P8: =IFERROR(VLOOKUP($B8,[3]평가!$B:$Z,MATCH(LEFT(P$2,2),[3]평가!$7:$7,0)-1,FALSE),"") -> 2 | Q8: =IFERROR(VLOOKUP($B8,[4]평가!$B:$Z,MATCH(LEFT(Q$2,2),[4]평가!$7:$7,0)-1,FALSE),"") -> 0 | R8: =IFERROR(VLOOKUP($B8,[4]평가!$B:$Z,MATCH(LEFT(R$2,2),[4]평가!$7:$7,0)-1,FALSE),"") -> 90 | S8: =IFERROR(VLOOKUP($B8,[4]평가!$B:$Z,MATCH(LEFT(S$2,2),[4]평가!$7:$7,0)-1,FALSE),"") -> 8 | T8: =IFERROR(VLOOKUP($B8,[5]평가!$B:$Z,MATCH(LEFT(T$2,2),[5]평가!$7:$7,0)-1,FALSE),"") -> 0 | U8: =IFERROR(VLOOKUP($B8,[5]평가!$B:$Z,MATCH(LEFT(U$2,2),[5]평가!$7:$7,0)-1,FALSE),"") -> 81 | V8: =IFERROR(VLOOKUP($B8,[5]평가!$B:$Z,MATCH(LEFT(V$2,2),[5]평가!$7:$7,0)-1,FALSE),"") -> 49 | W8: =IFERROR(VLOOKUP($B8,대상!$B:$AD,MATCH(W$2,대상!$1:$1,0)-1,FALSE),"") -> 0 | X8: =IF(ISBLANK(B8),"",T$1-COUNTIF(H8:V8,"회피")) -> 5 | Y8: =IF($T$1=X8,(SUM(I8,L8,O8,R8,U8)-MIN(I8,L8,O8,R8,U8)-MAX(I8,L8,O8,R8,U8))/($T$1-2),SUM(I8,L8,O8,R8,U8/X8)) -> 91 | Z8: =IFERROR(VLOOKUP($B8,대상!$B:$AD,MATCH(Z$2,대상!$1:$1,0)-1,FALSE),0) -> 0 | AA8: =IFERROR(IF(W8="면제","100"+Z8,Y8+Z8),"") -> 91 | AB8: =IF(OR(W8="면제",N(Y8)=0),"",IF(AA8<60,"과락","")) | AC8: =IF(N(AA8)=0,"",RANK(AA8,AA$3:AA$202)) -> 4 | AD8: =IFERROR(TEXT(VLOOKUP($B8,[1]평가!$B:$Z,MATCH(AD$2,[1]평가!$6:$6,0)-1,FALSE),"①@ ") & CHAR(13) & TEXT(VLOOKUP($B8,[2]평가!$B:$Z,MATCH(AD$2,[2]평가!$6:$6,0)-1,FALSE),"②@ ") & CHAR(13) & TEXT(VLOOKUP($B8,[3]평가!$B:$Z,MATCH(AD$2,[3]평가!$6:$6,0)-1,FALSE),"③@ ") & CHAR(13) & TEXT(VLOOKUP($B8,[4]평가!$B:$Z,MATCH(AD$2,[4]평가!$6:$6,0)-1,FALSE),"④@ ") & CHAR(13) & TEXT(VLOOKUP($B8,[5]평가!$B:$Z,MATCH(AD$2,[5]평가!$6:$6,0)-1,FALSE),"⑤@ "),"") -> ①26년도 15억 매출 및 프리 A 10억 투자유치위한 구체적 마케팅 방안과 IR계획 수립 요망함. _x000D_②5년간 4천호실 운영 실데이터를 보유하고 있으며 이를 활용한 AI 모델 구축을 통해 국내외 시장 확대가 가능할 것으로 보임 _x000D_③목표 시장의 설정과 수익 모델의 구조가 명확하게 제시되어 사업의 실질적인 수익 창출 가능성이 높음. 전반적인 사업 계획의 흐름과 방향성이 적정하게 설계되었음. _x000D_④인공지능 솔루션 기획단계이며 특화부분, 기술력 입증 평가하기 위한 경쟁자분석과 벤치마킹이 부족하며 수익에 대한 구체적 보완이 필요함 검증된 서비스와 사업에대한 피봇 고민이 필요해보임 _x000D_⑤창업 아이템의 배경과 목적은 비교적 구체벅으로 제시가 되어 있음. 핵심 역량 차별화를 반영한 엣지 보드 양산에 대한 내용 및 사업화를 위한 차별화 계획이 다소 부족해 보임. | AE8: =IFERROR(TEXT(VLOOKUP($B8,[1]평가!$B:$Z,MATCH(AE$2,[1]평가!$7:$7,0)-1,FALSE),"①@ ") & CHAR(13) & TEXT(VLOOKUP($B8,[2]평가!$B:$Z,MATCH(AE$2,[2]평가!$7:$7,0)-1,FALSE),"②@ ") & CHAR(13) & TEXT(VLOOKUP($B8,[3]평가!$B:$Z,MATCH(AE$2,[3]평가!$7:$7,0)-1,FALSE),"③@ ") & CHAR(13) & TEXT(VLOOKUP($B8,[4]평가!$B:$Z,MATCH(AE$2,[4]평가!$7:$7,0)-1,FALSE),"④@ ") & CHAR(13) & TEXT(VLOOKUP($B8,[5]평가!$B:$Z,MATCH(AE$2,[5]평가!$7:$7,0)-1,FALSE),"⑤@ "),"") -> 0_x000D_0_x000D_0_x000D_0_x000D_0 | AF8: =IFERROR(TEXT(VLOOKUP($B8,[1]평가!$B:$Z,MATCH(AF$2,[1]평가!$6:$6,0)-1,FALSE),"①@ ") & CHAR(13) & TEXT(VLOOKUP($B8,[2]평가!$B:$Z,MATCH(AF$2,[2]평가!$6:$6,0)-1,FALSE),"②@ ") & CHAR(13) & TEXT(VLOOKUP($B8,[3]평가!$B:$Z,MATCH(AF$2,[3]평가!$6:$6,0)-1,FALSE),"③@ ") & CHAR(13) & TEXT(VLOOKUP($B8,[4]평가!$B:$Z,MATCH(AF$2,[4]평가!$6:$6,0)-1,FALSE),"④@ ") & CHAR(13) & TEXT(VLOOKUP($B8,[5]평가!$B:$Z,MATCH(AF$2,[5]평가!$6:$6,0)-1,FALSE),"⑤@ "),"") -> 0_x000D_0_x000D_0_x000D_0_x000D_0
A9: 200 | B9: 20431043 | C9: =IFERROR(VLOOKUP($B9,대상!$B:$AC,MATCH(C$2,대상!$1:$1,0)-1,FALSE),"") -> 지역기반 | D9: =IFERROR(VLOOKUP($B9,대상!$B:$AC,MATCH(D$2,대상!$1:$1,0)-1,FALSE),"") -> 유병기 | E9: =IFERROR(VLOOKUP($B9,대상!$B:$AC,MATCH(E$2,대상!$1:$1,0)-1,FALSE),"") -> 정보ㆍ통신3 | F9: =IFERROR(VLOOKUP($B9,대상!$B:$AC,MATCH(F$2,대상!$1:$1,0)-1,FALSE),"") -> 로컬 LLM·RAG 기술이 적용된 보안 완결형 제조 지식검색 및 업무자동화 기능의 제조혁신형 AI SaaS | G9: =IFERROR(VLOOKUP($B9,대상!$B:$AC,MATCH(G$2,대상!$1:$1,0)-1,FALSE),"") | H9: =IFERROR(VLOOKUP($B9,[1]평가!$B:$Z,MATCH(LEFT(H$2,2),[1]평가!$7:$7,0)-1,FALSE),"") -> 0 | I9: =IFERROR(VLOOKUP($B9,[1]평가!$B:$Z,MATCH(LEFT(I$2,2),[1]평가!$7:$7,0)-1,FALSE),"") -> 90 | J9: =IFERROR(VLOOKUP($B9,[1]평가!$B:$Z,MATCH(LEFT(J$2,2),[1]평가!$7:$7,0)-1,FALSE),"") -> 2 | K9: =IFERROR(VLOOKUP($B9,[2]평가!$B:$Z,MATCH(LEFT(K$2,2),[2]평가!$7:$7,0)-1,FALSE),"") -> 0 | L9: =IFERROR(VLOOKUP($B9,[2]평가!$B:$Z,MATCH(LEFT(L$2,2),[2]평가!$7:$7,0)-1,FALSE),"") -> 94 | M9: =IFERROR(VLOOKUP($B9,[2]평가!$B:$Z,MATCH(LEFT(M$2,2),[2]평가!$7:$7,0)-1,FALSE),"") -> 2 | N9: =IFERROR(VLOOKUP($B9,[3]평가!$B:$Z,MATCH(LEFT(N$2,2),[3]평가!$7:$7,0)-1,FALSE),"") -> 0 | O9: =IFERROR(VLOOKUP($B9,[3]평가!$B:$Z,MATCH(LEFT(O$2,2),[3]평가!$7:$7,0)-1,FALSE),"") -> 91 | P9: =IFERROR(VLOOKUP($B9,[3]평가!$B:$Z,MATCH(LEFT(P$2,2),[3]평가!$7:$7,0)-1,FALSE),"") -> 9 | Q9: =IFERROR(VLOOKUP($B9,[4]평가!$B:$Z,MATCH(LEFT(Q$2,2),[4]평가!$7:$7,0)-1,FALSE),"") -> 0 | R9: =IFERROR(VLOOKUP($B9,[4]평가!$B:$Z,MATCH(LEFT(R$2,2),[4]평가!$7:$7,0)-1,FALSE),"") -> 92 | S9: =IFERROR(VLOOKUP($B9,[4]평가!$B:$Z,MATCH(LEFT(S$2,2),[4]평가!$7:$7,0)-1,FALSE),"") -> 3 | T9: =IFERROR(VLOOKUP($B9,[5]평가!$B:$Z,MATCH(LEFT(T$2,2),[5]평가!$7:$7,0)-1,FALSE),"") -> 0 | U9: =IFERROR(VLOOKUP($B9,[5]평가!$B:$Z,MATCH(LEFT(U$2,2),[5]평가!$7:$7,0)-1,FALSE),"") -> 84 | V9: =IFERROR(VLOOKUP($B9,[5]평가!$B:$Z,MATCH(LEFT(V$2,2),[5]평가!$7:$7,0)-1,FALSE),"") -> 26 | W9: =IFERROR(VLOOKUP($B9,대상!$B:$AD,MATCH(W$2,대상!$1:$1,0)-1,FALSE),"") -> 0 | X9: =IF(ISBLANK(B9),"",T$1-COUNTIF(H9:V9,"회피")) -> 5 | Y9: =IF($T$1=X9,(SUM(I9,L9,O9,R9,U9)-MIN(I9,L9,O9,R9,U9)-MAX(I9,L9,O9,R9,U9))/($T$1-2),SUM(I9,L9,O9,R9,U9/X9)) -> 91 | Z9: =IFERROR(VLOOKUP($B9,대상!$B:$AD,MATCH(Z$2,대상!$1:$1,0)-1,FALSE),0) -> 0 | AA9: =IFERROR(IF(W9="면제","100"+Z9,Y9+Z9),"") -> 91 | AB9: =IF(OR(W9="면제",N(Y9)=0),"",IF(AA9<60,"과락","")) | AC9: =IF(N(AA9)=0,"",RANK(AA9,AA$3:AA$202)) -> 4 | AD9: =IFERROR(TEXT(VLOOKUP($B9,[1]평가!$B:$Z,MATCH(AD$2,[1]평가!$6:$6,0)-1,FALSE),"①@ ") & CHAR(13) & TEXT(VLOOKUP($B9,[2]평가!$B:$Z,MATCH(AD$2,[2]평가!$6:$6,0)-1,FALSE),"②@ ") & CHAR(13) & TEXT(VLOOKUP($B9,[3]평가!$B:$Z,MATCH(AD$2,[3]평가!$6:$6,0)-1,FALSE),"③@ ") & CHAR(13) & TEXT(VLOOKUP($B9,[4]평가!$B:$Z,MATCH(AD$2,[4]평가!$6:$6,0)-1,FALSE),"④@ ") & CHAR(13) & TEXT(VLOOKUP($B9,[5]평가!$B:$Z,MATCH(AD$2,[5]평가!$6:$6,0)-1,FALSE),"⑤@ "),"") -> ①PoC 및 시장의 변화하는 요구사항을 지속적으로 반영한 기술 및 서비스 로드맵 수립 요망함. 추가 IR 로드맵도 보완 필요함. _x000D_②제조 특화 LLM 구축을 통한 특장점을 가져가고 있으며, 투자유치 가능성도 높은 상황으로 보여짐 _x000D_③명확한 목표 시장과 수익 구조를 갖추고 있어, 사업의 실질적인 수익 창출 가능성이 높게 평가됨. 사업 계획의 흐름과 방향성이 논리적으로 설계되어 있어 안정적인 사업 추진 기반을 확보하였음. _x000D_④LLM RAG기술이 적용된 보안 완결형 제조 지식검색 및 업무자동화 기능의 제조혁신형 AI SaaS 기획단계이며 특화부분, 기술력 입증 평가하기 위한 경쟁자분석과 벤치마킹이 부족하며 수익에 대한 구체적 보완이 필요함 팁스 및 Pre A 투자유치를 진행 중임 _x000D_⑤아이템과 관련하여 현장 실증을 통한 고도화 방안과 기술 보호 계획을 제시히고 있음. 서비스 개발을 할 수 있는 내부 역량이 있음. 다만 본격 성장을 위한 사업화 추진 전략이 다소 부족해 보임. | AE9: =IFERROR(TEXT(VLOOKUP($B9,[1]평가!$B:$Z,MATCH(AE$2,[1]평가!$7:$7,0)-1,FALSE),"①@ ") & CHAR(13) & TEXT(VLOOKUP($B9,[2]평가!$B:$Z,MATCH(AE$2,[2]평가!$7:$7,0)-1,FALSE),"②@ ") & CHAR(13) & TEXT(VLOOKUP($B9,[3]평가!$B:$Z,MATCH(AE$2,[3]평가!$7:$7,0)-1,FALSE),"③@ ") & CHAR(13) & TEXT(VLOOKUP($B9,[4]평가!$B:$Z,MATCH(AE$2,[4]평가!$7:$7,0)-1,FALSE),"④@ ") & CHAR(13) & TEXT(VLOOKUP($B9,[5]평가!$B:$Z,MATCH(AE$2,[5]평가!$7:$7,0)-1,FALSE),"⑤@ "),"") -> 0_x000D_0_x000D_0_x000D_0_x000D_0 | AF9: =IFERROR(TEXT(VLOOKUP($B9,[1]평가!$B:$Z,MATCH(AF$2,[1]평가!$6:$6,0)-1,FALSE),"①@ ") & CHAR(13) & TEXT(VLOOKUP($B9,[2]평가!$B:$Z,MATCH(AF$2,[2]평가!$6:$6,0)-1,FALSE),"②@ ") & CHAR(13) & TEXT(VLOOKUP($B9,[3]평가!$B:$Z,MATCH(AF$2,[3]평가!$6:$6,0)-1,FALSE),"③@ ") & CHAR(13) & TEXT(VLOOKUP($B9,[4]평가!$B:$Z,MATCH(AF$2,[4]평가!$6:$6,0)-1,FALSE),"④@ ") & CHAR(13) & TEXT(VLOOKUP($B9,[5]평가!$B:$Z,MATCH(AF$2,[5]평가!$6:$6,0)-1,FALSE),"⑤@ "),"") -> 0_x000D_0_x000D_0_x000D_0_x000D_0
A10: 97 | B10: 20425812 | C10: =IFERROR(VLOOKUP($B10,대상!$B:$AC,MATCH(C$2,대상!$1:$1,0)-1,FALSE),"") -> 지역기반 | D10: =IFERROR(VLOOKUP($B10,대상!$B:$AC,MATCH(D$2,대상!$1:$1,0)-1,FALSE),"") -> 이승한 | E10: =IFERROR(VLOOKUP($B10,대상!$B:$AC,MATCH(E$2,대상!$1:$1,0)-1,FALSE),"") -> 정보ㆍ통신3 | F10: =IFERROR(VLOOKUP($B10,대상!$B:$AC,MATCH(F$2,대상!$1:$1,0)-1,FALSE),"") -> 교배·해칭 기록 기반 양서파충류 모프 유전 확률 및 혈통 신뢰도 AI 시뮬레이션 기술 | G10: =IFERROR(VLOOKUP($B10,대상!$B:$AC,MATCH(G$2,대상!$1:$1,0)-1,FALSE),"") | H10: =IFERROR(VLOOKUP($B10,[1]평가!$B:$Z,MATCH(LEFT(H$2,2),[1]평가!$7:$7,0)-1,FALSE),"") -> 0 | I10: =IFERROR(VLOOKUP($B10,[1]평가!$B:$Z,MATCH(LEFT(I$2,2),[1]평가!$7:$7,0)-1,FALSE),"") -> 88 | J10: =IFERROR(VLOOKUP($B10,[1]평가!$B:$Z,MATCH(LEFT(J$2,2),[1]평가!$7:$7,0)-1,FALSE),"") -> 2 | K10: =IFERROR(VLOOKUP($B10,[2]평가!$B:$Z,MATCH(LEFT(K$2,2),[2]평가!$7:$7,0)-1,FALSE),"") -> 0 | L10: =IFERROR(VLOOKUP($B10,[2]평가!$B:$Z,MATCH(LEFT(L$2,2),[2]평가!$7:$7,0)-1,FALSE),"") -> 88 | M10: =IFERROR(VLOOKUP($B10,[2]평가!$B:$Z,MATCH(LEFT(M$2,2),[2]평가!$7:$7,0)-1,FALSE),"") -> 9 | N10: =IFERROR(VLOOKUP($B10,[3]평가!$B:$Z,MATCH(LEFT(N$2,2),[3]평가!$7:$7,0)-1,FALSE),"") -> 0 | O10: =IFERROR(VLOOKUP($B10,[3]평가!$B:$Z,MATCH(LEFT(O$2,2),[3]평가!$7:$7,0)-1,FALSE),"") -> 90 | P10: =IFERROR(VLOOKUP($B10,[3]평가!$B:$Z,MATCH(LEFT(P$2,2),[3]평가!$7:$7,0)-1,FALSE),"") -> 5 | Q10: =IFERROR(VLOOKUP($B10,[4]평가!$B:$Z,MATCH(LEFT(Q$2,2),[4]평가!$7:$7,0)-1,FALSE),"") -> 0 | R10: =IFERROR(VLOOKUP($B10,[4]평가!$B:$Z,MATCH(LEFT(R$2,2),[4]평가!$7:$7,0)-1,FALSE),"") -> 89 | S10: =IFERROR(VLOOKUP($B10,[4]평가!$B:$Z,MATCH(LEFT(S$2,2),[4]평가!$7:$7,0)-1,FALSE),"") -> 4 | T10: =IFERROR(VLOOKUP($B10,[5]평가!$B:$Z,MATCH(LEFT(T$2,2),[5]평가!$7:$7,0)-1,FALSE),"") -> 0 | U10: =IFERROR(VLOOKUP($B10,[5]평가!$B:$Z,MATCH(LEFT(U$2,2),[5]평가!$7:$7,0)-1,FALSE),"") -> 89 | V10: =IFERROR(VLOOKUP($B10,[5]평가!$B:$Z,MATCH(LEFT(V$2,2),[5]평가!$7:$7,0)-1,FALSE),"") -> 10 | W10: =IFERROR(VLOOKUP($B10,대상!$B:$AD,MATCH(W$2,대상!$1:$1,0)-1,FALSE),"") -> 0 | X10: =IF(ISBLANK(B10),"",T$1-COUNTIF(H10:V10,"회피")) -> 5 | Y10: =IF($T$1=X10,(SUM(I10,L10,O10,R10,U10)-MIN(I10,L10,O10,R10,U10)-MAX(I10,L10,O10,R10,U10))/($T$1-2),SUM(I10,L10,O10,R10,U10/X10)) -> 88.666667 | Z10: =IFERROR(VLOOKUP($B10,대상!$B:$AD,MATCH(Z$2,대상!$1:$1,0)-1,FALSE),0) -> 2 | AA10: =IFERROR(IF(W10="면제","100"+Z10,Y10+Z10),"") -> 90.666667 | AB10: =IF(OR(W10="면제",N(Y10)=0),"",IF(AA10<60,"과락","")) | AC10: =IF(N(AA10)=0,"",RANK(AA10,AA$3:AA$202)) -> 8 | AD10: =IFERROR(TEXT(VLOOKUP($B10,[1]평가!$B:$Z,MATCH(AD$2,[1]평가!$6:$6,0)-1,FALSE),"①@ ") & CHAR(13) & TEXT(VLOOKUP($B10,[2]평가!$B:$Z,MATCH(AD$2,[2]평가!$6:$6,0)-1,FALSE),"②@ ") & CHAR(13) & TEXT(VLOOKUP($B10,[3]평가!$B:$Z,MATCH(AD$2,[3]평가!$6:$6,0)-1,FALSE),"③@ ") & CHAR(13) & TEXT(VLOOKUP($B10,[4]평가!$B:$Z,MATCH(AD$2,[4]평가!$6:$6,0)-1,FALSE),"④@ ") & CHAR(13) & TEXT(VLOOKUP($B10,[5]평가!$B:$Z,MATCH(AD$2,[5]평가!$6:$6,0)-1,FALSE),"⑤@ "),"") -> ①보유한 데이터를기반으로 초기시장진입위한 마케팅계획을 구체화하고 inbound브리더유입위한 구체적 확보방안 수립 요망 _x000D_②12만 마리 규모의 데이터 확보를 기반으로 본 아이템을 추진중인 것으로 보이며, 홍보를 위한 풀 및 채널도 보유중으로 실현가능성 높아 보임. 수익모델은 다소 약해보이긴 하여 이에 대한 고민은 필요해 보임 _x000D_③시장진입대상과 수익구조가 비교적 명확하게 제시되었음. 그리고 사업계획의 방향성은 적절한것으로 판단됨. _x000D_④2D횡스크롤 액션 수집형 RPG와 길드 경영힐링 SNG가 결합된 하이브리드 모바일 게임 기획단계이며 특화부분, 기술력 입증 평가하기 위한 경쟁자분석과 벤치마킹이 부족하며 수익에 대한 구체적 보완이 필요함 _x000D_⑤다양한 마케팅 등 성과 보유 및 데이터를 활용한 AI분석 과금모델을 가지고 있어 추진계획의 완성도가 높아 보임. | AE10: =IFERROR(TEXT(VLOOKUP($B10,[1]평가!$B:$Z,MATCH(AE$2,[1]평가!$7:$7,0)-1,FALSE),"①@ ") & CHAR(13) & TEXT(VLOOKUP($B10,[2]평가!$B:$Z,MATCH(AE$2,[2]평가!$7:$7,0)-1,FALSE),"②@ ") & CHAR(13) & TEXT(VLOOKUP($B10,[3]평가!$B:$Z,MATCH(AE$2,[3]평가!$7:$7,0)-1,FALSE),"③@ ") & CHAR(13) & TEXT(VLOOKUP($B10,[4]평가!$B:$Z,MATCH(AE$2,[4]평가!$7:$7,0)-1,FALSE),"④@ ") & CHAR(13) & TEXT(VLOOKUP($B10,[5]평가!$B:$Z,MATCH(AE$2,[5]평가!$7:$7,0)-1,FALSE),"⑤@ "),"") -> 0_x000D_0_x000D_0_x000D_0_x000D_0 | AF10: =IFERROR(TEXT(VLOOKUP($B10,[1]평가!$B:$Z,MATCH(AF$2,[1]평가!$6:$6,0)-1,FALSE),"①@ ") & CHAR(13) & TEXT(VLOOKUP($B10,[2]평가!$B:$Z,MATCH(AF$2,[2]평가!$6:$6,0)-1,FALSE),"②@ ") & CHAR(13) & TEXT(VLOOKUP($B10,[3]평가!$B:$Z,MATCH(AF$2,[3]평가!$6:$6,0)-1,FALSE),"③@ ") & CHAR(13) & TEXT(VLOOKUP($B10,[4]평가!$B:$Z,MATCH(AF$2,[4]평가!$6:$6,0)-1,FALSE),"④@ ") & CHAR(13) & TEXT(VLOOKUP($B10,[5]평가!$B:$Z,MATCH(AF$2,[5]평가!$6:$6,0)-1,FALSE),"⑤@ "),"") -> 0_x000D_0_x000D_0_x000D_0_x000D_0
A11: 112 | B11: 20425943 | C11: =IFERROR(VLOOKUP($B11,대상!$B:$AC,MATCH(C$2,대상!$1:$1,0)-1,FALSE),"") -> 지역기반 | D11: =IFERROR(VLOOKUP($B11,대상!$B:$AC,MATCH(D$2,대상!$1:$1,0)-1,FALSE),"") -> 김태우 | E11: =IFERROR(VLOOKUP($B11,대상!$B:$AC,MATCH(E$2,대상!$1:$1,0)-1,FALSE),"") -> 정보ㆍ통신3 | F11: =IFERROR(VLOOKUP($B11,대상!$B:$AC,MATCH(F$2,대상!$1:$1,0)-1,FALSE),"") -> 바쁜 현대인 부모를 위한 아이 식단 데이터 기반 AI 영양소 맞춤화 관리 서비스 | G11: =IFERROR(VLOOKUP($B11,대상!$B:$AC,MATCH(G$2,대상!$1:$1,0)-1,FALSE),"") | H11: =IFERROR(VLOOKUP($B11,[1]평가!$B:$Z,MATCH(LEFT(H$2,2),[1]평가!$7:$7,0)-1,FALSE),"") -> 0 | I11: =IFERROR(VLOOKUP($B11,[1]평가!$B:$Z,MATCH(LEFT(I$2,2),[1]평가!$7:$7,0)-1,FALSE),"") -> 90 | J11: =IFERROR(VLOOKUP($B11,[1]평가!$B:$Z,MATCH(LEFT(J$2,2),[1]평가!$7:$7,0)-1,FALSE),"") -> 2 | K11: =IFERROR(VLOOKUP($B11,[2]평가!$B:$Z,MATCH(LEFT(K$2,2),[2]평가!$7:$7,0)-1,FALSE),"") -> 0 | L11: =IFERROR(VLOOKUP($B11,[2]평가!$B:$Z,MATCH(LEFT(L$2,2),[2]평가!$7:$7,0)-1,FALSE),"") -> 92 | M11: =IFERROR(VLOOKUP($B11,[2]평가!$B:$Z,MATCH(LEFT(M$2,2),[2]평가!$7:$7,0)-1,FALSE),"") -> 4 | N11: =IFERROR(VLOOKUP($B11,[3]평가!$B:$Z,MATCH(LEFT(N$2,2),[3]평가!$7:$7,0)-1,FALSE),"") -> 0 | O11: =IFERROR(VLOOKUP($B11,[3]평가!$B:$Z,MATCH(LEFT(O$2,2),[3]평가!$7:$7,0)-1,FALSE),"") -> 92 | P11: =IFERROR(VLOOKUP($B11,[3]평가!$B:$Z,MATCH(LEFT(P$2,2),[3]평가!$7:$7,0)-1,FALSE),"") -> 5 | Q11: =IFERROR(VLOOKUP($B11,[4]평가!$B:$Z,MATCH(LEFT(Q$2,2),[4]평가!$7:$7,0)-1,FALSE),"") -> 0 | R11: =IFERROR(VLOOKUP($B11,[4]평가!$B:$Z,MATCH(LEFT(R$2,2),[4]평가!$7:$7,0)-1,FALSE),"") -> 90 | S11: =IFERROR(VLOOKUP($B11,[4]평가!$B:$Z,MATCH(LEFT(S$2,2),[4]평가!$7:$7,0)-1,FALSE),"") -> 8 | T11: =IFERROR(VLOOKUP($B11,[5]평가!$B:$Z,MATCH(LEFT(T$2,2),[5]평가!$7:$7,0)-1,FALSE),"") -> 0 | U11: =IFERROR(VLOOKUP($B11,[5]평가!$B:$Z,MATCH(LEFT(U$2,2),[5]평가!$7:$7,0)-1,FALSE),"") -> 80 | V11: =IFERROR(VLOOKUP($B11,[5]평가!$B:$Z,MATCH(LEFT(V$2,2),[5]평가!$7:$7,0)-1,FALSE),"") -> 57 | W11: =IFERROR(VLOOKUP($B11,대상!$B:$AD,MATCH(W$2,대상!$1:$1,0)-1,FALSE),"") -> 0 | X11: =IF(ISBLANK(B11),"",T$1-COUNTIF(H11:V11,"회피")) -> 5 | Y11: =IF($T$1=X11,(SUM(I11,L11,O11,R11,U11)-MIN(I11,L11,O11,R11,U11)-MAX(I11,L11,O11,R11,U11))/($T$1-2),SUM(I11,L11,O11,R11,U11/X11)) -> 90.666667 | Z11: =IFERROR(VLOOKUP($B11,대상!$B:$AD,MATCH(Z$2,대상!$1:$1,0)-1,FALSE),0) -> 0 | AA11: =IFERROR(IF(W11="면제","100"+Z11,Y11+Z11),"") -> 90.666667 | AB11: =IF(OR(W11="면제",N(Y11)=0),"",IF(AA11<60,"과락","")) | AC11: =IF(N(AA11)=0,"",RANK(AA11,AA$3:AA$202)) -> 8 | AD11: =IFERROR(TEXT(VLOOKUP($B11,[1]평가!$B:$Z,MATCH(AD$2,[1]평가!$6:$6,0)-1,FALSE),"①@ ") & CHAR(13) & TEXT(VLOOKUP($B11,[2]평가!$B:$Z,MATCH(AD$2,[2]평가!$6:$6,0)-1,FALSE),"②@ ") & CHAR(13) & TEXT(VLOOKUP($B11,[3]평가!$B:$Z,MATCH(AD$2,[3]평가!$6:$6,0)-1,FALSE),"③@ ") & CHAR(13) & TEXT(VLOOKUP($B11,[4]평가!$B:$Z,MATCH(AD$2,[4]평가!$6:$6,0)-1,FALSE),"④@ ") & CHAR(13) & TEXT(VLOOKUP($B11,[5]평가!$B:$Z,MATCH(AD$2,[5]평가!$6:$6,0)-1,FALSE),"⑤@ "),"") -> ①유사경쟁서비스와의 차별화 요서를 지속발굴하고 초기고객확보 및 초기시장 진입위한 마케팅전략 구체화 요망함 _x000D_②실질적인 성과들이 나오는 시점으로 지속적인 서비스고도화가 진행되면 해당 시장에서의 시장 점유율을 홥대해 나갈 수 있을 것으로 보임. 예상 매출치가 낮은데 이를 확대시킬 수 있는 방안 마련 필요. B2B 매출 확장 전략 보완이 되면 좋을것임 _x000D_③목표 시장의 설정과 수익 모델의 구조가 명확하게 제시되어 사업의 실질적인 수익 창출 가능성이 높음. 전반적인 사업 계획의 흐름과 방향성이 적정하게 설계되었으며, 시장 안착을 위한 논리적 근거가 충분히 마련되었음. _x000D_④AI기반 영양분석 및 성장 관리 서비스 기획단계이며 특화부분, 기술력 입증 평가하기 위한 경쟁자분석과 벤치마킹이 부족하며 수익에 대한 구체적 보완이 필요함 _x000D_⑤아이템과 관련하여 경쟁사와 차별화 내용을 제시하고 있음.. 다만 사업화를 달성할 수 있는 추진 전략이 다소 부족해 보임. | AE11: =IFERROR(TEXT(VLOOKUP($B11,[1]평가!$B:$Z,MATCH(AE$2,[1]평가!$7:$7,0)-1,FALSE),"①@ ") & CHAR(13) & TEXT(VLOOKUP($B11,[2]평가!$B:$Z,MATCH(AE$2,[2]평가!$7:$7,0)-1,FALSE),"②@ ") & CHAR(13) & TEXT(VLOOKUP($B11,[3]평가!$B:$Z,MATCH(AE$2,[3]평가!$7:$7,0)-1,FALSE),"③@ ") & CHAR(13) & TEXT(VLOOKUP($B11,[4]평가!$B:$Z,MATCH(AE$2,[4]평가!$7:$7,0)-1,FALSE),"④@ ") & CHAR(13) & TEXT(VLOOKUP($B11,[5]평가!$B:$Z,MATCH(AE$2,[5]평가!$7:$7,0)-1,FALSE),"⑤@ "),"") -> 0_x000D_0_x000D_0_x000D_0_x000D_0 | AF11: =IFERROR(TEXT(VLOOKUP($B11,[1]평가!$B:$Z,MATCH(AF$2,[1]평가!$6:$6,0)-1,FALSE),"①@ ") & CHAR(13) & TEXT(VLOOKUP($B11,[2]평가!$B:$Z,MATCH(AF$2,[2]평가!$6:$6,0)-1,FALSE),"②@ ") & CHAR(13) & TEXT(VLOOKUP($B11,[3]평가!$B:$Z,MATCH(AF$2,[3]평가!$6:$6,0)-1,FALSE),"③@ ") & CHAR(13) & TEXT(VLOOKUP($B11,[4]평가!$B:$Z,MATCH(AF$2,[4]평가!$6:$6,0)-1,FALSE),"④@ ") & CHAR(13) & TEXT(VLOOKUP($B11,[5]평가!$B:$Z,MATCH(AF$2,[5]평가!$6:$6,0)-1,FALSE),"⑤@ "),"") -> 0_x000D_0_x000D_0_x000D_0_x000D_0
A12: 153 | B12: 20426678 | C12: =IFERROR(VLOOKUP($B12,대상!$B:$AC,MATCH(C$2,대상!$1:$1,0)-1,FALSE),"") -> 지역기반 | D12: =IFERROR(VLOOKUP($B12,대상!$B:$AC,MATCH(D$2,대상!$1:$1,0)-1,FALSE),"") -> 이효석 | E12: =IFERROR(VLOOKUP($B12,대상!$B:$AC,MATCH(E$2,대상!$1:$1,0)-1,FALSE),"") -> 정보ㆍ통신3 | F12: =IFERROR(VLOOKUP($B12,대상!$B:$AC,MATCH(F$2,대상!$1:$1,0)-1,FALSE),"") -> Opti AI | G12: =IFERROR(VLOOKUP($B12,대상!$B:$AC,MATCH(G$2,대상!$1:$1,0)-1,FALSE),"") | H12: =IFERROR(VLOOKUP($B12,[1]평가!$B:$Z,MATCH(LEFT(H$2,2),[1]평가!$7:$7,0)-1,FALSE),"") -> 0 | I12: =IFERROR(VLOOKUP($B12,[1]평가!$B:$Z,MATCH(LEFT(I$2,2),[1]평가!$7:$7,0)-1,FALSE),"") -> 90 | J12: =IFERROR(VLOOKUP($B12,[1]평가!$B:$Z,MATCH(LEFT(J$2,2),[1]평가!$7:$7,0)-1,FALSE),"") -> 2 | K12: =IFERROR(VLOOKUP($B12,[2]평가!$B:$Z,MATCH(LEFT(K$2,2),[2]평가!$7:$7,0)-1,FALSE),"") -> 0 | L12: =IFERROR(VLOOKUP($B12,[2]평가!$B:$Z,MATCH(LEFT(L$2,2),[2]평가!$7:$7,0)-1,FALSE),"") -> 92 | M12: =IFERROR(VLOOKUP($B12,[2]평가!$B:$Z,MATCH(LEFT(M$2,2),[2]평가!$7:$7,0)-1,FALSE),"") -> 4 | N12: =IFERROR(VLOOKUP($B12,[3]평가!$B:$Z,MATCH(LEFT(N$2,2),[3]평가!$7:$7,0)-1,FALSE),"") -> 0 | O12: =IFERROR(VLOOKUP($B12,[3]평가!$B:$Z,MATCH(LEFT(O$2,2),[3]평가!$7:$7,0)-1,FALSE),"") -> 92 | P12: =IFERROR(VLOOKUP($B12,[3]평가!$B:$Z,MATCH(LEFT(P$2,2),[3]평가!$7:$7,0)-1,FALSE),"") -> 5 | Q12: =IFERROR(VLOOKUP($B12,[4]평가!$B:$Z,MATCH(LEFT(Q$2,2),[4]평가!$7:$7,0)-1,FALSE),"") -> 0 | R12: =IFERROR(VLOOKUP($B12,[4]평가!$B:$Z,MATCH(LEFT(R$2,2),[4]평가!$7:$7,0)-1,FALSE),"") -> 90 | S12: =IFERROR(VLOOKUP($B12,[4]평가!$B:$Z,MATCH(LEFT(S$2,2),[4]평가!$7:$7,0)-1,FALSE),"") -> 8 | T12: =IFERROR(VLOOKUP($B12,[5]평가!$B:$Z,MATCH(LEFT(T$2,2),[5]평가!$7:$7,0)-1,FALSE),"") -> 0 | U12: =IFERROR(VLOOKUP($B12,[5]평가!$B:$Z,MATCH(LEFT(U$2,2),[5]평가!$7:$7,0)-1,FALSE),"") -> 88 | V12: =IFERROR(VLOOKUP($B12,[5]평가!$B:$Z,MATCH(LEFT(V$2,2),[5]평가!$7:$7,0)-1,FALSE),"") -> 13 | W12: =IFERROR(VLOOKUP($B12,대상!$B:$AD,MATCH(W$2,대상!$1:$1,0)-1,FALSE),"") -> 0 | X12: =IF(ISBLANK(B12),"",T$1-COUNTIF(H12:V12,"회피")) -> 5 | Y12: =IF($T$1=X12,(SUM(I12,L12,O12,R12,U12)-MIN(I12,L12,O12,R12,U12)-MAX(I12,L12,O12,R12,U12))/($T$1-2),SUM(I12,L12,O12,R12,U12/X12)) -> 90.666667 | Z12: =IFERROR(VLOOKUP($B12,대상!$B:$AD,MATCH(Z$2,대상!$1:$1,0)-1,FALSE),0) -> 0 | AA12: =IFERROR(IF(W12="면제","100"+Z12,Y12+Z12),"") -> 90.666667 | AB12: =IF(OR(W12="면제",N(Y12)=0),"",IF(AA12<60,"과락","")) | AC12: =IF(N(AA12)=0,"",RANK(AA12,AA$3:AA$202)) -> 8 | AD12: =IFERROR(TEXT(VLOOKUP($B12,[1]평가!$B:$Z,MATCH(AD$2,[1]평가!$6:$6,0)-1,FALSE),"①@ ") & CHAR(13) & TEXT(VLOOKUP($B12,[2]평가!$B:$Z,MATCH(AD$2,[2]평가!$6:$6,0)-1,FALSE),"②@ ") & CHAR(13) & TEXT(VLOOKUP($B12,[3]평가!$B:$Z,MATCH(AD$2,[3]평가!$6:$6,0)-1,FALSE),"③@ ") & CHAR(13) & TEXT(VLOOKUP($B12,[4]평가!$B:$Z,MATCH(AD$2,[4]평가!$6:$6,0)-1,FALSE),"④@ ") & CHAR(13) & TEXT(VLOOKUP($B12,[5]평가!$B:$Z,MATCH(AD$2,[5]평가!$6:$6,0)-1,FALSE),"⑤@ "),"") -> ①시장확장위한 마케팅 채널 확보방안 수립 요망.투자유치관련 IR로드맵 구체화 필요함 _x000D_②POC 검증 완료 및 정식 추리를 앞두고 있는 상황으로 시드 투자 확정 등 향후 지속 성장기반 마련중 _x000D_③목표 시장의 설정과 수익 모델의 구조가 명확하게 제시되어 사업의 실질적인 수익 창출 가능성이 높음. 전반적인 사업 계획의 흐름과 방향성이 적정하게 설계되었으며, 시장 안착을 위한 논리적 근거가 충분히 마련되었음. _x000D_④GEO/AEO컨설팅, AI SaaS 플랫폼 기획단계이며 특화부분, 기술력 입증 평가하기 위한 경쟁자분석과 벤치마킹이 부족하며 수익에 대한 구체적 보완이 필요함 _x000D_⑤목표시장과 수익모델은 비교적 명확하게 제시되었음. 사업 개발을 위한 기본 역량을 갖춘것으로 보여짐. 협약 기간내 3명의 추가 고용계획을 가지고 있음. | AE12: =IFERROR(TEXT(VLOOKUP($B12,[1]평가!$B:$Z,MATCH(AE$2,[1]평가!$7:$7,0)-1,FALSE),"①@ ") & CHAR(13) & TEXT(VLOOKUP($B12,[2]평가!$B:$Z,MATCH(AE$2,[2]평가!$7:$7,0)-1,FALSE),"②@ ") & CHAR(13) & TEXT(VLOOKUP($B12,[3]평가!$B:$Z,MATCH(AE$2,[3]평가!$7:$7,0)-1,FALSE),"③@ ") & CHAR(13) & TEXT(VLOOKUP($B12,[4]평가!$B:$Z,MATCH(AE$2,[4]평가!$7:$7,0)-1,FALSE),"④@ ") & CHAR(13) & TEXT(VLOOKUP($B12,[5]평가!$B:$Z,MATCH(AE$2,[5]평가!$7:$7,0)-1,FALSE),"⑤@ "),"") -> 0_x000D_0_x000D_0_x000D_0_x000D_0 | AF12: =IFERROR(TEXT(VLOOKUP($B12,[1]평가!$B:$Z,MATCH(AF$2,[1]평가!$6:$6,0)-1,FALSE),"①@ ") & CHAR(13) & TEXT(VLOOKUP($B12,[2]평가!$B:$Z,MATCH(AF$2,[2]평가!$6:$6,0)-1,FALSE),"②@ ") & CHAR(13) & TEXT(VLOOKUP($B12,[3]평가!$B:$Z,MATCH(AF$2,[3]평가!$6:$6,0)-1,FALSE),"③@ ") & CHAR(13) & TEXT(VLOOKUP($B12,[4]평가!$B:$Z,MATCH(AF$2,[4]평가!$6:$6,0)-1,FALSE),"④@ ") & CHAR(13) & TEXT(VLOOKUP($B12,[5]평가!$B:$Z,MATCH(AF$2,[5]평가!$6:$6,0)-1,FALSE),"⑤@ "),"") -> 0_x000D_0_x000D_0_x000D_0_x000D_0
A13: 186 | B13: 20428346 | C13: =IFERROR(VLOOKUP($B13,대상!$B:$AC,MATCH(C$2,대상!$1:$1,0)-1,FALSE),"") -> 지역기반 | D13: =IFERROR(VLOOKUP($B13,대상!$B:$AC,MATCH(D$2,대상!$1:$1,0)-1,FALSE),"") -> 김태겸 | E13: =IFERROR(VLOOKUP($B13,대상!$B:$AC,MATCH(E$2,대상!$1:$1,0)-1,FALSE),"") -> 정보ㆍ통신3 | F13: =IFERROR(VLOOKUP($B13,대상!$B:$AC,MATCH(F$2,대상!$1:$1,0)-1,FALSE),"") -> 실시간 멀티플레이어 LBE AIoT 플랫폼 고도화 | G13: =IFERROR(VLOOKUP($B13,대상!$B:$AC,MATCH(G$2,대상!$1:$1,0)-1,FALSE),"") | H13: =IFERROR(VLOOKUP($B13,[1]평가!$B:$Z,MATCH(LEFT(H$2,2),[1]평가!$7:$7,0)-1,FALSE),"") -> 0 | I13: =IFERROR(VLOOKUP($B13,[1]평가!$B:$Z,MATCH(LEFT(I$2,2),[1]평가!$7:$7,0)-1,FALSE),"") -> 90 | J13: =IFERROR(VLOOKUP($B13,[1]평가!$B:$Z,MATCH(LEFT(J$2,2),[1]평가!$7:$7,0)-1,FALSE),"") -> 2 | K13: =IFERROR(VLOOKUP($B13,[2]평가!$B:$Z,MATCH(LEFT(K$2,2),[2]평가!$7:$7,0)-1,FALSE),"") -> 0 | L13: =IFERROR(VLOOKUP($B13,[2]평가!$B:$Z,MATCH(LEFT(L$2,2),[2]평가!$7:$7,0)-1,FALSE),"") -> 90 | M13: =IFERROR(VLOOKUP($B13,[2]평가!$B:$Z,MATCH(LEFT(M$2,2),[2]평가!$7:$7,0)-1,FALSE),"") -> 9 | N13: =IFERROR(VLOOKUP($B13,[3]평가!$B:$Z,MATCH(LEFT(N$2,2),[3]평가!$7:$7,0)-1,FALSE),"") -> 0 | O13: =IFERROR(VLOOKUP($B13,[3]평가!$B:$Z,MATCH(LEFT(O$2,2),[3]평가!$7:$7,0)-1,FALSE),"") -> 93 | P13: =IFERROR(VLOOKUP($B13,[3]평가!$B:$Z,MATCH(LEFT(P$2,2),[3]평가!$7:$7,0)-1,FALSE),"") -> 2 | Q13: =IFERROR(VLOOKUP($B13,[4]평가!$B:$Z,MATCH(LEFT(Q$2,2),[4]평가!$7:$7,0)-1,FALSE),"") -> 0 | R13: =IFERROR(VLOOKUP($B13,[4]평가!$B:$Z,MATCH(LEFT(R$2,2),[4]평가!$7:$7,0)-1,FALSE),"") -> 91 | S13: =IFERROR(VLOOKUP($B13,[4]평가!$B:$Z,MATCH(LEFT(S$2,2),[4]평가!$7:$7,0)-1,FALSE),"") -> 4 | T13: =IFERROR(VLOOKUP($B13,[5]평가!$B:$Z,MATCH(LEFT(T$2,2),[5]평가!$7:$7,0)-1,FALSE),"") -> 0 | U13: =IFERROR(VLOOKUP($B13,[5]평가!$B:$Z,MATCH(LEFT(U$2,2),[5]평가!$7:$7,0)-1,FALSE),"") -> 79 | V13: =IFERROR(VLOOKUP($B13,[5]평가!$B:$Z,MATCH(LEFT(V$2,2),[5]평가!$7:$7,0)-1,FALSE),"") -> 70 | W13: =IFERROR(VLOOKUP($B13,대상!$B:$AD,MATCH(W$2,대상!$1:$1,0)-1,FALSE),"") -> 0 | X13: =IF(ISBLANK(B13),"",T$1-COUNTIF(H13:V13,"회피")) -> 5 | Y13: =IF($T$1=X13,(SUM(I13,L13,O13,R13,U13)-MIN(I13,L13,O13,R13,U13)-MAX(I13,L13,O13,R13,U13))/($T$1-2),SUM(I13,L13,O13,R13,U13/X13)) -> 90.333333 | Z13: =IFERROR(VLOOKUP($B13,대상!$B:$AD,MATCH(Z$2,대상!$1:$1,0)-1,FALSE),0) -> 0 | AA13: =IFERROR(IF(W13="면제","100"+Z13,Y13+Z13),"") -> 90.333333 | AB13: =IF(OR(W13="면제",N(Y13)=0),"",IF(AA13<60,"과락","")) | AC13: =IF(N(AA13)=0,"",RANK(AA13,AA$3:AA$202)) -> 11 | AD13: =IFERROR(TEXT(VLOOKUP($B13,[1]평가!$B:$Z,MATCH(AD$2,[1]평가!$6:$6,0)-1,FALSE),"①@ ") & CHAR(13) & TEXT(VLOOKUP($B13,[2]평가!$B:$Z,MATCH(AD$2,[2]평가!$6:$6,0)-1,FALSE),"②@ ") & CHAR(13) & TEXT(VLOOKUP($B13,[3]평가!$B:$Z,MATCH(AD$2,[3]평가!$6:$6,0)-1,FALSE),"③@ ") & CHAR(13) & TEXT(VLOOKUP($B13,[4]평가!$B:$Z,MATCH(AD$2,[4]평가!$6:$6,0)-1,FALSE),"④@ ") & CHAR(13) & TEXT(VLOOKUP($B13,[5]평가!$B:$Z,MATCH(AD$2,[5]평가!$6:$6,0)-1,FALSE),"⑤@ "),"") -> ①LBE게임기반의 사업확장에 대한 근거데이터 확보와 객관성검증의 선제적 분석이 필요함. 향후 투자유치위한 IR게획의 구체화된 일정 보완 요망 _x000D_②기술기반의 아이템이 좋고 매출 성장이 기대됨 _x000D_③목표 시장의 설정과 수익 모델의 구조가 명확하게 제시되어 사업의 실질적인 수익 창출 가능성이 높음. 전반적인 사업 계획의 흐름과 방향성이 적정하게 설계되었음. _x000D_④4년간 2개의 직영매장을 통한 누적 방문객 15만명의 데이터를 기반으로 운영 재현성을 구성하여 AIoT, E스포츠로 편성하였음, 또한 DDA엔진으로 구성하여 기존 방탈출, 레이저태그VR의 차별화전략을 함(실시간 자율제어), 고객 다양성 확보함, 초기관광벤처 선정 후 특허 등록 완료함 _x000D_⑤창업 아이템의 수익모델이 객관적이고 구체적으로 제시되어 있으나 자사 모델의 차별화 및 사업화를 위한 전략 방안은 다소 부족해 보임. | AE13: =IFERROR(TEXT(VLOOKUP($B13,[1]평가!$B:$Z,MATCH(AE$2,[1]평가!$7:$7,0)-1,FALSE),"①@ ") & CHAR(13) & TEXT(VLOOKUP($B13,[2]평가!$B:$Z,MATCH(AE$2,[2]평가!$7:$7,0)-1,FALSE),"②@ ") & CHAR(13) & TEXT(VLOOKUP($B13,[3]평가!$B:$Z,MATCH(AE$2,[3]평가!$7:$7,0)-1,FALSE),"③@ ") & CHAR(13) & TEXT(VLOOKUP($B13,[4]평가!$B:$Z,MATCH(AE$2,[4]평가!$7:$7,0)-1,FALSE),"④@ ") & CHAR(13) & TEXT(VLOOKUP($B13,[5]평가!$B:$Z,MATCH(AE$2,[5]평가!$7:$7,0)-1,FALSE),"⑤@ "),"") -> 0_x000D_0_x000D_0_x000D_0_x000D_0 | AF13: =IFERROR(TEXT(VLOOKUP($B13,[1]평가!$B:$Z,MATCH(AF$2,[1]평가!$6:$6,0)-1,FALSE),"①@ ") & CHAR(13) & TEXT(VLOOKUP($B13,[2]평가!$B:$Z,MATCH(AF$2,[2]평가!$6:$6,0)-1,FALSE),"②@ ") & CHAR(13) & TEXT(VLOOKUP($B13,[3]평가!$B:$Z,MATCH(AF$2,[3]평가!$6:$6,0)-1,FALSE),"③@ ") & CHAR(13) & TEXT(VLOOKUP($B13,[4]평가!$B:$Z,MATCH(AF$2,[4]평가!$6:$6,0)-1,FALSE),"④@ ") & CHAR(13) & TEXT(VLOOKUP($B13,[5]평가!$B:$Z,MATCH(AF$2,[5]평가!$6:$6,0)-1,FALSE),"⑤@ "),"") -> 0_x000D_0_x000D_0_x000D_0_x000D_0
A14: 193 | B14: 20415268 | C14: =IFERROR(VLOOKUP($B14,대상!$B:$AC,MATCH(C$2,대상!$1:$1,0)-1,FALSE),"") -> 지역기반 | D14: =IFERROR(VLOOKUP($B14,대상!$B:$AC,MATCH(D$2,대상!$1:$1,0)-1,FALSE),"") -> 민진하 | E14: =IFERROR(VLOOKUP($B14,대상!$B:$AC,MATCH(E$2,대상!$1:$1,0)-1,FALSE),"") -> 정보ㆍ통신3 | F14: =IFERROR(VLOOKUP($B14,대상!$B:$AC,MATCH(F$2,대상!$1:$1,0)-1,FALSE),"") -> FortunePic | G14: =IFERROR(VLOOKUP($B14,대상!$B:$AC,MATCH(G$2,대상!$1:$1,0)-1,FALSE),"") | H14: =IFERROR(VLOOKUP($B14,[1]평가!$B:$Z,MATCH(LEFT(H$2,2),[1]평가!$7:$7,0)-1,FALSE),"") -> 0 | I14: =IFERROR(VLOOKUP($B14,[1]평가!$B:$Z,MATCH(LEFT(I$2,2),[1]평가!$7:$7,0)-1,FALSE),"") -> 85 | J14: =IFERROR(VLOOKUP($B14,[1]평가!$B:$Z,MATCH(LEFT(J$2,2),[1]평가!$7:$7,0)-1,FALSE),"") -> 19 | K14: =IFERROR(VLOOKUP($B14,[2]평가!$B:$Z,MATCH(LEFT(K$2,2),[2]평가!$7:$7,0)-1,FALSE),"") -> 0 | L14: =IFERROR(VLOOKUP($B14,[2]평가!$B:$Z,MATCH(LEFT(L$2,2),[2]평가!$7:$7,0)-1,FALSE),"") -> 80 | M14: =IFERROR(VLOOKUP($B14,[2]평가!$B:$Z,MATCH(LEFT(M$2,2),[2]평가!$7:$7,0)-1,FALSE),"") -> 47 | N14: =IFERROR(VLOOKUP($B14,[3]평가!$B:$Z,MATCH(LEFT(N$2,2),[3]평가!$7:$7,0)-1,FALSE),"") -> 0 | O14: =IFERROR(VLOOKUP($B14,[3]평가!$B:$Z,MATCH(LEFT(O$2,2),[3]평가!$7:$7,0)-1,FALSE),"") -> 89 | P14: =IFERROR(VLOOKUP($B14,[3]평가!$B:$Z,MATCH(LEFT(P$2,2),[3]평가!$7:$7,0)-1,FALSE),"") -> 11 | Q14: =IFERROR(VLOOKUP($B14,[4]평가!$B:$Z,MATCH(LEFT(Q$2,2),[4]평가!$7:$7,0)-1,FALSE),"") -> 0 | R14: =IFERROR(VLOOKUP($B14,[4]평가!$B:$Z,MATCH(LEFT(R$2,2),[4]평가!$7:$7,0)-1,FALSE),"") -> 89 | S14: =IFERROR(VLOOKUP($B14,[4]평가!$B:$Z,MATCH(LEFT(S$2,2),[4]평가!$7:$7,0)-1,FALSE),"") -> 11 | T14: =IFERROR(VLOOKUP($B14,[5]평가!$B:$Z,MATCH(LEFT(T$2,2),[5]평가!$7:$7,0)-1,FALSE),"") -> 0 | U14: =IFERROR(VLOOKUP($B14,[5]평가!$B:$Z,MATCH(LEFT(U$2,2),[5]평가!$7:$7,0)-1,FALSE),"") -> 77 | V14: =IFERROR(VLOOKUP($B14,[5]평가!$B:$Z,MATCH(LEFT(V$2,2),[5]평가!$7:$7,0)-1,FALSE),"") -> 93 | W14: =IFERROR(VLOOKUP($B14,대상!$B:$AD,MATCH(W$2,대상!$1:$1,0)-1,FALSE),"") -> 0 | X14: =IF(ISBLANK(B14),"",T$1-COUNTIF(H14:V14,"회피")) -> 5 | Y14: =IF($T$1=X14,(SUM(I14,L14,O14,R14,U14)-MIN(I14,L14,O14,R14,U14)-MAX(I14,L14,O14,R14,U14))/($T$1-2),SUM(I14,L14,O14,R14,U14/X14)) -> 84.666667 | Z14: =IFERROR(VLOOKUP($B14,대상!$B:$AD,MATCH(Z$2,대상!$1:$1,0)-1,FALSE),0) -> 0 | AA14: =IFERROR(IF(W14="면제","100"+Z14,Y14+Z14),"") -> 84.666667 | AB14: =IF(OR(W14="면제",N(Y14)=0),"",IF(AA14<60,"과락","")) | AC14: =IF(N(AA14)=0,"",RANK(AA14,AA$3:AA$202)) -> 12 | AD14: =IFERROR(TEXT(VLOOKUP($B14,[1]평가!$B:$Z,MATCH(AD$2,[1]평가!$6:$6,0)-1,FALSE),"①@ ") & CHAR(13) & TEXT(VLOOKUP($B14,[2]평가!$B:$Z,MATCH(AD$2,[2]평가!$6:$6,0)-1,FALSE),"②@ ") & CHAR(13) & TEXT(VLOOKUP($B14,[3]평가!$B:$Z,MATCH(AD$2,[3]평가!$6:$6,0)-1,FALSE),"③@ ") & CHAR(13) & TEXT(VLOOKUP($B14,[4]평가!$B:$Z,MATCH(AD$2,[4]평가!$6:$6,0)-1,FALSE),"④@ ") & CHAR(13) & TEXT(VLOOKUP($B14,[5]평가!$B:$Z,MATCH(AD$2,[5]평가!$6:$6,0)-1,FALSE),"⑤@ "),"") -> ①시장의 수요 및 고객의 요구사항 변화에 대한 면밀한 분석과 이를 기반으로한 시장규모와 성장전략에 대한 수치화가 필요함 _x000D_②누적 사주 분석 15천건, 관상 분석 2만건 등 유의미한 데이터를 보유하고 있고 이를 통한 사업 고도화 가능해 보임. 제안 아이템에 대한 실현가능성 측면에서의 구체적인 설명은 다소 아쉬움 _x000D_③명확한 목표 시장과 수익 구조를 갖추고 있어, 사업의 실질적인 수익 창출 가능성이 높게 평가됨. 사업 계획의 흐름과 방향성이 논리적으로 설계되어 있어 안정적인 사업 추진 기반을 확보하였음. 다만, 시장 내 유사 경쟁사들에 대한 구체적 분석을 통해 본 사업만의 독보적인 차별성을 보강할 필요가 있음. _x000D_④사주명리학 관상학 AI 문화체험 컨텐츠로 글로벌4개언어 O2O 통합 앱구동방식의 도약기업으로 양산 설계 완성하였으며 관광벤처 선정되었음, 9억 매출에 대한 내역이 본사업의 매출인지는 불분명함, 확장을 위한 양산 대면 제품 생산계획을 구성하였으나 자금사용용도는 인건비로 표기되어 있음, 대표역량을 판단할 자료 기재가 누락되어 있음(역량지표 감점) _x000D_⑤아이템의 단계별 개발과정(양산 설계 완료을 일부 확인할 수 있음. 다만 해당 아이템 및 기술이 경쟁우위 요소 및 차별성에 대한 내용은 다소 부족해 보임. | AE14: =IFERROR(TEXT(VLOOKUP($B14,[1]평가!$B:$Z,MATCH(AE$2,[1]평가!$7:$7,0)-1,FALSE),"①@ ") & CHAR(13) & TEXT(VLOOKUP($B14,[2]평가!$B:$Z,MATCH(AE$2,[2]평가!$7:$7,0)-1,FALSE),"②@ ") & CHAR(13) & TEXT(VLOOKUP($B14,[3]평가!$B:$Z,MATCH(AE$2,[3]평가!$7:$7,0)-1,FALSE),"③@ ") & CHAR(13) & TEXT(VLOOKUP($B14,[4]평가!$B:$Z,MATCH(AE$2,[4]평가!$7:$7,0)-1,FALSE),"④@ ") & CHAR(13) & TEXT(VLOOKUP($B14,[5]평가!$B:$Z,MATCH(AE$2,[5]평가!$7:$7,0)-1,FALSE),"⑤@ "),"") -> 0_x000D_0_x000D_0_x000D_0_x000D_0 | AF14: =IFERROR(TEXT(VLOOKUP($B14,[1]평가!$B:$Z,MATCH(AF$2,[1]평가!$6:$6,0)-1,FALSE),"①@ ") & CHAR(13) & TEXT(VLOOKUP($B14,[2]평가!$B:$Z,MATCH(AF$2,[2]평가!$6:$6,0)-1,FALSE),"②@ ") & CHAR(13) & TEXT(VLOOKUP($B14,[3]평가!$B:$Z,MATCH(AF$2,[3]평가!$6:$6,0)-1,FALSE),"③@ ") & CHAR(13) & TEXT(VLOOKUP($B14,[4]평가!$B:$Z,MATCH(AF$2,[4]평가!$6:$6,0)-1,FALSE),"④@ ") & CHAR(13) & TEXT(VLOOKUP($B14,[5]평가!$B:$Z,MATCH(AF$2,[5]평가!$6:$6,0)-1,FALSE),"⑤@ "),"") -> 0_x000D_0_x000D_0_x000D_0_x000D_0
... A203: 175 | B203: 20415420 | C203: =IFERROR(VLOOKUP($B203,대상!$B:$AC,MATCH(C$2,대상!$1:$1,0)-1,FALSE),"") -> 지역기반 | D203: =IFERROR(VLOOKUP($B203,대상!$B:$AC,MATCH(D$2,대상!$1:$1,0)-1,FALSE),"") -> 안은진 | E203: =IFERROR(VLOOKUP($B203,대상!$B:$AC,MATCH(E$2,대상!$1:$1,0)-1,FALSE),"") -> 정보ㆍ통신3 | F203: =IFERROR(VLOOKUP($B203,대상!$B:$AC,MATCH(F$2,대상!$1:$1,0)-1,FALSE),"") -> 1인창업 | G203: =IFERROR(VLOOKUP($B203,대상!$B:$AC,MATCH(G$2,대상!$1:$1,0)-1,FALSE),"") | H203: =IFERROR(VLOOKUP($B203,[1]평가!$B:$Z,MATCH(LEFT(H$2,2),[1]평가!$7:$7,0)-1,FALSE),"") -> 요건탈락 | I203: =IFERROR(VLOOKUP($B203,[1]평가!$B:$Z,MATCH(LEFT(I$2,2),[1]평가!$7:$7,0)-1,FALSE),"") | J203: =IFERROR(VLOOKUP($B203,[1]평가!$B:$Z,MATCH(LEFT(J$2,2),[1]평가!$7:$7,0)-1,FALSE),"") | K203: =IFERROR(VLOOKUP($B203,[2]평가!$B:$Z,MATCH(LEFT(K$2,2),[2]평가!$7:$7,0)-1,FALSE),"") -> 요건탈락 | L203: =IFERROR(VLOOKUP($B203,[2]평가!$B:$Z,MATCH(LEFT(L$2,2),[2]평가!$7:$7,0)-1,FALSE),"") | M203: =IFERROR(VLOOKUP($B203,[2]평가!$B:$Z,MATCH(LEFT(M$2,2),[2]평가!$7:$7,0)-1,FALSE),"") | N203: =IFERROR(VLOOKUP($B203,[3]평가!$B:$Z,MATCH(LEFT(N$2,2),[3]평가!$7:$7,0)-1,FALSE),"") -> 요건탈락 | O203: =IFERROR(VLOOKUP($B203,[3]평가!$B:$Z,MATCH(LEFT(O$2,2),[3]평가!$7:$7,0)-1,FALSE),"") | P203: =IFERROR(VLOOKUP($B203,[3]평가!$B:$Z,MATCH(LEFT(P$2,2),[3]평가!$7:$7,0)-1,FALSE),"") | Q203: =IFERROR(VLOOKUP($B203,[4]평가!$B:$Z,MATCH(LEFT(Q$2,2),[4]평가!$7:$7,0)-1,FALSE),"") -> 요건탈락 | R203: =IFERROR(VLOOKUP($B203,[4]평가!$B:$Z,MATCH(LEFT(R$2,2),[4]평가!$7:$7,0)-1,FALSE),"") | S203: =IFERROR(VLOOKUP($B203,[4]평가!$B:$Z,MATCH(LEFT(S$2,2),[4]평가!$7:$7,0)-1,FALSE),"") | T203: =IFERROR(VLOOKUP($B203,[5]평가!$B:$Z,MATCH(LEFT(T$2,2),[5]평가!$7:$7,0)-1,FALSE),"") -> 요건탈락 | U203: =IFERROR(VLOOKUP($B203,[5]평가!$B:$Z,MATCH(LEFT(U$2,2),[5]평가!$7:$7,0)-1,FALSE),"") | V203: =IFERROR(VLOOKUP($B203,[5]평가!$B:$Z,MATCH(LEFT(V$2,2),[5]평가!$7:$7,0)-1,FALSE),"") | W203: =IFERROR(VLOOKUP($B203,대상!$B:$AD,MATCH(W$2,대상!$1:$1,0)-1,FALSE),"") -> 요건탈락 | X203: =IF(ISBLANK(B203),"",T$1-COUNTIF(H203:V203,"회피")) -> 5 | Y203: =IF($T$1=X203,(SUM(I203,L203,O203,R203,U203)-MIN(I203,L203,O203,R203,U203)-MAX(I203,L203,O203,R203,U203))/($T$1-2),SUM(I203,L203,O203,R203,U203/X203)) -> 0 | Z203: =IFERROR(VLOOKUP($B203,대상!$B:$AD,MATCH(Z$2,대상!$1:$1,0)-1,FALSE),0) -> 0 | AA203: =IFERROR(IF(W203="면제","100"+Z203,Y203+Z203),"") -> 0 | AB203: =IF(OR(W203="면제",N(Y203)=0),"",IF(AA203<60,"과락","")) | AC203: =IF(N(AA203)=0,"",RANK(AA203,AA$3:AA$202)) | AD203: =IFERROR(TEXT(VLOOKUP($B203,[1]평가!$B:$Z,MATCH(AD$2,[1]평가!$6:$6,0)-1,FALSE),"①@ ") & CHAR(13) & TEXT(VLOOKUP($B203,[2]평가!$B:$Z,MATCH(AD$2,[2]평가!$6:$6,0)-1,FALSE),"②@ ") & CHAR(13) & TEXT(VLOOKUP($B203,[3]평가!$B:$Z,MATCH(AD$2,[3]평가!$6:$6,0)-1,FALSE),"③@ ") & CHAR(13) & TEXT(VLOOKUP($B203,[4]평가!$B:$Z,MATCH(AD$2,[4]평가!$6:$6,0)-1,FALSE),"④@ ") & CHAR(13) & TEXT(VLOOKUP($B203,[5]평가!$B:$Z,MATCH(AD$2,[5]평가!$6:$6,0)-1,FALSE),"⑤@ "),"") -> 0_x000D_0_x000D_0_x000D_0_x000D_0 | AE203: =IFERROR(TEXT(VLOOKUP($B203,[1]평가!$B:$Z,MATCH(AE$2,[1]평가!$7:$7,0)-1,FALSE),"①@ ") & CHAR(13) & TEXT(VLOOKUP($B203,[2]평가!$B:$Z,MATCH(AE$2,[2]평가!$7:$7,0)-1,FALSE),"②@ ") & CHAR(13) & TEXT(VLOOKUP($B203,[3]평가!$B:$Z,MATCH(AE$2,[3]평가!$7:$7,0)-1,FALSE),"③@ ") & CHAR(13) & TEXT(VLOOKUP($B203,[4]평가!$B:$Z,MATCH(AE$2,[4]평가!$7:$7,0)-1,FALSE),"④@ ") & CHAR(13) & TEXT(VLOOKUP($B203,[5]평가!$B:$Z,MATCH(AE$2,[5]평가!$7:$7,0)-1,FALSE),"⑤@ "),"") -> 0_x000D_0_x000D_0_x000D_0_x000D_0 | AF203: =IFERROR(TEXT(VLOOKUP($B203,[1]평가!$B:$Z,MATCH(AF$2,[1]평가!$6:$6,0)-1,FALSE),"①@ ") & CHAR(13) & TEXT(VLOOKUP($B203,[2]평가!$B:$Z,MATCH(AF$2,[2]평가!$6:$6,0)-1,FALSE),"②@ ") & CHAR(13) & TEXT(VLOOKUP($B203,[3]평가!$B:$Z,MATCH(AF$2,[3]평가!$6:$6,0)-1,FALSE),"③@ ") & CHAR(13) & TEXT(VLOOKUP($B203,[4]평가!$B:$Z,MATCH(AF$2,[4]평가!$6:$6,0)-1,FALSE),"④@ ") & CHAR(13) & TEXT(VLOOKUP($B203,[5]평가!$B:$Z,MATCH(AF$2,[5]평가!$6:$6,0)-1,FALSE),"⑤@ "),"") -> 0_x000D_0_x000D_0_x000D_0_x000D_0
A204: 202 | C204: =IFERROR(VLOOKUP($B204,대상!$B:$AC,MATCH(C$2,대상!$1:$1,0)-1,FALSE),"") | D204: =IFERROR(VLOOKUP($B204,대상!$B:$AC,MATCH(D$2,대상!$1:$1,0)-1,FALSE),"") | E204: =IFERROR(VLOOKUP($B204,대상!$B:$AC,MATCH(E$2,대상!$1:$1,0)-1,FALSE),"") | F204: =IFERROR(VLOOKUP($B204,대상!$B:$AC,MATCH(F$2,대상!$1:$1,0)-1,FALSE),"") | G204: =IFERROR(VLOOKUP($B204,대상!$B:$AC,MATCH(G$2,대상!$1:$1,0)-1,FALSE),"") | H204: =IFERROR(VLOOKUP($B204,[1]평가!$B:$Z,MATCH(LEFT(H$2,2),[1]평가!$7:$7,0)-1,FALSE),"") | I204: =IFERROR(VLOOKUP($B204,[1]평가!$B:$Z,MATCH(LEFT(I$2,2),[1]평가!$7:$7,0)-1,FALSE),"") | J204: =IFERROR(VLOOKUP($B204,[1]평가!$B:$Z,MATCH(LEFT(J$2,2),[1]평가!$7:$7,0)-1,FALSE),"") | K204: =IFERROR(VLOOKUP($B204,[2]평가!$B:$Z,MATCH(LEFT(K$2,2),[2]평가!$7:$7,0)-1,FALSE),"") | L204: =IFERROR(VLOOKUP($B204,[2]평가!$B:$Z,MATCH(LEFT(L$2,2),[2]평가!$7:$7,0)-1,FALSE),"") | M204: =IFERROR(VLOOKUP($B204,[2]평가!$B:$Z,MATCH(LEFT(M$2,2),[2]평가!$7:$7,0)-1,FALSE),"") | N204: =IFERROR(VLOOKUP($B204,[3]평가!$B:$Z,MATCH(LEFT(N$2,2),[3]평가!$7:$7,0)-1,FALSE),"") | O204: =IFERROR(VLOOKUP($B204,[3]평가!$B:$Z,MATCH(LEFT(O$2,2),[3]평가!$7:$7,0)-1,FALSE),"") | P204: =IFERROR(VLOOKUP($B204,[3]평가!$B:$Z,MATCH(LEFT(P$2,2),[3]평가!$7:$7,0)-1,FALSE),"") | Q204: =IFERROR(VLOOKUP($B204,[4]평가!$B:$Z,MATCH(LEFT(Q$2,2),[4]평가!$7:$7,0)-1,FALSE),"") | R204: =IFERROR(VLOOKUP($B204,[4]평가!$B:$Z,MATCH(LEFT(R$2,2),[4]평가!$7:$7,0)-1,FALSE),"") | S204: =IFERROR(VLOOKUP($B204,[4]평가!$B:$Z,MATCH(LEFT(S$2,2),[4]평가!$7:$7,0)-1,FALSE),"") | T204: =IFERROR(VLOOKUP($B204,[5]평가!$B:$Z,MATCH(LEFT(T$2,2),[5]평가!$7:$7,0)-1,FALSE),"") | U204: =IFERROR(VLOOKUP($B204,[5]평가!$B:$Z,MATCH(LEFT(U$2,2),[5]평가!$7:$7,0)-1,FALSE),"") | V204: =IFERROR(VLOOKUP($B204,[5]평가!$B:$Z,MATCH(LEFT(V$2,2),[5]평가!$7:$7,0)-1,FALSE),"") | W204: =IFERROR(VLOOKUP($B204,대상!$B:$AD,MATCH(W$2,대상!$1:$1,0)-1,FALSE),"") | X204: =IF(ISBLANK(B204),"",T$1-COUNTIF(H204:V204,"회피")) | Y204: =IF($T$1=X204,(SUM(I204,L204,O204,R204,U204)-MIN(I204,L204,O204,R204,U204)-MAX(I204,L204,O204,R204,U204))/($T$1-2),SUM(I204,L204,O204,R204,U204/X204)) -> #VALUE! | Z204: =IFERROR(VLOOKUP($B204,대상!$B:$AD,MATCH(Z$2,대상!$1:$1,0)-1,FALSE),0) -> 0 | AA204: =IFERROR(IF(W204="면제","100"+Z204,Y204+Z204),"") | AB204: =IF(OR(W204="면제",N(Y204)=0),"",IF(AA204<60,"과락","")) -> #VALUE! | AC204: =IF(N(AA204)=0,"",RANK(AA204,AA$3:AA$202)) | AD204: =IFERROR(TEXT(VLOOKUP($B204,[1]평가!$B:$Z,MATCH(AD$2,[1]평가!$6:$6,0)-1,FALSE),"①@ ") & CHAR(13) & TEXT(VLOOKUP($B204,[2]평가!$B:$Z,MATCH(AD$2,[2]평가!$6:$6,0)-1,FALSE),"②@ ") & CHAR(13) & TEXT(VLOOKUP($B204,[3]평가!$B:$Z,MATCH(AD$2,[3]평가!$6:$6,0)-1,FALSE),"③@ ") & CHAR(13) & TEXT(VLOOKUP($B204,[4]평가!$B:$Z,MATCH(AD$2,[4]평가!$6:$6,0)-1,FALSE),"④@ ") & CHAR(13) & TEXT(VLOOKUP($B204,[5]평가!$B:$Z,MATCH(AD$2,[5]평가!$6:$6,0)-1,FALSE),"⑤@ "),"") | AE204: =IFERROR(TEXT(VLOOKUP($B204,[1]평가!$B:$Z,MATCH(AE$2,[1]평가!$7:$7,0)-1,FALSE),"①@ ") & CHAR(13) & TEXT(VLOOKUP($B204,[2]평가!$B:$Z,MATCH(AE$2,[2]평가!$7:$7,0)-1,FALSE),"②@ ") & CHAR(13) & TEXT(VLOOKUP($B204,[3]평가!$B:$Z,MATCH(AE$2,[3]평가!$7:$7,0)-1,FALSE),"③@ ") & CHAR(13) & TEXT(VLOOKUP($B204,[4]평가!$B:$Z,MATCH(AE$2,[4]평가!$7:$7,0)-1,FALSE),"④@ ") & CHAR(13) & TEXT(VLOOKUP($B204,[5]평가!$B:$Z,MATCH(AE$2,[5]평가!$7:$7,0)-1,FALSE),"⑤@ "),"") | AF204: =IFERROR(TEXT(VLOOKUP($B204,[1]평가!$B:$Z,MATCH(AF$2,[1]평가!$6:$6,0)-1,FALSE),"①@ ") & CHAR(13) & TEXT(VLOOKUP($B204,[2]평가!$B:$Z,MATCH(AF$2,[2]평가!$6:$6,0)-1,FALSE),"②@ ") & CHAR(13) & TEXT(VLOOKUP($B204,[3]평가!$B:$Z,MATCH(AF$2,[3]평가!$6:$6,0)-1,FALSE),"③@ ") & CHAR(13) & TEXT(VLOOKUP($B204,[4]평가!$B:$Z,MATCH(AF$2,[4]평가!$6:$6,0)-1,FALSE),"④@ ") & CHAR(13) & TEXT(VLOOKUP($B204,[5]평가!$B:$Z,MATCH(AF$2,[5]평가!$6:$6,0)-1,FALSE),"⑤@ "),"")
A205: 203 | C205: =IFERROR(VLOOKUP($B205,대상!$B:$AC,MATCH(C$2,대상!$1:$1,0)-1,FALSE),"") | D205: =IFERROR(VLOOKUP($B205,대상!$B:$AC,MATCH(D$2,대상!$1:$1,0)-1,FALSE),"") | E205: =IFERROR(VLOOKUP($B205,대상!$B:$AC,MATCH(E$2,대상!$1:$1,0)-1,FALSE),"") | F205: =IFERROR(VLOOKUP($B205,대상!$B:$AC,MATCH(F$2,대상!$1:$1,0)-1,FALSE),"") | G205: =IFERROR(VLOOKUP($B205,대상!$B:$AC,MATCH(G$2,대상!$1:$1,0)-1,FALSE),"") | H205: =IFERROR(VLOOKUP($B205,[1]평가!$B:$Z,MATCH(LEFT(H$2,2),[1]평가!$7:$7,0)-1,FALSE),"") | I205: =IFERROR(VLOOKUP($B205,[1]평가!$B:$Z,MATCH(LEFT(I$2,2),[1]평가!$7:$7,0)-1,FALSE),"") | J205: =IFERROR(VLOOKUP($B205,[1]평가!$B:$Z,MATCH(LEFT(J$2,2),[1]평가!$7:$7,0)-1,FALSE),"") | K205: =IFERROR(VLOOKUP($B205,[2]평가!$B:$Z,MATCH(LEFT(K$2,2),[2]평가!$7:$7,0)-1,FALSE),"") | L205: =IFERROR(VLOOKUP($B205,[2]평가!$B:$Z,MATCH(LEFT(L$2,2),[2]평가!$7:$7,0)-1,FALSE),"") | M205: =IFERROR(VLOOKUP($B205,[2]평가!$B:$Z,MATCH(LEFT(M$2,2),[2]평가!$7:$7,0)-1,FALSE),"") | N205: =IFERROR(VLOOKUP($B205,[3]평가!$B:$Z,MATCH(LEFT(N$2,2),[3]평가!$7:$7,0)-1,FALSE),"") | O205: =IFERROR(VLOOKUP($B205,[3]평가!$B:$Z,MATCH(LEFT(O$2,2),[3]평가!$7:$7,0)-1,FALSE),"") | P205: =IFERROR(VLOOKUP($B205,[3]평가!$B:$Z,MATCH(LEFT(P$2,2),[3]평가!$7:$7,0)-1,FALSE),"") | Q205: =IFERROR(VLOOKUP($B205,[4]평가!$B:$Z,MATCH(LEFT(Q$2,2),[4]평가!$7:$7,0)-1,FALSE),"") | R205: =IFERROR(VLOOKUP($B205,[4]평가!$B:$Z,MATCH(LEFT(R$2,2),[4]평가!$7:$7,0)-1,FALSE),"") | S205: =IFERROR(VLOOKUP($B205,[4]평가!$B:$Z,MATCH(LEFT(S$2,2),[4]평가!$7:$7,0)-1,FALSE),"") | T205: =IFERROR(VLOOKUP($B205,[5]평가!$B:$Z,MATCH(LEFT(T$2,2),[5]평가!$7:$7,0)-1,FALSE),"") | U205: =IFERROR(VLOOKUP($B205,[5]평가!$B:$Z,MATCH(LEFT(U$2,2),[5]평가!$7:$7,0)-1,FALSE),"") | V205: =IFERROR(VLOOKUP($B205,[5]평가!$B:$Z,MATCH(LEFT(V$2,2),[5]평가!$7:$7,0)-1,FALSE),"") | W205: =IFERROR(VLOOKUP($B205,대상!$B:$AD,MATCH(W$2,대상!$1:$1,0)-1,FALSE),"") | X205: =IF(ISBLANK(B205),"",T$1-COUNTIF(H205:V205,"회피")) | Y205: =IF($T$1=X205,(SUM(I205,L205,O205,R205,U205)-MIN(I205,L205,O205,R205,U205)-MAX(I205,L205,O205,R205,U205))/($T$1-2),SUM(I205,L205,O205,R205,U205/X205)) -> #VALUE! | Z205: =IFERROR(VLOOKUP($B205,대상!$B:$AD,MATCH(Z$2,대상!$1:$1,0)-1,FALSE),0) -> 0 | AA205: =IFERROR(IF(W205="면제","100"+Z205,Y205+Z205),"") | AB205: =IF(OR(W205="면제",N(Y205)=0),"",IF(AA205<60,"과락","")) -> #VALUE! | AC205: =IF(N(AA205)=0,"",RANK(AA205,AA$3:AA$202)) | AD205: =IFERROR(TEXT(VLOOKUP($B205,[1]평가!$B:$Z,MATCH(AD$2,[1]평가!$6:$6,0)-1,FALSE),"①@ ") & CHAR(13) & TEXT(VLOOKUP($B205,[2]평가!$B:$Z,MATCH(AD$2,[2]평가!$6:$6,0)-1,FALSE),"②@ ") & CHAR(13) & TEXT(VLOOKUP($B205,[3]평가!$B:$Z,MATCH(AD$2,[3]평가!$6:$6,0)-1,FALSE),"③@ ") & CHAR(13) & TEXT(VLOOKUP($B205,[4]평가!$B:$Z,MATCH(AD$2,[4]평가!$6:$6,0)-1,FALSE),"④@ ") & CHAR(13) & TEXT(VLOOKUP($B205,[5]평가!$B:$Z,MATCH(AD$2,[5]평가!$6:$6,0)-1,FALSE),"⑤@ "),"") | AE205: =IFERROR(TEXT(VLOOKUP($B205,[1]평가!$B:$Z,MATCH(AE$2,[1]평가!$7:$7,0)-1,FALSE),"①@ ") & CHAR(13) & TEXT(VLOOKUP($B205,[2]평가!$B:$Z,MATCH(AE$2,[2]평가!$7:$7,0)-1,FALSE),"②@ ") & CHAR(13) & TEXT(VLOOKUP($B205,[3]평가!$B:$Z,MATCH(AE$2,[3]평가!$7:$7,0)-1,FALSE),"③@ ") & CHAR(13) & TEXT(VLOOKUP($B205,[4]평가!$B:$Z,MATCH(AE$2,[4]평가!$7:$7,0)-1,FALSE),"④@ ") & CHAR(13) & TEXT(VLOOKUP($B205,[5]평가!$B:$Z,MATCH(AE$2,[5]평가!$7:$7,0)-1,FALSE),"⑤@ "),"") | AF205: =IFERROR(TEXT(VLOOKUP($B205,[1]평가!$B:$Z,MATCH(AF$2,[1]평가!$6:$6,0)-1,FALSE),"①@ ") & CHAR(13) & TEXT(VLOOKUP($B205,[2]평가!$B:$Z,MATCH(AF$2,[2]평가!$6:$6,0)-1,FALSE),"②@ ") & CHAR(13) & TEXT(VLOOKUP($B205,[3]평가!$B:$Z,MATCH(AF$2,[3]평가!$6:$6,0)-1,FALSE),"③@ ") & CHAR(13) & TEXT(VLOOKUP($B205,[4]평가!$B:$Z,MATCH(AF$2,[4]평가!$6:$6,0)-1,FALSE),"④@ ") & CHAR(13) & TEXT(VLOOKUP($B205,[5]평가!$B:$Z,MATCH(AF$2,[5]평가!$6:$6,0)-1,FALSE),"⑤@ "),"")
A206: 204 | C206: =IFERROR(VLOOKUP($B206,대상!$B:$AC,MATCH(C$2,대상!$1:$1,0)-1,FALSE),"") | D206: =IFERROR(VLOOKUP($B206,대상!$B:$AC,MATCH(D$2,대상!$1:$1,0)-1,FALSE),"") | E206: =IFERROR(VLOOKUP($B206,대상!$B:$AC,MATCH(E$2,대상!$1:$1,0)-1,FALSE),"") | F206: =IFERROR(VLOOKUP($B206,대상!$B:$AC,MATCH(F$2,대상!$1:$1,0)-1,FALSE),"") | G206: =IFERROR(VLOOKUP($B206,대상!$B:$AC,MATCH(G$2,대상!$1:$1,0)-1,FALSE),"") | H206: =IFERROR(VLOOKUP($B206,[1]평가!$B:$Z,MATCH(LEFT(H$2,2),[1]평가!$7:$7,0)-1,FALSE),"") | I206: =IFERROR(VLOOKUP($B206,[1]평가!$B:$Z,MATCH(LEFT(I$2,2),[1]평가!$7:$7,0)-1,FALSE),"") | J206: =IFERROR(VLOOKUP($B206,[1]평가!$B:$Z,MATCH(LEFT(J$2,2),[1]평가!$7:$7,0)-1,FALSE),"") | K206: =IFERROR(VLOOKUP($B206,[2]평가!$B:$Z,MATCH(LEFT(K$2,2),[2]평가!$7:$7,0)-1,FALSE),"") | L206: =IFERROR(VLOOKUP($B206,[2]평가!$B:$Z,MATCH(LEFT(L$2,2),[2]평가!$7:$7,0)-1,FALSE),"") | M206: =IFERROR(VLOOKUP($B206,[2]평가!$B:$Z,MATCH(LEFT(M$2,2),[2]평가!$7:$7,0)-1,FALSE),"") | N206: =IFERROR(VLOOKUP($B206,[3]평가!$B:$Z,MATCH(LEFT(N$2,2),[3]평가!$7:$7,0)-1,FALSE),"") | O206: =IFERROR(VLOOKUP($B206,[3]평가!$B:$Z,MATCH(LEFT(O$2,2),[3]평가!$7:$7,0)-1,FALSE),"") | P206: =IFERROR(VLOOKUP($B206,[3]평가!$B:$Z,MATCH(LEFT(P$2,2),[3]평가!$7:$7,0)-1,FALSE),"") | Q206: =IFERROR(VLOOKUP($B206,[4]평가!$B:$Z,MATCH(LEFT(Q$2,2),[4]평가!$7:$7,0)-1,FALSE),"") | R206: =IFERROR(VLOOKUP($B206,[4]평가!$B:$Z,MATCH(LEFT(R$2,2),[4]평가!$7:$7,0)-1,FALSE),"") | S206: =IFERROR(VLOOKUP($B206,[4]평가!$B:$Z,MATCH(LEFT(S$2,2),[4]평가!$7:$7,0)-1,FALSE),"") | T206: =IFERROR(VLOOKUP($B206,[5]평가!$B:$Z,MATCH(LEFT(T$2,2),[5]평가!$7:$7,0)-1,FALSE),"") | U206: =IFERROR(VLOOKUP($B206,[5]평가!$B:$Z,MATCH(LEFT(U$2,2),[5]평가!$7:$7,0)-1,FALSE),"") | V206: =IFERROR(VLOOKUP($B206,[5]평가!$B:$Z,MATCH(LEFT(V$2,2),[5]평가!$7:$7,0)-1,FALSE),"") | W206: =IFERROR(VLOOKUP($B206,대상!$B:$AD,MATCH(W$2,대상!$1:$1,0)-1,FALSE),"") | X206: =IF(ISBLANK(B206),"",T$1-COUNTIF(H206:V206,"회피")) | Y206: =IF($T$1=X206,(SUM(I206,L206,O206,R206,U206)-MIN(I206,L206,O206,R206,U206)-MAX(I206,L206,O206,R206,U206))/($T$1-2),SUM(I206,L206,O206,R206,U206/X206)) -> #VALUE! | Z206: =IFERROR(VLOOKUP($B206,대상!$B:$AD,MATCH(Z$2,대상!$1:$1,0)-1,FALSE),0) -> 0 | AA206: =IFERROR(IF(W206="면제","100"+Z206,Y206+Z206),"") | AB206: =IF(OR(W206="면제",N(Y206)=0),"",IF(AA206<60,"과락","")) -> #VALUE! | AC206: =IF(N(AA206)=0,"",RANK(AA206,AA$3:AA$202)) | AD206: =IFERROR(TEXT(VLOOKUP($B206,[1]평가!$B:$Z,MATCH(AD$2,[1]평가!$6:$6,0)-1,FALSE),"①@ ") & CHAR(13) & TEXT(VLOOKUP($B206,[2]평가!$B:$Z,MATCH(AD$2,[2]평가!$6:$6,0)-1,FALSE),"②@ ") & CHAR(13) & TEXT(VLOOKUP($B206,[3]평가!$B:$Z,MATCH(AD$2,[3]평가!$6:$6,0)-1,FALSE),"③@ ") & CHAR(13) & TEXT(VLOOKUP($B206,[4]평가!$B:$Z,MATCH(AD$2,[4]평가!$6:$6,0)-1,FALSE),"④@ ") & CHAR(13) & TEXT(VLOOKUP($B206,[5]평가!$B:$Z,MATCH(AD$2,[5]평가!$6:$6,0)-1,FALSE),"⑤@ "),"") | AE206: =IFERROR(TEXT(VLOOKUP($B206,[1]평가!$B:$Z,MATCH(AE$2,[1]평가!$7:$7,0)-1,FALSE),"①@ ") & CHAR(13) & TEXT(VLOOKUP($B206,[2]평가!$B:$Z,MATCH(AE$2,[2]평가!$7:$7,0)-1,FALSE),"②@ ") & CHAR(13) & TEXT(VLOOKUP($B206,[3]평가!$B:$Z,MATCH(AE$2,[3]평가!$7:$7,0)-1,FALSE),"③@ ") & CHAR(13) & TEXT(VLOOKUP($B206,[4]평가!$B:$Z,MATCH(AE$2,[4]평가!$7:$7,0)-1,FALSE),"④@ ") & CHAR(13) & TEXT(VLOOKUP($B206,[5]평가!$B:$Z,MATCH(AE$2,[5]평가!$7:$7,0)-1,FALSE),"⑤@ "),"") | AF206: =IFERROR(TEXT(VLOOKUP($B206,[1]평가!$B:$Z,MATCH(AF$2,[1]평가!$6:$6,0)-1,FALSE),"①@ ") & CHAR(13) & TEXT(VLOOKUP($B206,[2]평가!$B:$Z,MATCH(AF$2,[2]평가!$6:$6,0)-1,FALSE),"②@ ") & CHAR(13) & TEXT(VLOOKUP($B206,[3]평가!$B:$Z,MATCH(AF$2,[3]평가!$6:$6,0)-1,FALSE),"③@ ") & CHAR(13) & TEXT(VLOOKUP($B206,[4]평가!$B:$Z,MATCH(AF$2,[4]평가!$6:$6,0)-1,FALSE),"④@ ") & CHAR(13) & TEXT(VLOOKUP($B206,[5]평가!$B:$Z,MATCH(AF$2,[5]평가!$6:$6,0)-1,FALSE),"⑤@ "),"")
A207: 205 | C207: =IFERROR(VLOOKUP($B207,대상!$B:$AC,MATCH(C$2,대상!$1:$1,0)-1,FALSE),"") | D207: =IFERROR(VLOOKUP($B207,대상!$B:$AC,MATCH(D$2,대상!$1:$1,0)-1,FALSE),"") | E207: =IFERROR(VLOOKUP($B207,대상!$B:$AC,MATCH(E$2,대상!$1:$1,0)-1,FALSE),"") | F207: =IFERROR(VLOOKUP($B207,대상!$B:$AC,MATCH(F$2,대상!$1:$1,0)-1,FALSE),"") | G207: =IFERROR(VLOOKUP($B207,대상!$B:$AC,MATCH(G$2,대상!$1:$1,0)-1,FALSE),"") | H207: =IFERROR(VLOOKUP($B207,[1]평가!$B:$Z,MATCH(LEFT(H$2,2),[1]평가!$7:$7,0)-1,FALSE),"") | I207: =IFERROR(VLOOKUP($B207,[1]평가!$B:$Z,MATCH(LEFT(I$2,2),[1]평가!$7:$7,0)-1,FALSE),"") | J207: =IFERROR(VLOOKUP($B207,[1]평가!$B:$Z,MATCH(LEFT(J$2,2),[1]평가!$7:$7,0)-1,FALSE),"") | K207: =IFERROR(VLOOKUP($B207,[2]평가!$B:$Z,MATCH(LEFT(K$2,2),[2]평가!$7:$7,0)-1,FALSE),"") | L207: =IFERROR(VLOOKUP($B207,[2]평가!$B:$Z,MATCH(LEFT(L$2,2),[2]평가!$7:$7,0)-1,FALSE),"") | M207: =IFERROR(VLOOKUP($B207,[2]평가!$B:$Z,MATCH(LEFT(M$2,2),[2]평가!$7:$7,0)-1,FALSE),"") | N207: =IFERROR(VLOOKUP($B207,[3]평가!$B:$Z,MATCH(LEFT(N$2,2),[3]평가!$7:$7,0)-1,FALSE),"") | O207: =IFERROR(VLOOKUP($B207,[3]평가!$B:$Z,MATCH(LEFT(O$2,2),[3]평가!$7:$7,0)-1,FALSE),"") | P207: =IFERROR(VLOOKUP($B207,[3]평가!$B:$Z,MATCH(LEFT(P$2,2),[3]평가!$7:$7,0)-1,FALSE),"") | Q207: =IFERROR(VLOOKUP($B207,[4]평가!$B:$Z,MATCH(LEFT(Q$2,2),[4]평가!$7:$7,0)-1,FALSE),"") | R207: =IFERROR(VLOOKUP($B207,[4]평가!$B:$Z,MATCH(LEFT(R$2,2),[4]평가!$7:$7,0)-1,FALSE),"") | S207: =IFERROR(VLOOKUP($B207,[4]평가!$B:$Z,MATCH(LEFT(S$2,2),[4]평가!$7:$7,0)-1,FALSE),"") | T207: =IFERROR(VLOOKUP($B207,[5]평가!$B:$Z,MATCH(LEFT(T$2,2),[5]평가!$7:$7,0)-1,FALSE),"") | U207: =IFERROR(VLOOKUP($B207,[5]평가!$B:$Z,MATCH(LEFT(U$2,2),[5]평가!$7:$7,0)-1,FALSE),"") | V207: =IFERROR(VLOOKUP($B207,[5]평가!$B:$Z,MATCH(LEFT(V$2,2),[5]평가!$7:$7,0)-1,FALSE),"") | W207: =IFERROR(VLOOKUP($B207,대상!$B:$AD,MATCH(W$2,대상!$1:$1,0)-1,FALSE),"") | X207: =IF(ISBLANK(B207),"",T$1-COUNTIF(H207:V207,"회피")) | Y207: =IF($T$1=X207,(SUM(I207,L207,O207,R207,U207)-MIN(I207,L207,O207,R207,U207)-MAX(I207,L207,O207,R207,U207))/($T$1-2),SUM(I207,L207,O207,R207,U207/X207)) -> #VALUE! | Z207: =IFERROR(VLOOKUP($B207,대상!$B:$AD,MATCH(Z$2,대상!$1:$1,0)-1,FALSE),0) -> 0 | AA207: =IFERROR(IF(W207="면제","100"+Z207,Y207+Z207),"") | AB207: =IF(OR(W207="면제",N(Y207)=0),"",IF(AA207<60,"과락","")) -> #VALUE! | AC207: =IF(N(AA207)=0,"",RANK(AA207,AA$3:AA$202)) | AD207: =IFERROR(TEXT(VLOOKUP($B207,[1]평가!$B:$Z,MATCH(AD$2,[1]평가!$6:$6,0)-1,FALSE),"①@ ") & CHAR(13) & TEXT(VLOOKUP($B207,[2]평가!$B:$Z,MATCH(AD$2,[2]평가!$6:$6,0)-1,FALSE),"②@ ") & CHAR(13) & TEXT(VLOOKUP($B207,[3]평가!$B:$Z,MATCH(AD$2,[3]평가!$6:$6,0)-1,FALSE),"③@ ") & CHAR(13) & TEXT(VLOOKUP($B207,[4]평가!$B:$Z,MATCH(AD$2,[4]평가!$6:$6,0)-1,FALSE),"④@ ") & CHAR(13) & TEXT(VLOOKUP($B207,[5]평가!$B:$Z,MATCH(AD$2,[5]평가!$6:$6,0)-1,FALSE),"⑤@ "),"") | AE207: =IFERROR(TEXT(VLOOKUP($B207,[1]평가!$B:$Z,MATCH(AE$2,[1]평가!$7:$7,0)-1,FALSE),"①@ ") & CHAR(13) & TEXT(VLOOKUP($B207,[2]평가!$B:$Z,MATCH(AE$2,[2]평가!$7:$7,0)-1,FALSE),"②@ ") & CHAR(13) & TEXT(VLOOKUP($B207,[3]평가!$B:$Z,MATCH(AE$2,[3]평가!$7:$7,0)-1,FALSE),"③@ ") & CHAR(13) & TEXT(VLOOKUP($B207,[4]평가!$B:$Z,MATCH(AE$2,[4]평가!$7:$7,0)-1,FALSE),"④@ ") & CHAR(13) & TEXT(VLOOKUP($B207,[5]평가!$B:$Z,MATCH(AE$2,[5]평가!$7:$7,0)-1,FALSE),"⑤@ "),"") | AF207: =IFERROR(TEXT(VLOOKUP($B207,[1]평가!$B:$Z,MATCH(AF$2,[1]평가!$6:$6,0)-1,FALSE),"①@ ") & CHAR(13) & TEXT(VLOOKUP($B207,[2]평가!$B:$Z,MATCH(AF$2,[2]평가!$6:$6,0)-1,FALSE),"②@ ") & CHAR(13) & TEXT(VLOOKUP($B207,[3]평가!$B:$Z,MATCH(AF$2,[3]평가!$6:$6,0)-1,FALSE),"③@ ") & CHAR(13) & TEXT(VLOOKUP($B207,[4]평가!$B:$Z,MATCH(AF$2,[4]평가!$6:$6,0)-1,FALSE),"④@ ") & CHAR(13) & TEXT(VLOOKUP($B207,[5]평가!$B:$Z,MATCH(AF$2,[5]평가!$6:$6,0)-1,FALSE),"⑤@ "),"")
A208: 206 | C208: =IFERROR(VLOOKUP($B208,대상!$B:$AC,MATCH(C$2,대상!$1:$1,0)-1,FALSE),"") | D208: =IFERROR(VLOOKUP($B208,대상!$B:$AC,MATCH(D$2,대상!$1:$1,0)-1,FALSE),"") | E208: =IFERROR(VLOOKUP($B208,대상!$B:$AC,MATCH(E$2,대상!$1:$1,0)-1,FALSE),"") | F208: =IFERROR(VLOOKUP($B208,대상!$B:$AC,MATCH(F$2,대상!$1:$1,0)-1,FALSE),"") | G208: =IFERROR(VLOOKUP($B208,대상!$B:$AC,MATCH(G$2,대상!$1:$1,0)-1,FALSE),"") | H208: =IFERROR(VLOOKUP($B208,[1]평가!$B:$Z,MATCH(LEFT(H$2,2),[1]평가!$7:$7,0)-1,FALSE),"") | I208: =IFERROR(VLOOKUP($B208,[1]평가!$B:$Z,MATCH(LEFT(I$2,2),[1]평가!$7:$7,0)-1,FALSE),"") | J208: =IFERROR(VLOOKUP($B208,[1]평가!$B:$Z,MATCH(LEFT(J$2,2),[1]평가!$7:$7,0)-1,FALSE),"") | K208: =IFERROR(VLOOKUP($B208,[2]평가!$B:$Z,MATCH(LEFT(K$2,2),[2]평가!$7:$7,0)-1,FALSE),"") | L208: =IFERROR(VLOOKUP($B208,[2]평가!$B:$Z,MATCH(LEFT(L$2,2),[2]평가!$7:$7,0)-1,FALSE),"") | M208: =IFERROR(VLOOKUP($B208,[2]평가!$B:$Z,MATCH(LEFT(M$2,2),[2]평가!$7:$7,0)-1,FALSE),"") | N208: =IFERROR(VLOOKUP($B208,[3]평가!$B:$Z,MATCH(LEFT(N$2,2),[3]평가!$7:$7,0)-1,FALSE),"") | O208: =IFERROR(VLOOKUP($B208,[3]평가!$B:$Z,MATCH(LEFT(O$2,2),[3]평가!$7:$7,0)-1,FALSE),"") | P208: =IFERROR(VLOOKUP($B208,[3]평가!$B:$Z,MATCH(LEFT(P$2,2),[3]평가!$7:$7,0)-1,FALSE),"") | Q208: =IFERROR(VLOOKUP($B208,[4]평가!$B:$Z,MATCH(LEFT(Q$2,2),[4]평가!$7:$7,0)-1,FALSE),"") | R208: =IFERROR(VLOOKUP($B208,[4]평가!$B:$Z,MATCH(LEFT(R$2,2),[4]평가!$7:$7,0)-1,FALSE),"") | S208: =IFERROR(VLOOKUP($B208,[4]평가!$B:$Z,MATCH(LEFT(S$2,2),[4]평가!$7:$7,0)-1,FALSE),"") | T208: =IFERROR(VLOOKUP($B208,[5]평가!$B:$Z,MATCH(LEFT(T$2,2),[5]평가!$7:$7,0)-1,FALSE),"") | U208: =IFERROR(VLOOKUP($B208,[5]평가!$B:$Z,MATCH(LEFT(U$2,2),[5]평가!$7:$7,0)-1,FALSE),"") | V208: =IFERROR(VLOOKUP($B208,[5]평가!$B:$Z,MATCH(LEFT(V$2,2),[5]평가!$7:$7,0)-1,FALSE),"") | W208: =IFERROR(VLOOKUP($B208,대상!$B:$AD,MATCH(W$2,대상!$1:$1,0)-1,FALSE),"") | X208: =IF(ISBLANK(B208),"",T$1-COUNTIF(H208:V208,"회피")) | Y208: =IF($T$1=X208,(SUM(I208,L208,O208,R208,U208)-MIN(I208,L208,O208,R208,U208)-MAX(I208,L208,O208,R208,U208))/($T$1-2),SUM(I208,L208,O208,R208,U208/X208)) -> #VALUE! | Z208: =IFERROR(VLOOKUP($B208,대상!$B:$AD,MATCH(Z$2,대상!$1:$1,0)-1,FALSE),0) -> 0 | AA208: =IFERROR(IF(W208="면제","100"+Z208,Y208+Z208),"") | AB208: =IF(OR(W208="면제",N(Y208)=0),"",IF(AA208<60,"과락","")) -> #VALUE! | AC208: =IF(N(AA208)=0,"",RANK(AA208,AA$3:AA$202)) | AD208: =IFERROR(TEXT(VLOOKUP($B208,[1]평가!$B:$Z,MATCH(AD$2,[1]평가!$6:$6,0)-1,FALSE),"①@ ") & CHAR(13) & TEXT(VLOOKUP($B208,[2]평가!$B:$Z,MATCH(AD$2,[2]평가!$6:$6,0)-1,FALSE),"②@ ") & CHAR(13) & TEXT(VLOOKUP($B208,[3]평가!$B:$Z,MATCH(AD$2,[3]평가!$6:$6,0)-1,FALSE),"③@ ") & CHAR(13) & TEXT(VLOOKUP($B208,[4]평가!$B:$Z,MATCH(AD$2,[4]평가!$6:$6,0)-1,FALSE),"④@ ") & CHAR(13) & TEXT(VLOOKUP($B208,[5]평가!$B:$Z,MATCH(AD$2,[5]평가!$6:$6,0)-1,FALSE),"⑤@ "),"") | AE208: =IFERROR(TEXT(VLOOKUP($B208,[1]평가!$B:$Z,MATCH(AE$2,[1]평가!$7:$7,0)-1,FALSE),"①@ ") & CHAR(13) & TEXT(VLOOKUP($B208,[2]평가!$B:$Z,MATCH(AE$2,[2]평가!$7:$7,0)-1,FALSE),"②@ ") & CHAR(13) & TEXT(VLOOKUP($B208,[3]평가!$B:$Z,MATCH(AE$2,[3]평가!$7:$7,0)-1,FALSE),"③@ ") & CHAR(13) & TEXT(VLOOKUP($B208,[4]평가!$B:$Z,MATCH(AE$2,[4]평가!$7:$7,0)-1,FALSE),"④@ ") & CHAR(13) & TEXT(VLOOKUP($B208,[5]평가!$B:$Z,MATCH(AE$2,[5]평가!$7:$7,0)-1,FALSE),"⑤@ "),"") | AF208: =IFERROR(TEXT(VLOOKUP($B208,[1]평가!$B:$Z,MATCH(AF$2,[1]평가!$6:$6,0)-1,FALSE),"①@ ") & CHAR(13) & TEXT(VLOOKUP($B208,[2]평가!$B:$Z,MATCH(AF$2,[2]평가!$6:$6,0)-1,FALSE),"②@ ") & CHAR(13) & TEXT(VLOOKUP($B208,[3]평가!$B:$Z,MATCH(AF$2,[3]평가!$6:$6,0)-1,FALSE),"③@ ") & CHAR(13) & TEXT(VLOOKUP($B208,[4]평가!$B:$Z,MATCH(AF$2,[4]평가!$6:$6,0)-1,FALSE),"④@ ") & CHAR(13) & TEXT(VLOOKUP($B208,[5]평가!$B:$Z,MATCH(AF$2,[5]평가!$6:$6,0)-1,FALSE),"⑤@ "),"")
A209: 207 | C209: =IFERROR(VLOOKUP($B209,대상!$B:$AC,MATCH(C$2,대상!$1:$1,0)-1,FALSE),"") | D209: =IFERROR(VLOOKUP($B209,대상!$B:$AC,MATCH(D$2,대상!$1:$1,0)-1,FALSE),"") | E209: =IFERROR(VLOOKUP($B209,대상!$B:$AC,MATCH(E$2,대상!$1:$1,0)-1,FALSE),"") | F209: =IFERROR(VLOOKUP($B209,대상!$B:$AC,MATCH(F$2,대상!$1:$1,0)-1,FALSE),"") | G209: =IFERROR(VLOOKUP($B209,대상!$B:$AC,MATCH(G$2,대상!$1:$1,0)-1,FALSE),"") | H209: =IFERROR(VLOOKUP($B209,[1]평가!$B:$Z,MATCH(LEFT(H$2,2),[1]평가!$7:$7,0)-1,FALSE),"") | I209: =IFERROR(VLOOKUP($B209,[1]평가!$B:$Z,MATCH(LEFT(I$2,2),[1]평가!$7:$7,0)-1,FALSE),"") | J209: =IFERROR(VLOOKUP($B209,[1]평가!$B:$Z,MATCH(LEFT(J$2,2),[1]평가!$7:$7,0)-1,FALSE),"") | K209: =IFERROR(VLOOKUP($B209,[2]평가!$B:$Z,MATCH(LEFT(K$2,2),[2]평가!$7:$7,0)-1,FALSE),"") | L209: =IFERROR(VLOOKUP($B209,[2]평가!$B:$Z,MATCH(LEFT(L$2,2),[2]평가!$7:$7,0)-1,FALSE),"") | M209: =IFERROR(VLOOKUP($B209,[2]평가!$B:$Z,MATCH(LEFT(M$2,2),[2]평가!$7:$7,0)-1,FALSE),"") | N209: =IFERROR(VLOOKUP($B209,[3]평가!$B:$Z,MATCH(LEFT(N$2,2),[3]평가!$7:$7,0)-1,FALSE),"") | O209: =IFERROR(VLOOKUP($B209,[3]평가!$B:$Z,MATCH(LEFT(O$2,2),[3]평가!$7:$7,0)-1,FALSE),"") | P209: =IFERROR(VLOOKUP($B209,[3]평가!$B:$Z,MATCH(LEFT(P$2,2),[3]평가!$7:$7,0)-1,FALSE),"") | Q209: =IFERROR(VLOOKUP($B209,[4]평가!$B:$Z,MATCH(LEFT(Q$2,2),[4]평가!$7:$7,0)-1,FALSE),"") | R209: =IFERROR(VLOOKUP($B209,[4]평가!$B:$Z,MATCH(LEFT(R$2,2),[4]평가!$7:$7,0)-1,FALSE),"") | S209: =IFERROR(VLOOKUP($B209,[4]평가!$B:$Z,MATCH(LEFT(S$2,2),[4]평가!$7:$7,0)-1,FALSE),"") | T209: =IFERROR(VLOOKUP($B209,[5]평가!$B:$Z,MATCH(LEFT(T$2,2),[5]평가!$7:$7,0)-1,FALSE),"") | U209: =IFERROR(VLOOKUP($B209,[5]평가!$B:$Z,MATCH(LEFT(U$2,2),[5]평가!$7:$7,0)-1,FALSE),"") | V209: =IFERROR(VLOOKUP($B209,[5]평가!$B:$Z,MATCH(LEFT(V$2,2),[5]평가!$7:$7,0)-1,FALSE),"") | W209: =IFERROR(VLOOKUP($B209,대상!$B:$AD,MATCH(W$2,대상!$1:$1,0)-1,FALSE),"") | X209: =IF(ISBLANK(B209),"",T$1-COUNTIF(H209:V209,"회피")) | Y209: =IF($T$1=X209,(SUM(I209,L209,O209,R209,U209)-MIN(I209,L209,O209,R209,U209)-MAX(I209,L209,O209,R209,U209))/($T$1-2),SUM(I209,L209,O209,R209,U209/X209)) -> #VALUE! | Z209: =IFERROR(VLOOKUP($B209,대상!$B:$AD,MATCH(Z$2,대상!$1:$1,0)-1,FALSE),0) -> 0 | AA209: =IFERROR(IF(W209="면제","100"+Z209,Y209+Z209),"") | AB209: =IF(OR(W209="면제",N(Y209)=0),"",IF(AA209<60,"과락","")) -> #VALUE! | AC209: =IF(N(AA209)=0,"",RANK(AA209,AA$3:AA$202)) | AD209: =IFERROR(TEXT(VLOOKUP($B209,[1]평가!$B:$Z,MATCH(AD$2,[1]평가!$6:$6,0)-1,FALSE),"①@ ") & CHAR(13) & TEXT(VLOOKUP($B209,[2]평가!$B:$Z,MATCH(AD$2,[2]평가!$6:$6,0)-1,FALSE),"②@ ") & CHAR(13) & TEXT(VLOOKUP($B209,[3]평가!$B:$Z,MATCH(AD$2,[3]평가!$6:$6,0)-1,FALSE),"③@ ") & CHAR(13) & TEXT(VLOOKUP($B209,[4]평가!$B:$Z,MATCH(AD$2,[4]평가!$6:$6,0)-1,FALSE),"④@ ") & CHAR(13) & TEXT(VLOOKUP($B209,[5]평가!$B:$Z,MATCH(AD$2,[5]평가!$6:$6,0)-1,FALSE),"⑤@ "),"") | AE209: =IFERROR(TEXT(VLOOKUP($B209,[1]평가!$B:$Z,MATCH(AE$2,[1]평가!$7:$7,0)-1,FALSE),"①@ ") & CHAR(13) & TEXT(VLOOKUP($B209,[2]평가!$B:$Z,MATCH(AE$2,[2]평가!$7:$7,0)-1,FALSE),"②@ ") & CHAR(13) & TEXT(VLOOKUP($B209,[3]평가!$B:$Z,MATCH(AE$2,[3]평가!$7:$7,0)-1,FALSE),"③@ ") & CHAR(13) & TEXT(VLOOKUP($B209,[4]평가!$B:$Z,MATCH(AE$2,[4]평가!$7:$7,0)-1,FALSE),"④@ ") & CHAR(13) & TEXT(VLOOKUP($B209,[5]평가!$B:$Z,MATCH(AE$2,[5]평가!$7:$7,0)-1,FALSE),"⑤@ "),"") | AF209: =IFERROR(TEXT(VLOOKUP($B209,[1]평가!$B:$Z,MATCH(AF$2,[1]평가!$6:$6,0)-1,FALSE),"①@ ") & CHAR(13) & TEXT(VLOOKUP($B209,[2]평가!$B:$Z,MATCH(AF$2,[2]평가!$6:$6,0)-1,FALSE),"②@ ") & CHAR(13) & TEXT(VLOOKUP($B209,[3]평가!$B:$Z,MATCH(AF$2,[3]평가!$6:$6,0)-1,FALSE),"③@ ") & CHAR(13) & TEXT(VLOOKUP($B209,[4]평가!$B:$Z,MATCH(AF$2,[4]평가!$6:$6,0)-1,FALSE),"④@ ") & CHAR(13) & TEXT(VLOOKUP($B209,[5]평가!$B:$Z,MATCH(AF$2,[5]평가!$6:$6,0)-1,FALSE),"⑤@ "),"")
A210: 208 | C210: =IFERROR(VLOOKUP($B210,대상!$B:$AC,MATCH(C$2,대상!$1:$1,0)-1,FALSE),"") | D210: =IFERROR(VLOOKUP($B210,대상!$B:$AC,MATCH(D$2,대상!$1:$1,0)-1,FALSE),"") | E210: =IFERROR(VLOOKUP($B210,대상!$B:$AC,MATCH(E$2,대상!$1:$1,0)-1,FALSE),"") | F210: =IFERROR(VLOOKUP($B210,대상!$B:$AC,MATCH(F$2,대상!$1:$1,0)-1,FALSE),"") | G210: =IFERROR(VLOOKUP($B210,대상!$B:$AC,MATCH(G$2,대상!$1:$1,0)-1,FALSE),"") | H210: =IFERROR(VLOOKUP($B210,[1]평가!$B:$Z,MATCH(LEFT(H$2,2),[1]평가!$7:$7,0)-1,FALSE),"") | I210: =IFERROR(VLOOKUP($B210,[1]평가!$B:$Z,MATCH(LEFT(I$2,2),[1]평가!$7:$7,0)-1,FALSE),"") | J210: =IFERROR(VLOOKUP($B210,[1]평가!$B:$Z,MATCH(LEFT(J$2,2),[1]평가!$7:$7,0)-1,FALSE),"") | K210: =IFERROR(VLOOKUP($B210,[2]평가!$B:$Z,MATCH(LEFT(K$2,2),[2]평가!$7:$7,0)-1,FALSE),"") | L210: =IFERROR(VLOOKUP($B210,[2]평가!$B:$Z,MATCH(LEFT(L$2,2),[2]평가!$7:$7,0)-1,FALSE),"") | M210: =IFERROR(VLOOKUP($B210,[2]평가!$B:$Z,MATCH(LEFT(M$2,2),[2]평가!$7:$7,0)-1,FALSE),"") | N210: =IFERROR(VLOOKUP($B210,[3]평가!$B:$Z,MATCH(LEFT(N$2,2),[3]평가!$7:$7,0)-1,FALSE),"") | O210: =IFERROR(VLOOKUP($B210,[3]평가!$B:$Z,MATCH(LEFT(O$2,2),[3]평가!$7:$7,0)-1,FALSE),"") | P210: =IFERROR(VLOOKUP($B210,[3]평가!$B:$Z,MATCH(LEFT(P$2,2),[3]평가!$7:$7,0)-1,FALSE),"") | Q210: =IFERROR(VLOOKUP($B210,[4]평가!$B:$Z,MATCH(LEFT(Q$2,2),[4]평가!$7:$7,0)-1,FALSE),"") | R210: =IFERROR(VLOOKUP($B210,[4]평가!$B:$Z,MATCH(LEFT(R$2,2),[4]평가!$7:$7,0)-1,FALSE),"") | S210: =IFERROR(VLOOKUP($B210,[4]평가!$B:$Z,MATCH(LEFT(S$2,2),[4]평가!$7:$7,0)-1,FALSE),"") | T210: =IFERROR(VLOOKUP($B210,[5]평가!$B:$Z,MATCH(LEFT(T$2,2),[5]평가!$7:$7,0)-1,FALSE),"") | U210: =IFERROR(VLOOKUP($B210,[5]평가!$B:$Z,MATCH(LEFT(U$2,2),[5]평가!$7:$7,0)-1,FALSE),"") | V210: =IFERROR(VLOOKUP($B210,[5]평가!$B:$Z,MATCH(LEFT(V$2,2),[5]평가!$7:$7,0)-1,FALSE),"") | W210: =IFERROR(VLOOKUP($B210,대상!$B:$AD,MATCH(W$2,대상!$1:$1,0)-1,FALSE),"") | X210: =IF(ISBLANK(B210),"",T$1-COUNTIF(H210:V210,"회피")) | Y210: =IF($T$1=X210,(SUM(I210,L210,O210,R210,U210)-MIN(I210,L210,O210,R210,U210)-MAX(I210,L210,O210,R210,U210))/($T$1-2),SUM(I210,L210,O210,R210,U210/X210)) -> #VALUE! | Z210: =IFERROR(VLOOKUP($B210,대상!$B:$AD,MATCH(Z$2,대상!$1:$1,0)-1,FALSE),0) -> 0 | AA210: =IFERROR(IF(W210="면제","100"+Z210,Y210+Z210),"") | AB210: =IF(OR(W210="면제",N(Y210)=0),"",IF(AA210<60,"과락","")) -> #VALUE! | AC210: =IF(N(AA210)=0,"",RANK(AA210,AA$3:AA$202)) | AD210: =IFERROR(TEXT(VLOOKUP($B210,[1]평가!$B:$Z,MATCH(AD$2,[1]평가!$6:$6,0)-1,FALSE),"①@ ") & CHAR(13) & TEXT(VLOOKUP($B210,[2]평가!$B:$Z,MATCH(AD$2,[2]평가!$6:$6,0)-1,FALSE),"②@ ") & CHAR(13) & TEXT(VLOOKUP($B210,[3]평가!$B:$Z,MATCH(AD$2,[3]평가!$6:$6,0)-1,FALSE),"③@ ") & CHAR(13) & TEXT(VLOOKUP($B210,[4]평가!$B:$Z,MATCH(AD$2,[4]평가!$6:$6,0)-1,FALSE),"④@ ") & CHAR(13) & TEXT(VLOOKUP($B210,[5]평가!$B:$Z,MATCH(AD$2,[5]평가!$6:$6,0)-1,FALSE),"⑤@ "),"") | AE210: =IFERROR(TEXT(VLOOKUP($B210,[1]평가!$B:$Z,MATCH(AE$2,[1]평가!$7:$7,0)-1,FALSE),"①@ ") & CHAR(13) & TEXT(VLOOKUP($B210,[2]평가!$B:$Z,MATCH(AE$2,[2]평가!$7:$7,0)-1,FALSE),"②@ ") & CHAR(13) & TEXT(VLOOKUP($B210,[3]평가!$B:$Z,MATCH(AE$2,[3]평가!$7:$7,0)-1,FALSE),"③@ ") & CHAR(13) & TEXT(VLOOKUP($B210,[4]평가!$B:$Z,MATCH(AE$2,[4]평가!$7:$7,0)-1,FALSE),"④@ ") & CHAR(13) & TEXT(VLOOKUP($B210,[5]평가!$B:$Z,MATCH(AE$2,[5]평가!$7:$7,0)-1,FALSE),"⑤@ "),"") | AF210: =IFERROR(TEXT(VLOOKUP($B210,[1]평가!$B:$Z,MATCH(AF$2,[1]평가!$6:$6,0)-1,FALSE),"①@ ") & CHAR(13) & TEXT(VLOOKUP($B210,[2]평가!$B:$Z,MATCH(AF$2,[2]평가!$6:$6,0)-1,FALSE),"②@ ") & CHAR(13) & TEXT(VLOOKUP($B210,[3]평가!$B:$Z,MATCH(AF$2,[3]평가!$6:$6,0)-1,FALSE),"③@ ") & CHAR(13) & TEXT(VLOOKUP($B210,[4]평가!$B:$Z,MATCH(AF$2,[4]평가!$6:$6,0)-1,FALSE),"④@ ") & CHAR(13) & TEXT(VLOOKUP($B210,[5]평가!$B:$Z,MATCH(AF$2,[5]평가!$6:$6,0)-1,FALSE),"⑤@ "),"")
A211: 209 | C211: =IFERROR(VLOOKUP($B211,대상!$B:$AC,MATCH(C$2,대상!$1:$1,0)-1,FALSE),"") | D211: =IFERROR(VLOOKUP($B211,대상!$B:$AC,MATCH(D$2,대상!$1:$1,0)-1,FALSE),"") | E211: =IFERROR(VLOOKUP($B211,대상!$B:$AC,MATCH(E$2,대상!$1:$1,0)-1,FALSE),"") | F211: =IFERROR(VLOOKUP($B211,대상!$B:$AC,MATCH(F$2,대상!$1:$1,0)-1,FALSE),"") | G211: =IFERROR(VLOOKUP($B211,대상!$B:$AC,MATCH(G$2,대상!$1:$1,0)-1,FALSE),"") | H211: =IFERROR(VLOOKUP($B211,[1]평가!$B:$Z,MATCH(LEFT(H$2,2),[1]평가!$7:$7,0)-1,FALSE),"") | I211: =IFERROR(VLOOKUP($B211,[1]평가!$B:$Z,MATCH(LEFT(I$2,2),[1]평가!$7:$7,0)-1,FALSE),"") | J211: =IFERROR(VLOOKUP($B211,[1]평가!$B:$Z,MATCH(LEFT(J$2,2),[1]평가!$7:$7,0)-1,FALSE),"") | K211: =IFERROR(VLOOKUP($B211,[2]평가!$B:$Z,MATCH(LEFT(K$2,2),[2]평가!$7:$7,0)-1,FALSE),"") | L211: =IFERROR(VLOOKUP($B211,[2]평가!$B:$Z,MATCH(LEFT(L$2,2),[2]평가!$7:$7,0)-1,FALSE),"") | M211: =IFERROR(VLOOKUP($B211,[2]평가!$B:$Z,MATCH(LEFT(M$2,2),[2]평가!$7:$7,0)-1,FALSE),"") | N211: =IFERROR(VLOOKUP($B211,[3]평가!$B:$Z,MATCH(LEFT(N$2,2),[3]평가!$7:$7,0)-1,FALSE),"") | O211: =IFERROR(VLOOKUP($B211,[3]평가!$B:$Z,MATCH(LEFT(O$2,2),[3]평가!$7:$7,0)-1,FALSE),"") | P211: =IFERROR(VLOOKUP($B211,[3]평가!$B:$Z,MATCH(LEFT(P$2,2),[3]평가!$7:$7,0)-1,FALSE),"") | Q211: =IFERROR(VLOOKUP($B211,[4]평가!$B:$Z,MATCH(LEFT(Q$2,2),[4]평가!$7:$7,0)-1,FALSE),"") | R211: =IFERROR(VLOOKUP($B211,[4]평가!$B:$Z,MATCH(LEFT(R$2,2),[4]평가!$7:$7,0)-1,FALSE),"") | S211: =IFERROR(VLOOKUP($B211,[4]평가!$B:$Z,MATCH(LEFT(S$2,2),[4]평가!$7:$7,0)-1,FALSE),"") | T211: =IFERROR(VLOOKUP($B211,[5]평가!$B:$Z,MATCH(LEFT(T$2,2),[5]평가!$7:$7,0)-1,FALSE),"") | U211: =IFERROR(VLOOKUP($B211,[5]평가!$B:$Z,MATCH(LEFT(U$2,2),[5]평가!$7:$7,0)-1,FALSE),"") | V211: =IFERROR(VLOOKUP($B211,[5]평가!$B:$Z,MATCH(LEFT(V$2,2),[5]평가!$7:$7,0)-1,FALSE),"") | W211: =IFERROR(VLOOKUP($B211,대상!$B:$AD,MATCH(W$2,대상!$1:$1,0)-1,FALSE),"") | X211: =IF(ISBLANK(B211),"",T$1-COUNTIF(H211:V211,"회피")) | Y211: =IF($T$1=X211,(SUM(I211,L211,O211,R211,U211)-MIN(I211,L211,O211,R211,U211)-MAX(I211,L211,O211,R211,U211))/($T$1-2),SUM(I211,L211,O211,R211,U211/X211)) -> #VALUE! | Z211: =IFERROR(VLOOKUP($B211,대상!$B:$AD,MATCH(Z$2,대상!$1:$1,0)-1,FALSE),0) -> 0 | AA211: =IFERROR(IF(W211="면제","100"+Z211,Y211+Z211),"") | AB211: =IF(OR(W211="면제",N(Y211)=0),"",IF(AA211<60,"과락","")) -> #VALUE! | AC211: =IF(N(AA211)=0,"",RANK(AA211,AA$3:AA$202)) | AD211: =IFERROR(TEXT(VLOOKUP($B211,[1]평가!$B:$Z,MATCH(AD$2,[1]평가!$6:$6,0)-1,FALSE),"①@ ") & CHAR(13) & TEXT(VLOOKUP($B211,[2]평가!$B:$Z,MATCH(AD$2,[2]평가!$6:$6,0)-1,FALSE),"②@ ") & CHAR(13) & TEXT(VLOOKUP($B211,[3]평가!$B:$Z,MATCH(AD$2,[3]평가!$6:$6,0)-1,FALSE),"③@ ") & CHAR(13) & TEXT(VLOOKUP($B211,[4]평가!$B:$Z,MATCH(AD$2,[4]평가!$6:$6,0)-1,FALSE),"④@ ") & CHAR(13) & TEXT(VLOOKUP($B211,[5]평가!$B:$Z,MATCH(AD$2,[5]평가!$6:$6,0)-1,FALSE),"⑤@ "),"") | AE211: =IFERROR(TEXT(VLOOKUP($B211,[1]평가!$B:$Z,MATCH(AE$2,[1]평가!$7:$7,0)-1,FALSE),"①@ ") & CHAR(13) & TEXT(VLOOKUP($B211,[2]평가!$B:$Z,MATCH(AE$2,[2]평가!$7:$7,0)-1,FALSE),"②@ ") & CHAR(13) & TEXT(VLOOKUP($B211,[3]평가!$B:$Z,MATCH(AE$2,[3]평가!$7:$7,0)-1,FALSE),"③@ ") & CHAR(13) & TEXT(VLOOKUP($B211,[4]평가!$B:$Z,MATCH(AE$2,[4]평가!$7:$7,0)-1,FALSE),"④@ ") & CHAR(13) & TEXT(VLOOKUP($B211,[5]평가!$B:$Z,MATCH(AE$2,[5]평가!$7:$7,0)-1,FALSE),"⑤@ "),"") | AF211: =IFERROR(TEXT(VLOOKUP($B211,[1]평가!$B:$Z,MATCH(AF$2,[1]평가!$6:$6,0)-1,FALSE),"①@ ") & CHAR(13) & TEXT(VLOOKUP($B211,[2]평가!$B:$Z,MATCH(AF$2,[2]평가!$6:$6,0)-1,FALSE),"②@ ") & CHAR(13) & TEXT(VLOOKUP($B211,[3]평가!$B:$Z,MATCH(AF$2,[3]평가!$6:$6,0)-1,FALSE),"③@ ") & CHAR(13) & TEXT(VLOOKUP($B211,[4]평가!$B:$Z,MATCH(AF$2,[4]평가!$6:$6,0)-1,FALSE),"④@ ") & CHAR(13) & TEXT(VLOOKUP($B211,[5]평가!$B:$Z,MATCH(AF$2,[5]평가!$6:$6,0)-1,FALSE),"⑤@ "),"")
A212: 210 | C212: =IFERROR(VLOOKUP($B212,대상!$B:$AC,MATCH(C$2,대상!$1:$1,0)-1,FALSE),"") | D212: =IFERROR(VLOOKUP($B212,대상!$B:$AC,MATCH(D$2,대상!$1:$1,0)-1,FALSE),"") | E212: =IFERROR(VLOOKUP($B212,대상!$B:$AC,MATCH(E$2,대상!$1:$1,0)-1,FALSE),"") | F212: =IFERROR(VLOOKUP($B212,대상!$B:$AC,MATCH(F$2,대상!$1:$1,0)-1,FALSE),"") | G212: =IFERROR(VLOOKUP($B212,대상!$B:$AC,MATCH(G$2,대상!$1:$1,0)-1,FALSE),"") | H212: =IFERROR(VLOOKUP($B212,[1]평가!$B:$Z,MATCH(LEFT(H$2,2),[1]평가!$7:$7,0)-1,FALSE),"") | I212: =IFERROR(VLOOKUP($B212,[1]평가!$B:$Z,MATCH(LEFT(I$2,2),[1]평가!$7:$7,0)-1,FALSE),"") | J212: =IFERROR(VLOOKUP($B212,[1]평가!$B:$Z,MATCH(LEFT(J$2,2),[1]평가!$7:$7,0)-1,FALSE),"") | K212: =IFERROR(VLOOKUP($B212,[2]평가!$B:$Z,MATCH(LEFT(K$2,2),[2]평가!$7:$7,0)-1,FALSE),"") | L212: =IFERROR(VLOOKUP($B212,[2]평가!$B:$Z,MATCH(LEFT(L$2,2),[2]평가!$7:$7,0)-1,FALSE),"") | M212: =IFERROR(VLOOKUP($B212,[2]평가!$B:$Z,MATCH(LEFT(M$2,2),[2]평가!$7:$7,0)-1,FALSE),"") | N212: =IFERROR(VLOOKUP($B212,[3]평가!$B:$Z,MATCH(LEFT(N$2,2),[3]평가!$7:$7,0)-1,FALSE),"") | O212: =IFERROR(VLOOKUP($B212,[3]평가!$B:$Z,MATCH(LEFT(O$2,2),[3]평가!$7:$7,0)-1,FALSE),"") | P212: =IFERROR(VLOOKUP($B212,[3]평가!$B:$Z,MATCH(LEFT(P$2,2),[3]평가!$7:$7,0)-1,FALSE),"") | Q212: =IFERROR(VLOOKUP($B212,[4]평가!$B:$Z,MATCH(LEFT(Q$2,2),[4]평가!$7:$7,0)-1,FALSE),"") | R212: =IFERROR(VLOOKUP($B212,[4]평가!$B:$Z,MATCH(LEFT(R$2,2),[4]평가!$7:$7,0)-1,FALSE),"") | S212: =IFERROR(VLOOKUP($B212,[4]평가!$B:$Z,MATCH(LEFT(S$2,2),[4]평가!$7:$7,0)-1,FALSE),"") | T212: =IFERROR(VLOOKUP($B212,[5]평가!$B:$Z,MATCH(LEFT(T$2,2),[5]평가!$7:$7,0)-1,FALSE),"") | U212: =IFERROR(VLOOKUP($B212,[5]평가!$B:$Z,MATCH(LEFT(U$2,2),[5]평가!$7:$7,0)-1,FALSE),"") | V212: =IFERROR(VLOOKUP($B212,[5]평가!$B:$Z,MATCH(LEFT(V$2,2),[5]평가!$7:$7,0)-1,FALSE),"") | W212: =IFERROR(VLOOKUP($B212,대상!$B:$AD,MATCH(W$2,대상!$1:$1,0)-1,FALSE),"") | X212: =IF(ISBLANK(B212),"",T$1-COUNTIF(H212:V212,"회피")) | Y212: =IF($T$1=X212,(SUM(I212,L212,O212,R212,U212)-MIN(I212,L212,O212,R212,U212)-MAX(I212,L212,O212,R212,U212))/($T$1-2),SUM(I212,L212,O212,R212,U212/X212)) -> #VALUE! | Z212: =IFERROR(VLOOKUP($B212,대상!$B:$AD,MATCH(Z$2,대상!$1:$1,0)-1,FALSE),0) -> 0 | AA212: =IFERROR(IF(W212="면제","100"+Z212,Y212+Z212),"") | AB212: =IF(OR(W212="면제",N(Y212)=0),"",IF(AA212<60,"과락","")) -> #VALUE! | AC212: =IF(N(AA212)=0,"",RANK(AA212,AA$3:AA$202)) | AD212: =IFERROR(TEXT(VLOOKUP($B212,[1]평가!$B:$Z,MATCH(AD$2,[1]평가!$6:$6,0)-1,FALSE),"①@ ") & CHAR(13) & TEXT(VLOOKUP($B212,[2]평가!$B:$Z,MATCH(AD$2,[2]평가!$6:$6,0)-1,FALSE),"②@ ") & CHAR(13) & TEXT(VLOOKUP($B212,[3]평가!$B:$Z,MATCH(AD$2,[3]평가!$6:$6,0)-1,FALSE),"③@ ") & CHAR(13) & TEXT(VLOOKUP($B212,[4]평가!$B:$Z,MATCH(AD$2,[4]평가!$6:$6,0)-1,FALSE),"④@ ") & CHAR(13) & TEXT(VLOOKUP($B212,[5]평가!$B:$Z,MATCH(AD$2,[5]평가!$6:$6,0)-1,FALSE),"⑤@ "),"") | AE212: =IFERROR(TEXT(VLOOKUP($B212,[1]평가!$B:$Z,MATCH(AE$2,[1]평가!$7:$7,0)-1,FALSE),"①@ ") & CHAR(13) & TEXT(VLOOKUP($B212,[2]평가!$B:$Z,MATCH(AE$2,[2]평가!$7:$7,0)-1,FALSE),"②@ ") & CHAR(13) & TEXT(VLOOKUP($B212,[3]평가!$B:$Z,MATCH(AE$2,[3]평가!$7:$7,0)-1,FALSE),"③@ ") & CHAR(13) & TEXT(VLOOKUP($B212,[4]평가!$B:$Z,MATCH(AE$2,[4]평가!$7:$7,0)-1,FALSE),"④@ ") & CHAR(13) & TEXT(VLOOKUP($B212,[5]평가!$B:$Z,MATCH(AE$2,[5]평가!$7:$7,0)-1,FALSE),"⑤@ "),"") | AF212: =IFERROR(TEXT(VLOOKUP($B212,[1]평가!$B:$Z,MATCH(AF$2,[1]평가!$6:$6,0)-1,FALSE),"①@ ") & CHAR(13) & TEXT(VLOOKUP($B212,[2]평가!$B:$Z,MATCH(AF$2,[2]평가!$6:$6,0)-1,FALSE),"②@ ") & CHAR(13) & TEXT(VLOOKUP($B212,[3]평가!$B:$Z,MATCH(AF$2,[3]평가!$6:$6,0)-1,FALSE),"③@ ") & CHAR(13) & TEXT(VLOOKUP($B212,[4]평가!$B:$Z,MATCH(AF$2,[4]평가!$6:$6,0)-1,FALSE),"④@ ") & CHAR(13) & TEXT(VLOOKUP($B212,[5]평가!$B:$Z,MATCH(AF$2,[5]평가!$6:$6,0)-1,FALSE),"⑤@ "),"")
A213: 211 | C213: =IFERROR(VLOOKUP($B213,대상!$B:$AC,MATCH(C$2,대상!$1:$1,0)-1,FALSE),"") | D213: =IFERROR(VLOOKUP($B213,대상!$B:$AC,MATCH(D$2,대상!$1:$1,0)-1,FALSE),"") | E213: =IFERROR(VLOOKUP($B213,대상!$B:$AC,MATCH(E$2,대상!$1:$1,0)-1,FALSE),"") | F213: =IFERROR(VLOOKUP($B213,대상!$B:$AC,MATCH(F$2,대상!$1:$1,0)-1,FALSE),"") | G213: =IFERROR(VLOOKUP($B213,대상!$B:$AC,MATCH(G$2,대상!$1:$1,0)-1,FALSE),"") | H213: =IFERROR(VLOOKUP($B213,[1]평가!$B:$Z,MATCH(LEFT(H$2,2),[1]평가!$7:$7,0)-1,FALSE),"") | I213: =IFERROR(VLOOKUP($B213,[1]평가!$B:$Z,MATCH(LEFT(I$2,2),[1]평가!$7:$7,0)-1,FALSE),"") | J213: =IFERROR(VLOOKUP($B213,[1]평가!$B:$Z,MATCH(LEFT(J$2,2),[1]평가!$7:$7,0)-1,FALSE),"") | K213: =IFERROR(VLOOKUP($B213,[2]평가!$B:$Z,MATCH(LEFT(K$2,2),[2]평가!$7:$7,0)-1,FALSE),"") | L213: =IFERROR(VLOOKUP($B213,[2]평가!$B:$Z,MATCH(LEFT(L$2,2),[2]평가!$7:$7,0)-1,FALSE),"") | M213: =IFERROR(VLOOKUP($B213,[2]평가!$B:$Z,MATCH(LEFT(M$2,2),[2]평가!$7:$7,0)-1,FALSE),"") | N213: =IFERROR(VLOOKUP($B213,[3]평가!$B:$Z,MATCH(LEFT(N$2,2),[3]평가!$7:$7,0)-1,FALSE),"") | O213: =IFERROR(VLOOKUP($B213,[3]평가!$B:$Z,MATCH(LEFT(O$2,2),[3]평가!$7:$7,0)-1,FALSE),"") | P213: =IFERROR(VLOOKUP($B213,[3]평가!$B:$Z,MATCH(LEFT(P$2,2),[3]평가!$7:$7,0)-1,FALSE),"") | Q213: =IFERROR(VLOOKUP($B213,[4]평가!$B:$Z,MATCH(LEFT(Q$2,2),[4]평가!$7:$7,0)-1,FALSE),"") | R213: =IFERROR(VLOOKUP($B213,[4]평가!$B:$Z,MATCH(LEFT(R$2,2),[4]평가!$7:$7,0)-1,FALSE),"") | S213: =IFERROR(VLOOKUP($B213,[4]평가!$B:$Z,MATCH(LEFT(S$2,2),[4]평가!$7:$7,0)-1,FALSE),"") | T213: =IFERROR(VLOOKUP($B213,[5]평가!$B:$Z,MATCH(LEFT(T$2,2),[5]평가!$7:$7,0)-1,FALSE),"") | U213: =IFERROR(VLOOKUP($B213,[5]평가!$B:$Z,MATCH(LEFT(U$2,2),[5]평가!$7:$7,0)-1,FALSE),"") | V213: =IFERROR(VLOOKUP($B213,[5]평가!$B:$Z,MATCH(LEFT(V$2,2),[5]평가!$7:$7,0)-1,FALSE),"") | W213: =IFERROR(VLOOKUP($B213,대상!$B:$AD,MATCH(W$2,대상!$1:$1,0)-1,FALSE),"") | X213: =IF(ISBLANK(B213),"",T$1-COUNTIF(H213:V213,"회피")) | Y213: =IF($T$1=X213,(SUM(I213,L213,O213,R213,U213)-MIN(I213,L213,O213,R213,U213)-MAX(I213,L213,O213,R213,U213))/($T$1-2),SUM(I213,L213,O213,R213,U213/X213)) -> #VALUE! | Z213: =IFERROR(VLOOKUP($B213,대상!$B:$AD,MATCH(Z$2,대상!$1:$1,0)-1,FALSE),0) -> 0 | AA213: =IFERROR(IF(W213="면제","100"+Z213,Y213+Z213),"") | AB213: =IF(OR(W213="면제",N(Y213)=0),"",IF(AA213<60,"과락","")) -> #VALUE! | AC213: =IF(N(AA213)=0,"",RANK(AA213,AA$3:AA$202)) | AD213: =IFERROR(TEXT(VLOOKUP($B213,[1]평가!$B:$Z,MATCH(AD$2,[1]평가!$6:$6,0)-1,FALSE),"①@ ") & CHAR(13) & TEXT(VLOOKUP($B213,[2]평가!$B:$Z,MATCH(AD$2,[2]평가!$6:$6,0)-1,FALSE),"②@ ") & CHAR(13) & TEXT(VLOOKUP($B213,[3]평가!$B:$Z,MATCH(AD$2,[3]평가!$6:$6,0)-1,FALSE),"③@ ") & CHAR(13) & TEXT(VLOOKUP($B213,[4]평가!$B:$Z,MATCH(AD$2,[4]평가!$6:$6,0)-1,FALSE),"④@ ") & CHAR(13) & TEXT(VLOOKUP($B213,[5]평가!$B:$Z,MATCH(AD$2,[5]평가!$6:$6,0)-1,FALSE),"⑤@ "),"") | AE213: =IFERROR(TEXT(VLOOKUP($B213,[1]평가!$B:$Z,MATCH(AE$2,[1]평가!$7:$7,0)-1,FALSE),"①@ ") & CHAR(13) & TEXT(VLOOKUP($B213,[2]평가!$B:$Z,MATCH(AE$2,[2]평가!$7:$7,0)-1,FALSE),"②@ ") & CHAR(13) & TEXT(VLOOKUP($B213,[3]평가!$B:$Z,MATCH(AE$2,[3]평가!$7:$7,0)-1,FALSE),"③@ ") & CHAR(13) & TEXT(VLOOKUP($B213,[4]평가!$B:$Z,MATCH(AE$2,[4]평가!$7:$7,0)-1,FALSE),"④@ ") & CHAR(13) & TEXT(VLOOKUP($B213,[5]평가!$B:$Z,MATCH(AE$2,[5]평가!$7:$7,0)-1,FALSE),"⑤@ "),"") | AF213: =IFERROR(TEXT(VLOOKUP($B213,[1]평가!$B:$Z,MATCH(AF$2,[1]평가!$6:$6,0)-1,FALSE),"①@ ") & CHAR(13) & TEXT(VLOOKUP($B213,[2]평가!$B:$Z,MATCH(AF$2,[2]평가!$6:$6,0)-1,FALSE),"②@ ") & CHAR(13) & TEXT(VLOOKUP($B213,[3]평가!$B:$Z,MATCH(AF$2,[3]평가!$6:$6,0)-1,FALSE),"③@ ") & CHAR(13) & TEXT(VLOOKUP($B213,[4]평가!$B:$Z,MATCH(AF$2,[4]평가!$6:$6,0)-1,FALSE),"④@ ") & CHAR(13) & TEXT(VLOOKUP($B213,[5]평가!$B:$Z,MATCH(AF$2,[5]평가!$6:$6,0)-1,FALSE),"⑤@ "),"")
A214: 212 | C214: =IFERROR(VLOOKUP($B214,대상!$B:$AC,MATCH(C$2,대상!$1:$1,0)-1,FALSE),"") | D214: =IFERROR(VLOOKUP($B214,대상!$B:$AC,MATCH(D$2,대상!$1:$1,0)-1,FALSE),"") | E214: =IFERROR(VLOOKUP($B214,대상!$B:$AC,MATCH(E$2,대상!$1:$1,0)-1,FALSE),"") | F214: =IFERROR(VLOOKUP($B214,대상!$B:$AC,MATCH(F$2,대상!$1:$1,0)-1,FALSE),"") | G214: =IFERROR(VLOOKUP($B214,대상!$B:$AC,MATCH(G$2,대상!$1:$1,0)-1,FALSE),"") | H214: =IFERROR(VLOOKUP($B214,[1]평가!$B:$Z,MATCH(LEFT(H$2,2),[1]평가!$7:$7,0)-1,FALSE),"") | I214: =IFERROR(VLOOKUP($B214,[1]평가!$B:$Z,MATCH(LEFT(I$2,2),[1]평가!$7:$7,0)-1,FALSE),"") | J214: =IFERROR(VLOOKUP($B214,[1]평가!$B:$Z,MATCH(LEFT(J$2,2),[1]평가!$7:$7,0)-1,FALSE),"") | K214: =IFERROR(VLOOKUP($B214,[2]평가!$B:$Z,MATCH(LEFT(K$2,2),[2]평가!$7:$7,0)-1,FALSE),"") | L214: =IFERROR(VLOOKUP($B214,[2]평가!$B:$Z,MATCH(LEFT(L$2,2),[2]평가!$7:$7,0)-1,FALSE),"") | M214: =IFERROR(VLOOKUP($B214,[2]평가!$B:$Z,MATCH(LEFT(M$2,2),[2]평가!$7:$7,0)-1,FALSE),"") | N214: =IFERROR(VLOOKUP($B214,[3]평가!$B:$Z,MATCH(LEFT(N$2,2),[3]평가!$7:$7,0)-1,FALSE),"") | O214: =IFERROR(VLOOKUP($B214,[3]평가!$B:$Z,MATCH(LEFT(O$2,2),[3]평가!$7:$7,0)-1,FALSE),"") | P214: =IFERROR(VLOOKUP($B214,[3]평가!$B:$Z,MATCH(LEFT(P$2,2),[3]평가!$7:$7,0)-1,FALSE),"") | Q214: =IFERROR(VLOOKUP($B214,[4]평가!$B:$Z,MATCH(LEFT(Q$2,2),[4]평가!$7:$7,0)-1,FALSE),"") | R214: =IFERROR(VLOOKUP($B214,[4]평가!$B:$Z,MATCH(LEFT(R$2,2),[4]평가!$7:$7,0)-1,FALSE),"") | S214: =IFERROR(VLOOKUP($B214,[4]평가!$B:$Z,MATCH(LEFT(S$2,2),[4]평가!$7:$7,0)-1,FALSE),"") | T214: =IFERROR(VLOOKUP($B214,[5]평가!$B:$Z,MATCH(LEFT(T$2,2),[5]평가!$7:$7,0)-1,FALSE),"") | U214: =IFERROR(VLOOKUP($B214,[5]평가!$B:$Z,MATCH(LEFT(U$2,2),[5]평가!$7:$7,0)-1,FALSE),"") | V214: =IFERROR(VLOOKUP($B214,[5]평가!$B:$Z,MATCH(LEFT(V$2,2),[5]평가!$7:$7,0)-1,FALSE),"") | W214: =IFERROR(VLOOKUP($B214,대상!$B:$AD,MATCH(W$2,대상!$1:$1,0)-1,FALSE),"") | X214: =IF(ISBLANK(B214),"",T$1-COUNTIF(H214:V214,"회피")) | Y214: =IF($T$1=X214,(SUM(I214,L214,O214,R214,U214)-MIN(I214,L214,O214,R214,U214)-MAX(I214,L214,O214,R214,U214))/($T$1-2),SUM(I214,L214,O214,R214,U214/X214)) -> #VALUE! | Z214: =IFERROR(VLOOKUP($B214,대상!$B:$AD,MATCH(Z$2,대상!$1:$1,0)-1,FALSE),0) -> 0 | AA214: =IFERROR(IF(W214="면제","100"+Z214,Y214+Z214),"") | AB214: =IF(OR(W214="면제",N(Y214)=0),"",IF(AA214<60,"과락","")) -> #VALUE! | AC214: =IF(N(AA214)=0,"",RANK(AA214,AA$3:AA$202)) | AD214: =IFERROR(TEXT(VLOOKUP($B214,[1]평가!$B:$Z,MATCH(AD$2,[1]평가!$6:$6,0)-1,FALSE),"①@ ") & CHAR(13) & TEXT(VLOOKUP($B214,[2]평가!$B:$Z,MATCH(AD$2,[2]평가!$6:$6,0)-1,FALSE),"②@ ") & CHAR(13) & TEXT(VLOOKUP($B214,[3]평가!$B:$Z,MATCH(AD$2,[3]평가!$6:$6,0)-1,FALSE),"③@ ") & CHAR(13) & TEXT(VLOOKUP($B214,[4]평가!$B:$Z,MATCH(AD$2,[4]평가!$6:$6,0)-1,FALSE),"④@ ") & CHAR(13) & TEXT(VLOOKUP($B214,[5]평가!$B:$Z,MATCH(AD$2,[5]평가!$6:$6,0)-1,FALSE),"⑤@ "),"") | AE214: =IFERROR(TEXT(VLOOKUP($B214,[1]평가!$B:$Z,MATCH(AE$2,[1]평가!$7:$7,0)-1,FALSE),"①@ ") & CHAR(13) & TEXT(VLOOKUP($B214,[2]평가!$B:$Z,MATCH(AE$2,[2]평가!$7:$7,0)-1,FALSE),"②@ ") & CHAR(13) & TEXT(VLOOKUP($B214,[3]평가!$B:$Z,MATCH(AE$2,[3]평가!$7:$7,0)-1,FALSE),"③@ ") & CHAR(13) & TEXT(VLOOKUP($B214,[4]평가!$B:$Z,MATCH(AE$2,[4]평가!$7:$7,0)-1,FALSE),"④@ ") & CHAR(13) & TEXT(VLOOKUP($B214,[5]평가!$B:$Z,MATCH(AE$2,[5]평가!$7:$7,0)-1,FALSE),"⑤@ "),"") | AF214: =IFERROR(TEXT(VLOOKUP($B214,[1]평가!$B:$Z,MATCH(AF$2,[1]평가!$6:$6,0)-1,FALSE),"①@ ") & CHAR(13) & TEXT(VLOOKUP($B214,[2]평가!$B:$Z,MATCH(AF$2,[2]평가!$6:$6,0)-1,FALSE),"②@ ") & CHAR(13) & TEXT(VLOOKUP($B214,[3]평가!$B:$Z,MATCH(AF$2,[3]평가!$6:$6,0)-1,FALSE),"③@ ") & CHAR(13) & TEXT(VLOOKUP($B214,[4]평가!$B:$Z,MATCH(AF$2,[4]평가!$6:$6,0)-1,FALSE),"④@ ") & CHAR(13) & TEXT(VLOOKUP($B214,[5]평가!$B:$Z,MATCH(AF$2,[5]평가!$6:$6,0)-1,FALSE),"⑤@ "),"")
A215: 213 | C215: =IFERROR(VLOOKUP($B215,대상!$B:$AC,MATCH(C$2,대상!$1:$1,0)-1,FALSE),"") | D215: =IFERROR(VLOOKUP($B215,대상!$B:$AC,MATCH(D$2,대상!$1:$1,0)-1,FALSE),"") | E215: =IFERROR(VLOOKUP($B215,대상!$B:$AC,MATCH(E$2,대상!$1:$1,0)-1,FALSE),"") | F215: =IFERROR(VLOOKUP($B215,대상!$B:$AC,MATCH(F$2,대상!$1:$1,0)-1,FALSE),"") | G215: =IFERROR(VLOOKUP($B215,대상!$B:$AC,MATCH(G$2,대상!$1:$1,0)-1,FALSE),"") | H215: =IFERROR(VLOOKUP($B215,[1]평가!$B:$Z,MATCH(LEFT(H$2,2),[1]평가!$7:$7,0)-1,FALSE),"") | I215: =IFERROR(VLOOKUP($B215,[1]평가!$B:$Z,MATCH(LEFT(I$2,2),[1]평가!$7:$7,0)-1,FALSE),"") | J215: =IFERROR(VLOOKUP($B215,[1]평가!$B:$Z,MATCH(LEFT(J$2,2),[1]평가!$7:$7,0)-1,FALSE),"") | K215: =IFERROR(VLOOKUP($B215,[2]평가!$B:$Z,MATCH(LEFT(K$2,2),[2]평가!$7:$7,0)-1,FALSE),"") | L215: =IFERROR(VLOOKUP($B215,[2]평가!$B:$Z,MATCH(LEFT(L$2,2),[2]평가!$7:$7,0)-1,FALSE),"") | M215: =IFERROR(VLOOKUP($B215,[2]평가!$B:$Z,MATCH(LEFT(M$2,2),[2]평가!$7:$7,0)-1,FALSE),"") | N215: =IFERROR(VLOOKUP($B215,[3]평가!$B:$Z,MATCH(LEFT(N$2,2),[3]평가!$7:$7,0)-1,FALSE),"") | O215: =IFERROR(VLOOKUP($B215,[3]평가!$B:$Z,MATCH(LEFT(O$2,2),[3]평가!$7:$7,0)-1,FALSE),"") | P215: =IFERROR(VLOOKUP($B215,[3]평가!$B:$Z,MATCH(LEFT(P$2,2),[3]평가!$7:$7,0)-1,FALSE),"") | Q215: =IFERROR(VLOOKUP($B215,[4]평가!$B:$Z,MATCH(LEFT(Q$2,2),[4]평가!$7:$7,0)-1,FALSE),"") | R215: =IFERROR(VLOOKUP($B215,[4]평가!$B:$Z,MATCH(LEFT(R$2,2),[4]평가!$7:$7,0)-1,FALSE),"") | S215: =IFERROR(VLOOKUP($B215,[4]평가!$B:$Z,MATCH(LEFT(S$2,2),[4]평가!$7:$7,0)-1,FALSE),"") | T215: =IFERROR(VLOOKUP($B215,[5]평가!$B:$Z,MATCH(LEFT(T$2,2),[5]평가!$7:$7,0)-1,FALSE),"") | U215: =IFERROR(VLOOKUP($B215,[5]평가!$B:$Z,MATCH(LEFT(U$2,2),[5]평가!$7:$7,0)-1,FALSE),"") | V215: =IFERROR(VLOOKUP($B215,[5]평가!$B:$Z,MATCH(LEFT(V$2,2),[5]평가!$7:$7,0)-1,FALSE),"") | W215: =IFERROR(VLOOKUP($B215,대상!$B:$AD,MATCH(W$2,대상!$1:$1,0)-1,FALSE),"") | X215: =IF(ISBLANK(B215),"",T$1-COUNTIF(H215:V215,"회피")) | Y215: =IF($T$1=X215,(SUM(I215,L215,O215,R215,U215)-MIN(I215,L215,O215,R215,U215)-MAX(I215,L215,O215,R215,U215))/($T$1-2),SUM(I215,L215,O215,R215,U215/X215)) -> #VALUE! | Z215: =IFERROR(VLOOKUP($B215,대상!$B:$AD,MATCH(Z$2,대상!$1:$1,0)-1,FALSE),0) -> 0 | AA215: =IFERROR(IF(W215="면제","100"+Z215,Y215+Z215),"") | AB215: =IF(OR(W215="면제",N(Y215)=0),"",IF(AA215<60,"과락","")) -> #VALUE! | AC215: =IF(N(AA215)=0,"",RANK(AA215,AA$3:AA$202)) | AD215: =IFERROR(TEXT(VLOOKUP($B215,[1]평가!$B:$Z,MATCH(AD$2,[1]평가!$6:$6,0)-1,FALSE),"①@ ") & CHAR(13) & TEXT(VLOOKUP($B215,[2]평가!$B:$Z,MATCH(AD$2,[2]평가!$6:$6,0)-1,FALSE),"②@ ") & CHAR(13) & TEXT(VLOOKUP($B215,[3]평가!$B:$Z,MATCH(AD$2,[3]평가!$6:$6,0)-1,FALSE),"③@ ") & CHAR(13) & TEXT(VLOOKUP($B215,[4]평가!$B:$Z,MATCH(AD$2,[4]평가!$6:$6,0)-1,FALSE),"④@ ") & CHAR(13) & TEXT(VLOOKUP($B215,[5]평가!$B:$Z,MATCH(AD$2,[5]평가!$6:$6,0)-1,FALSE),"⑤@ "),"") | AE215: =IFERROR(TEXT(VLOOKUP($B215,[1]평가!$B:$Z,MATCH(AE$2,[1]평가!$7:$7,0)-1,FALSE),"①@ ") & CHAR(13) & TEXT(VLOOKUP($B215,[2]평가!$B:$Z,MATCH(AE$2,[2]평가!$7:$7,0)-1,FALSE),"②@ ") & CHAR(13) & TEXT(VLOOKUP($B215,[3]평가!$B:$Z,MATCH(AE$2,[3]평가!$7:$7,0)-1,FALSE),"③@ ") & CHAR(13) & TEXT(VLOOKUP($B215,[4]평가!$B:$Z,MATCH(AE$2,[4]평가!$7:$7,0)-1,FALSE),"④@ ") & CHAR(13) & TEXT(VLOOKUP($B215,[5]평가!$B:$Z,MATCH(AE$2,[5]평가!$7:$7,0)-1,FALSE),"⑤@ "),"") | AF215: =IFERROR(TEXT(VLOOKUP($B215,[1]평가!$B:$Z,MATCH(AF$2,[1]평가!$6:$6,0)-1,FALSE),"①@ ") & CHAR(13) & TEXT(VLOOKUP($B215,[2]평가!$B:$Z,MATCH(AF$2,[2]평가!$6:$6,0)-1,FALSE),"②@ ") & CHAR(13) & TEXT(VLOOKUP($B215,[3]평가!$B:$Z,MATCH(AF$2,[3]평가!$6:$6,0)-1,FALSE),"③@ ") & CHAR(13) & TEXT(VLOOKUP($B215,[4]평가!$B:$Z,MATCH(AF$2,[4]평가!$6:$6,0)-1,FALSE),"④@ ") & CHAR(13) & TEXT(VLOOKUP($B215,[5]평가!$B:$Z,MATCH(AF$2,[5]평가!$6:$6,0)-1,FALSE),"⑤@ "),"")
... A219: 217 | C219: =IFERROR(VLOOKUP($B219,대상!$B:$AC,MATCH(C$2,대상!$1:$1,0)-1,FALSE),"") | D219: =IFERROR(VLOOKUP($B219,대상!$B:$AC,MATCH(D$2,대상!$1:$1,0)-1,FALSE),"") | E219: =IFERROR(VLOOKUP($B219,대상!$B:$AC,MATCH(E$2,대상!$1:$1,0)-1,FALSE),"") | F219: =IFERROR(VLOOKUP($B219,대상!$B:$AC,MATCH(F$2,대상!$1:$1,0)-1,FALSE),"") | G219: =IFERROR(VLOOKUP($B219,대상!$B:$AC,MATCH(G$2,대상!$1:$1,0)-1,FALSE),"") | H219: =IFERROR(VLOOKUP($B219,[1]평가!$B:$Z,MATCH(LEFT(H$2,2),[1]평가!$7:$7,0)-1,FALSE),"") | I219: =IFERROR(VLOOKUP($B219,[1]평가!$B:$Z,MATCH(LEFT(I$2,2),[1]평가!$7:$7,0)-1,FALSE),"") | J219: =IFERROR(VLOOKUP($B219,[1]평가!$B:$Z,MATCH(LEFT(J$2,2),[1]평가!$7:$7,0)-1,FALSE),"") | K219: =IFERROR(VLOOKUP($B219,[2]평가!$B:$Z,MATCH(LEFT(K$2,2),[2]평가!$7:$7,0)-1,FALSE),"") | L219: =IFERROR(VLOOKUP($B219,[2]평가!$B:$Z,MATCH(LEFT(L$2,2),[2]평가!$7:$7,0)-1,FALSE),"") | M219: =IFERROR(VLOOKUP($B219,[2]평가!$B:$Z,MATCH(LEFT(M$2,2),[2]평가!$7:$7,0)-1,FALSE),"") | N219: =IFERROR(VLOOKUP($B219,[3]평가!$B:$Z,MATCH(LEFT(N$2,2),[3]평가!$7:$7,0)-1,FALSE),"") | O219: =IFERROR(VLOOKUP($B219,[3]평가!$B:$Z,MATCH(LEFT(O$2,2),[3]평가!$7:$7,0)-1,FALSE),"") | P219: =IFERROR(VLOOKUP($B219,[3]평가!$B:$Z,MATCH(LEFT(P$2,2),[3]평가!$7:$7,0)-1,FALSE),"") | Q219: =IFERROR(VLOOKUP($B219,[4]평가!$B:$Z,MATCH(LEFT(Q$2,2),[4]평가!$7:$7,0)-1,FALSE),"") | R219: =IFERROR(VLOOKUP($B219,[4]평가!$B:$Z,MATCH(LEFT(R$2,2),[4]평가!$7:$7,0)-1,FALSE),"") | S219: =IFERROR(VLOOKUP($B219,[4]평가!$B:$Z,MATCH(LEFT(S$2,2),[4]평가!$7:$7,0)-1,FALSE),"") | T219: =IFERROR(VLOOKUP($B219,[5]평가!$B:$Z,MATCH(LEFT(T$2,2),[5]평가!$7:$7,0)-1,FALSE),"") | U219: =IFERROR(VLOOKUP($B219,[5]평가!$B:$Z,MATCH(LEFT(U$2,2),[5]평가!$7:$7,0)-1,FALSE),"") | V219: =IFERROR(VLOOKUP($B219,[5]평가!$B:$Z,MATCH(LEFT(V$2,2),[5]평가!$7:$7,0)-1,FALSE),"") | W219: =IFERROR(VLOOKUP($B219,대상!$B:$AD,MATCH(W$2,대상!$1:$1,0)-1,FALSE),"") | X219: =IF(ISBLANK(B219),"",T$1-COUNTIF(H219:V219,"회피")) | Y219: =IF($T$1=X219,(SUM(I219,L219,O219,R219,U219)-MIN(I219,L219,O219,R219,U219)-MAX(I219,L219,O219,R219,U219))/($T$1-2),SUM(I219,L219,O219,R219,U219/X219)) -> #VALUE! | Z219: =IFERROR(VLOOKUP($B219,대상!$B:$AD,MATCH(Z$2,대상!$1:$1,0)-1,FALSE),0) -> 0 | AA219: =IFERROR(IF(W219="면제","100"+Z219,Y219+Z219),"") | AB219: =IF(OR(W219="면제",N(Y219)=0),"",IF(AA219<60,"과락","")) -> #VALUE! | AC219: =IF(N(AA219)=0,"",RANK(AA219,AA$3:AA$202)) | AD219: =IFERROR(TEXT(VLOOKUP($B219,[1]평가!$B:$Z,MATCH(AD$2,[1]평가!$6:$6,0)-1,FALSE),"①@ ") & CHAR(13) & TEXT(VLOOKUP($B219,[2]평가!$B:$Z,MATCH(AD$2,[2]평가!$6:$6,0)-1,FALSE),"②@ ") & CHAR(13) & TEXT(VLOOKUP($B219,[3]평가!$B:$Z,MATCH(AD$2,[3]평가!$6:$6,0)-1,FALSE),"③@ ") & CHAR(13) & TEXT(VLOOKUP($B219,[4]평가!$B:$Z,MATCH(AD$2,[4]평가!$6:$6,0)-1,FALSE),"④@ ") & CHAR(13) & TEXT(VLOOKUP($B219,[5]평가!$B:$Z,MATCH(AD$2,[5]평가!$6:$6,0)-1,FALSE),"⑤@ "),"") | AE219: =IFERROR(TEXT(VLOOKUP($B219,[1]평가!$B:$Z,MATCH(AE$2,[1]평가!$7:$7,0)-1,FALSE),"①@ ") & CHAR(13) & TEXT(VLOOKUP($B219,[2]평가!$B:$Z,MATCH(AE$2,[2]평가!$7:$7,0)-1,FALSE),"②@ ") & CHAR(13) & TEXT(VLOOKUP($B219,[3]평가!$B:$Z,MATCH(AE$2,[3]평가!$7:$7,0)-1,FALSE),"③@ ") & CHAR(13) & TEXT(VLOOKUP($B219,[4]평가!$B:$Z,MATCH(AE$2,[4]평가!$7:$7,0)-1,FALSE),"④@ ") & CHAR(13) & TEXT(VLOOKUP($B219,[5]평가!$B:$Z,MATCH(AE$2,[5]평가!$7:$7,0)-1,FALSE),"⑤@ "),"") | AF219: =IFERROR(TEXT(VLOOKUP($B219,[1]평가!$B:$Z,MATCH(AF$2,[1]평가!$6:$6,0)-1,FALSE),"①@ ") & CHAR(13) & TEXT(VLOOKUP($B219,[2]평가!$B:$Z,MATCH(AF$2,[2]평가!$6:$6,0)-1,FALSE),"②@ ") & CHAR(13) & TEXT(VLOOKUP($B219,[3]평가!$B:$Z,MATCH(AF$2,[3]평가!$6:$6,0)-1,FALSE),"③@ ") & CHAR(13) & TEXT(VLOOKUP($B219,[4]평가!$B:$Z,MATCH(AF$2,[4]평가!$6:$6,0)-1,FALSE),"④@ ") & CHAR(13) & TEXT(VLOOKUP($B219,[5]평가!$B:$Z,MATCH(AF$2,[5]평가!$6:$6,0)-1,FALSE),"⑤@ "),"")

Sheet 결과
A1: 과제번호 | B1: 순위 | C1: 대표자명 | D1: 과제번호 | E1: 과제명 | F1: 사전검토 | G1: 평가자수 | H1: 위원1 | I1: 위원2 | J1: 위원3 | K1: 위원4 | L1: 위원5 | M1: 평점 | N1: 가점 | O1: 점수 | P1: 과락
A2: 20423304 | B2: =IFERROR(VLOOKUP($A2,집계!$B:$AD,MATCH(B$1,집계!$2:$2,0)-1,FALSE),"") -> 138 | C2: =IFERROR(VLOOKUP($A2,집계!$B:$AD,MATCH(C$1,집계!$2:$2,0)-1,FALSE),"") -> 강희준 | D2: =IFERROR(VLOOKUP($A2,집계!$B:$AD,MATCH(D$1,집계!$2:$2,0)-1,FALSE),"") -> 20423304 | E2: =IFERROR(VLOOKUP($A2,집계!$B:$AD,MATCH(E$1,집계!$2:$2,0)-1,FALSE),"") -> [AI 스타일 복제] 기술이 적용된 영상 전문가를 위한 ‘IP자산화’ 및 편집 자동화 엔진 | F2: =IFERROR(VLOOKUP($A2,대상!$B:$AD,MATCH(F$1,대상!$1:$1,0)-1,FALSE),"") -> 0 | G2: =IFERROR(VLOOKUP($A2,집계!$B:$AD,MATCH(G$1,집계!$2:$2,0)-1,FALSE),"") -> 5 | H2: =IFERROR(VLOOKUP($A2,집계!$B:$AD,MATCH(H$1,집계!$2:$2,0)-1,FALSE),"") -> 67 | I2: =IFERROR(VLOOKUP($A2,집계!$B:$AD,MATCH(I$1,집계!$2:$2,0)-1,FALSE),"") -> 72 | J2: =IFERROR(VLOOKUP($A2,집계!$B:$AD,MATCH(J$1,집계!$2:$2,0)-1,FALSE),"") -> 69 | K2: =IFERROR(VLOOKUP($A2,집계!$B:$AD,MATCH(K$1,집계!$2:$2,0)-1,FALSE),"") -> 84 | L2: =IFERROR(VLOOKUP($A2,집계!$B:$AD,MATCH(L$1,집계!$2:$2,0)-1,FALSE),"") -> 71 | M2: =IFERROR(VLOOKUP($A2,집계!$B:$AD,MATCH(M$1,집계!$2:$2,0)-1,FALSE),"") -> 70.666667 | N2: =IFERROR(VLOOKUP($A2,집계!$B:$AD,MATCH(N$1,집계!$2:$2,0)-1,FALSE),"") -> 2 | ... P2: =IFERROR(VLOOKUP($A2,집계!$B:$AD,MATCH(P$1,집계!$2:$2,0)-1,FALSE),"")
A3: 20430731 | B3: =IFERROR(VLOOKUP($A3,집계!$B:$AD,MATCH(B$1,집계!$2:$2,0)-1,FALSE),"") -> 163 | C3: =IFERROR(VLOOKUP($A3,집계!$B:$AD,MATCH(C$1,집계!$2:$2,0)-1,FALSE),"") -> 강동호 | D3: =IFERROR(VLOOKUP($A3,집계!$B:$AD,MATCH(D$1,집계!$2:$2,0)-1,FALSE),"") -> 20430731 | E3: =IFERROR(VLOOKUP($A3,집계!$B:$AD,MATCH(E$1,집계!$2:$2,0)-1,FALSE),"") -> AI 지원 남성 외모 진단·개인화 관리 솔루션 | F3: =IFERROR(VLOOKUP($A3,대상!$B:$AD,MATCH(F$1,대상!$1:$1,0)-1,FALSE),"") -> 0 | G3: =IFERROR(VLOOKUP($A3,집계!$B:$AD,MATCH(G$1,집계!$2:$2,0)-1,FALSE),"") -> 5 | H3: =IFERROR(VLOOKUP($A3,집계!$B:$AD,MATCH(H$1,집계!$2:$2,0)-1,FALSE),"") -> 68 | I3: =IFERROR(VLOOKUP($A3,집계!$B:$AD,MATCH(I$1,집계!$2:$2,0)-1,FALSE),"") -> 65 | J3: =IFERROR(VLOOKUP($A3,집계!$B:$AD,MATCH(J$1,집계!$2:$2,0)-1,FALSE),"") -> 69 | K3: =IFERROR(VLOOKUP($A3,집계!$B:$AD,MATCH(K$1,집계!$2:$2,0)-1,FALSE),"") -> 85 | L3: =IFERROR(VLOOKUP($A3,집계!$B:$AD,MATCH(L$1,집계!$2:$2,0)-1,FALSE),"") -> 76 | M3: =IFERROR(VLOOKUP($A3,집계!$B:$AD,MATCH(M$1,집계!$2:$2,0)-1,FALSE),"") -> 71 | N3: =IFERROR(VLOOKUP($A3,집계!$B:$AD,MATCH(N$1,집계!$2:$2,0)-1,FALSE),"") -> 0 | ... P3: =IFERROR(VLOOKUP($A3,집계!$B:$AD,MATCH(P$1,집계!$2:$2,0)-1,FALSE),"")
A4: 20421554 | B4: =IFERROR(VLOOKUP($A4,집계!$B:$AD,MATCH(B$1,집계!$2:$2,0)-1,FALSE),"") -> 126 | C4: =IFERROR(VLOOKUP($A4,집계!$B:$AD,MATCH(C$1,집계!$2:$2,0)-1,FALSE),"") -> 이수미 | D4: =IFERROR(VLOOKUP($A4,집계!$B:$AD,MATCH(D$1,집계!$2:$2,0)-1,FALSE),"") -> 20421554 | E4: =IFERROR(VLOOKUP($A4,집계!$B:$AD,MATCH(E$1,집계!$2:$2,0)-1,FALSE),"") -> 굿거리, 자진모리, 휘모리 등 한국 장단을 반영한 MusicGen 파인튜닝 AI 기술이 적용된 글로벌 크리에이터 맞춤형 저작권 프리 국악 사운드 생성 플랫폼, K-Gugak Beat | F4: =IFERROR(VLOOKUP($A4,대상!$B:$AD,MATCH(F$1,대상!$1:$1,0)-1,FALSE),"") -> 0 | G4: =IFERROR(VLOOKUP($A4,집계!$B:$AD,MATCH(G$1,집계!$2:$2,0)-1,FALSE),"") -> 5 | H4: =IFERROR(VLOOKUP($A4,집계!$B:$AD,MATCH(H$1,집계!$2:$2,0)-1,FALSE),"") -> 75 | I4: =IFERROR(VLOOKUP($A4,집계!$B:$AD,MATCH(I$1,집계!$2:$2,0)-1,FALSE),"") -> 67 | J4: =IFERROR(VLOOKUP($A4,집계!$B:$AD,MATCH(J$1,집계!$2:$2,0)-1,FALSE),"") -> 69 | K4: =IFERROR(VLOOKUP($A4,집계!$B:$AD,MATCH(K$1,집계!$2:$2,0)-1,FALSE),"") -> 80 | L4: =IFERROR(VLOOKUP($A4,집계!$B:$AD,MATCH(L$1,집계!$2:$2,0)-1,FALSE),"") -> 76 | M4: =IFERROR(VLOOKUP($A4,집계!$B:$AD,MATCH(M$1,집계!$2:$2,0)-1,FALSE),"") -> 73.333333 | N4: =IFERROR(VLOOKUP($A4,집계!$B:$AD,MATCH(N$1,집계!$2:$2,0)-1,FALSE),"") -> 0 | ... P4: =IFERROR(VLOOKUP($A4,집계!$B:$AD,MATCH(P$1,집계!$2:$2,0)-1,FALSE),"")
A5: 20415305 | B5: =IFERROR(VLOOKUP($A5,집계!$B:$AD,MATCH(B$1,집계!$2:$2,0)-1,FALSE),"") -> 71 | C5: =IFERROR(VLOOKUP($A5,집계!$B:$AD,MATCH(C$1,집계!$2:$2,0)-1,FALSE),"") -> 노동관 | D5: =IFERROR(VLOOKUP($A5,집계!$B:$AD,MATCH(D$1,집계!$2:$2,0)-1,FALSE),"") -> 20415305 | E5: =IFERROR(VLOOKUP($A5,집계!$B:$AD,MATCH(E$1,집계!$2:$2,0)-1,FALSE),"") -> 사생활 침해 없는 비식별 스켈레톤 AI 기반, 시니어 낙상 사고 ‘골든타임’ 확보 솔루션 ‘안심ON’ | F5: =IFERROR(VLOOKUP($A5,대상!$B:$AD,MATCH(F$1,대상!$1:$1,0)-1,FALSE),"") -> 0 | G5: =IFERROR(VLOOKUP($A5,집계!$B:$AD,MATCH(G$1,집계!$2:$2,0)-1,FALSE),"") -> 5 | H5: =IFERROR(VLOOKUP($A5,집계!$B:$AD,MATCH(H$1,집계!$2:$2,0)-1,FALSE),"") -> 74 | I5: =IFERROR(VLOOKUP($A5,집계!$B:$AD,MATCH(I$1,집계!$2:$2,0)-1,FALSE),"") -> 75 | J5: =IFERROR(VLOOKUP($A5,집계!$B:$AD,MATCH(J$1,집계!$2:$2,0)-1,FALSE),"") -> 88 | K5: =IFERROR(VLOOKUP($A5,집계!$B:$AD,MATCH(K$1,집계!$2:$2,0)-1,FALSE),"") -> 80 | L5: =IFERROR(VLOOKUP($A5,집계!$B:$AD,MATCH(L$1,집계!$2:$2,0)-1,FALSE),"") -> 77 | M5: =IFERROR(VLOOKUP($A5,집계!$B:$AD,MATCH(M$1,집계!$2:$2,0)-1,FALSE),"") -> 77.333333 | N5: =IFERROR(VLOOKUP($A5,집계!$B:$AD,MATCH(N$1,집계!$2:$2,0)-1,FALSE),"") -> 0 | ... P5: =IFERROR(VLOOKUP($A5,집계!$B:$AD,MATCH(P$1,집계!$2:$2,0)-1,FALSE),"")
A6: 20429585 | B6: =IFERROR(VLOOKUP($A6,집계!$B:$AD,MATCH(B$1,집계!$2:$2,0)-1,FALSE),"") -> 71 | C6: =IFERROR(VLOOKUP($A6,집계!$B:$AD,MATCH(C$1,집계!$2:$2,0)-1,FALSE),"") -> 서윤기 | D6: =IFERROR(VLOOKUP($A6,집계!$B:$AD,MATCH(D$1,집계!$2:$2,0)-1,FALSE),"") -> 20429585 | E6: =IFERROR(VLOOKUP($A6,집계!$B:$AD,MATCH(E$1,집계!$2:$2,0)-1,FALSE),"") -> AI 기반 치매 조기 발견을 위한 인지 평가 및 의료 연계 헬스케어 플랫폼 | F6: =IFERROR(VLOOKUP($A6,대상!$B:$AD,MATCH(F$1,대상!$1:$1,0)-1,FALSE),"") -> 0 | G6: =IFERROR(VLOOKUP($A6,집계!$B:$AD,MATCH(G$1,집계!$2:$2,0)-1,FALSE),"") -> 5 | H6: =IFERROR(VLOOKUP($A6,집계!$B:$AD,MATCH(H$1,집계!$2:$2,0)-1,FALSE),"") -> 74 | I6: =IFERROR(VLOOKUP($A6,집계!$B:$AD,MATCH(I$1,집계!$2:$2,0)-1,FALSE),"") -> 67 | J6: =IFERROR(VLOOKUP($A6,집계!$B:$AD,MATCH(J$1,집계!$2:$2,0)-1,FALSE),"") -> 87 | K6: =IFERROR(VLOOKUP($A6,집계!$B:$AD,MATCH(K$1,집계!$2:$2,0)-1,FALSE),"") -> 84 | L6: =IFERROR(VLOOKUP($A6,집계!$B:$AD,MATCH(L$1,집계!$2:$2,0)-1,FALSE),"") -> 74 | M6: =IFERROR(VLOOKUP($A6,집계!$B:$AD,MATCH(M$1,집계!$2:$2,0)-1,FALSE),"") -> 77.333333 | N6: =IFERROR(VLOOKUP($A6,집계!$B:$AD,MATCH(N$1,집계!$2:$2,0)-1,FALSE),"") -> 0 | ... P6: =IFERROR(VLOOKUP($A6,집계!$B:$AD,MATCH(P$1,집계!$2:$2,0)-1,FALSE),"")
A7: 20431797 | B7: =IFERROR(VLOOKUP($A7,집계!$B:$AD,MATCH(B$1,집계!$2:$2,0)-1,FALSE),"") -> 71 | C7: =IFERROR(VLOOKUP($A7,집계!$B:$AD,MATCH(C$1,집계!$2:$2,0)-1,FALSE),"") -> 김재현 | D7: =IFERROR(VLOOKUP($A7,집계!$B:$AD,MATCH(D$1,집계!$2:$2,0)-1,FALSE),"") -> 20431797 | E7: =IFERROR(VLOOKUP($A7,집계!$B:$AD,MATCH(E$1,집계!$2:$2,0)-1,FALSE),"") -> 지워지지 않는 옷의 지문: 정품 인증 및 이력 관리 플랫폼 | F7: =IFERROR(VLOOKUP($A7,대상!$B:$AD,MATCH(F$1,대상!$1:$1,0)-1,FALSE),"") -> 0 | G7: =IFERROR(VLOOKUP($A7,집계!$B:$AD,MATCH(G$1,집계!$2:$2,0)-1,FALSE),"") -> 5 | H7: =IFERROR(VLOOKUP($A7,집계!$B:$AD,MATCH(H$1,집계!$2:$2,0)-1,FALSE),"") -> 73 | I7: =IFERROR(VLOOKUP($A7,집계!$B:$AD,MATCH(I$1,집계!$2:$2,0)-1,FALSE),"") -> 60 | J7: =IFERROR(VLOOKUP($A7,집계!$B:$AD,MATCH(J$1,집계!$2:$2,0)-1,FALSE),"") -> 85 | K7: =IFERROR(VLOOKUP($A7,집계!$B:$AD,MATCH(K$1,집계!$2:$2,0)-1,FALSE),"") -> 85 | L7: =IFERROR(VLOOKUP($A7,집계!$B:$AD,MATCH(L$1,집계!$2:$2,0)-1,FALSE),"") -> 74 | M7: =IFERROR(VLOOKUP($A7,집계!$B:$AD,MATCH(M$1,집계!$2:$2,0)-1,FALSE),"") -> 77.333333 | N7: =IFERROR(VLOOKUP($A7,집계!$B:$AD,MATCH(N$1,집계!$2:$2,0)-1,FALSE),"") -> 0 | ... P7: =IFERROR(VLOOKUP($A7,집계!$B:$AD,MATCH(P$1,집계!$2:$2,0)-1,FALSE),"")
A8: 20429927 | B8: =IFERROR(VLOOKUP($A8,집계!$B:$AD,MATCH(B$1,집계!$2:$2,0)-1,FALSE),"") -> 177 | C8: =IFERROR(VLOOKUP($A8,집계!$B:$AD,MATCH(C$1,집계!$2:$2,0)-1,FALSE),"") -> 최영일 | D8: =IFERROR(VLOOKUP($A8,집계!$B:$AD,MATCH(D$1,집계!$2:$2,0)-1,FALSE),"") -> 20429927 | E8: =IFERROR(VLOOKUP($A8,집계!$B:$AD,MATCH(E$1,집계!$2:$2,0)-1,FALSE),"") -> 개인 투자자를 위한 실시간 기업 성장성 평가 및 데이터 시각화 솔루션: 스탁랭킹 | F8: =IFERROR(VLOOKUP($A8,대상!$B:$AD,MATCH(F$1,대상!$1:$1,0)-1,FALSE),"") -> 0 | G8: =IFERROR(VLOOKUP($A8,집계!$B:$AD,MATCH(G$1,집계!$2:$2,0)-1,FALSE),"") -> 5 | H8: =IFERROR(VLOOKUP($A8,집계!$B:$AD,MATCH(H$1,집계!$2:$2,0)-1,FALSE),"") -> 69 | I8: =IFERROR(VLOOKUP($A8,집계!$B:$AD,MATCH(I$1,집계!$2:$2,0)-1,FALSE),"") -> 61 | J8: =IFERROR(VLOOKUP($A8,집계!$B:$AD,MATCH(J$1,집계!$2:$2,0)-1,FALSE),"") -> 74 | K8: =IFERROR(VLOOKUP($A8,집계!$B:$AD,MATCH(K$1,집계!$2:$2,0)-1,FALSE),"") -> 72 | L8: =IFERROR(VLOOKUP($A8,집계!$B:$AD,MATCH(L$1,집계!$2:$2,0)-1,FALSE),"") -> 68 | M8: =IFERROR(VLOOKUP($A8,집계!$B:$AD,MATCH(M$1,집계!$2:$2,0)-1,FALSE),"") -> 69.666667 | N8: =IFERROR(VLOOKUP($A8,집계!$B:$AD,MATCH(N$1,집계!$2:$2,0)-1,FALSE),"") -> 0 | ... P8: =IFERROR(VLOOKUP($A8,집계!$B:$AD,MATCH(P$1,집계!$2:$2,0)-1,FALSE),"")
A9: 20424365 | B9: =IFERROR(VLOOKUP($A9,집계!$B:$AD,MATCH(B$1,집계!$2:$2,0)-1,FALSE),"") -> 138 | C9: =IFERROR(VLOOKUP($A9,집계!$B:$AD,MATCH(C$1,집계!$2:$2,0)-1,FALSE),"") -> 김동영 | D9: =IFERROR(VLOOKUP($A9,집계!$B:$AD,MATCH(D$1,집계!$2:$2,0)-1,FALSE),"") -> 20424365 | E9: =IFERROR(VLOOKUP($A9,집계!$B:$AD,MATCH(E$1,집계!$2:$2,0)-1,FALSE),"") -> 실시간 면접관 리스크 차단 및 면접자 평가 AI 인터뷰 코파일럿, Castee | F9: =IFERROR(VLOOKUP($A9,대상!$B:$AD,MATCH(F$1,대상!$1:$1,0)-1,FALSE),"") -> 0 | G9: =IFERROR(VLOOKUP($A9,집계!$B:$AD,MATCH(G$1,집계!$2:$2,0)-1,FALSE),"") -> 5 | H9: =IFERROR(VLOOKUP($A9,집계!$B:$AD,MATCH(H$1,집계!$2:$2,0)-1,FALSE),"") -> 73 | I9: =IFERROR(VLOOKUP($A9,집계!$B:$AD,MATCH(I$1,집계!$2:$2,0)-1,FALSE),"") -> 63 | J9: =IFERROR(VLOOKUP($A9,집계!$B:$AD,MATCH(J$1,집계!$2:$2,0)-1,FALSE),"") -> 84 | K9: =IFERROR(VLOOKUP($A9,집계!$B:$AD,MATCH(K$1,집계!$2:$2,0)-1,FALSE),"") -> 76 | L9: =IFERROR(VLOOKUP($A9,집계!$B:$AD,MATCH(L$1,집계!$2:$2,0)-1,FALSE),"") -> 69 | M9: =IFERROR(VLOOKUP($A9,집계!$B:$AD,MATCH(M$1,집계!$2:$2,0)-1,FALSE),"") -> 72.666667 | N9: =IFERROR(VLOOKUP($A9,집계!$B:$AD,MATCH(N$1,집계!$2:$2,0)-1,FALSE),"") -> 0 | ... P9: =IFERROR(VLOOKUP($A9,집계!$B:$AD,MATCH(P$1,집계!$2:$2,0)-1,FALSE),"")
A10: 20425958 | B10: =IFERROR(VLOOKUP($A10,집계!$B:$AD,MATCH(B$1,집계!$2:$2,0)-1,FALSE),"") -> 101 | C10: =IFERROR(VLOOKUP($A10,집계!$B:$AD,MATCH(C$1,집계!$2:$2,0)-1,FALSE),"") -> 정아휘 | D10: =IFERROR(VLOOKUP($A10,집계!$B:$AD,MATCH(D$1,집계!$2:$2,0)-1,FALSE),"") -> 20425958 | E10: =IFERROR(VLOOKUP($A10,집계!$B:$AD,MATCH(E$1,집계!$2:$2,0)-1,FALSE),"") -> 생성형 AI(LLM·TTS) 기술이 적용된, 상황별 한국어 롤플레잉 및 로컬 상권 연계 보상을 제공하는 관광·에듀테크 플랫폼 | F10: =IFERROR(VLOOKUP($A10,대상!$B:$AD,MATCH(F$1,대상!$1:$1,0)-1,FALSE),"") -> 0 | G10: =IFERROR(VLOOKUP($A10,집계!$B:$AD,MATCH(G$1,집계!$2:$2,0)-1,FALSE),"") -> 5 | H10: =IFERROR(VLOOKUP($A10,집계!$B:$AD,MATCH(H$1,집계!$2:$2,0)-1,FALSE),"") -> 73 | I10: =IFERROR(VLOOKUP($A10,집계!$B:$AD,MATCH(I$1,집계!$2:$2,0)-1,FALSE),"") -> 61 | J10: =IFERROR(VLOOKUP($A10,집계!$B:$AD,MATCH(J$1,집계!$2:$2,0)-1,FALSE),"") -> 79 | K10: =IFERROR(VLOOKUP($A10,집계!$B:$AD,MATCH(K$1,집계!$2:$2,0)-1,FALSE),"") -> 79 | L10: =IFERROR(VLOOKUP($A10,집계!$B:$AD,MATCH(L$1,집계!$2:$2,0)-1,FALSE),"") -> 74 | M10: =IFERROR(VLOOKUP($A10,집계!$B:$AD,MATCH(M$1,집계!$2:$2,0)-1,FALSE),"") -> 75.333333 | N10: =IFERROR(VLOOKUP($A10,집계!$B:$AD,MATCH(N$1,집계!$2:$2,0)-1,FALSE),"") -> 0 | ... P10: =IFERROR(VLOOKUP($A10,집계!$B:$AD,MATCH(P$1,집계!$2:$2,0)-1,FALSE),"")
A11: 20416478 | B11: =IFERROR(VLOOKUP($A11,집계!$B:$AD,MATCH(B$1,집계!$2:$2,0)-1,FALSE),"") -> 92 | C11: =IFERROR(VLOOKUP($A11,집계!$B:$AD,MATCH(C$1,집계!$2:$2,0)-1,FALSE),"") -> 조경식 | D11: =IFERROR(VLOOKUP($A11,집계!$B:$AD,MATCH(D$1,집계!$2:$2,0)-1,FALSE),"") -> 20416478 | E11: =IFERROR(VLOOKUP($A11,집계!$B:$AD,MATCH(E$1,집계!$2:$2,0)-1,FALSE),"") -> 고비용 PT의 한계를 극복하는 온디바이스 초개인화 AI 실시간 개인 맞춤형 코칭 앱 및 스마트짐 B2B 연계 플랫폼, 'Lockin' | F11: =IFERROR(VLOOKUP($A11,대상!$B:$AD,MATCH(F$1,대상!$1:$1,0)-1,FALSE),"") -> 0 | G11: =IFERROR(VLOOKUP($A11,집계!$B:$AD,MATCH(G$1,집계!$2:$2,0)-1,FALSE),"") -> 5 | H11: =IFERROR(VLOOKUP($A11,집계!$B:$AD,MATCH(H$1,집계!$2:$2,0)-1,FALSE),"") -> 73 | I11: =IFERROR(VLOOKUP($A11,집계!$B:$AD,MATCH(I$1,집계!$2:$2,0)-1,FALSE),"") -> 64 | J11: =IFERROR(VLOOKUP($A11,집계!$B:$AD,MATCH(J$1,집계!$2:$2,0)-1,FALSE),"") -> 77 | K11: =IFERROR(VLOOKUP($A11,집계!$B:$AD,MATCH(K$1,집계!$2:$2,0)-1,FALSE),"") -> 77 | L11: =IFERROR(VLOOKUP($A11,집계!$B:$AD,MATCH(L$1,집계!$2:$2,0)-1,FALSE),"") -> 71 | M11: =IFERROR(VLOOKUP($A11,집계!$B:$AD,MATCH(M$1,집계!$2:$2,0)-1,FALSE),"") -> 73.666667 | N11: =IFERROR(VLOOKUP($A11,집계!$B:$AD,MATCH(N$1,집계!$2:$2,0)-1,FALSE),"") -> 2 | ... P11: =IFERROR(VLOOKUP($A11,집계!$B:$AD,MATCH(P$1,집계!$2:$2,0)-1,FALSE),"")
A12: 20426844 | B12: =IFERROR(VLOOKUP($A12,집계!$B:$AD,MATCH(B$1,집계!$2:$2,0)-1,FALSE),"") -> 132 | C12: =IFERROR(VLOOKUP($A12,집계!$B:$AD,MATCH(C$1,집계!$2:$2,0)-1,FALSE),"") -> 하중한 | D12: =IFERROR(VLOOKUP($A12,집계!$B:$AD,MATCH(D$1,집계!$2:$2,0)-1,FALSE),"") -> 20426844 | E12: =IFERROR(VLOOKUP($A12,집계!$B:$AD,MATCH(E$1,집계!$2:$2,0)-1,FALSE),"") -> AI를 활용한 드론산업 매칭 마켓플레이스 플랫폼 | F12: =IFERROR(VLOOKUP($A12,대상!$B:$AD,MATCH(F$1,대상!$1:$1,0)-1,FALSE),"") -> 0 | G12: =IFERROR(VLOOKUP($A12,집계!$B:$AD,MATCH(G$1,집계!$2:$2,0)-1,FALSE),"") -> 5 | H12: =IFERROR(VLOOKUP($A12,집계!$B:$AD,MATCH(H$1,집계!$2:$2,0)-1,FALSE),"") -> 73 | I12: =IFERROR(VLOOKUP($A12,집계!$B:$AD,MATCH(I$1,집계!$2:$2,0)-1,FALSE),"") -> 67 | J12: =IFERROR(VLOOKUP($A12,집계!$B:$AD,MATCH(J$1,집계!$2:$2,0)-1,FALSE),"") -> 78 | K12: =IFERROR(VLOOKUP($A12,집계!$B:$AD,MATCH(K$1,집계!$2:$2,0)-1,FALSE),"") -> 77 | L12: =IFERROR(VLOOKUP($A12,집계!$B:$AD,MATCH(L$1,집계!$2:$2,0)-1,FALSE),"") -> 69 | M12: =IFERROR(VLOOKUP($A12,집계!$B:$AD,MATCH(M$1,집계!$2:$2,0)-1,FALSE),"") -> 73 | N12: =IFERROR(VLOOKUP($A12,집계!$B:$AD,MATCH(N$1,집계!$2:$2,0)-1,FALSE),"") -> 0 | ... P12: =IFERROR(VLOOKUP($A12,집계!$B:$AD,MATCH(P$1,집계!$2:$2,0)-1,FALSE),"")
A13: 20419052 | B13: =IFERROR(VLOOKUP($A13,집계!$B:$AD,MATCH(B$1,집계!$2:$2,0)-1,FALSE),"") -> 92 | C13: =IFERROR(VLOOKUP($A13,집계!$B:$AD,MATCH(C$1,집계!$2:$2,0)-1,FALSE),"") -> 박주명 | D13: =IFERROR(VLOOKUP($A13,집계!$B:$AD,MATCH(D$1,집계!$2:$2,0)-1,FALSE),"") -> 20419052 | E13: =IFERROR(VLOOKUP($A13,집계!$B:$AD,MATCH(E$1,집계!$2:$2,0)-1,FALSE),"") -> FINLY : 금융상담 서류접수·보완요청·사전심사 보조 자동화 AI /SaaS 솔루션 | F13: =IFERROR(VLOOKUP($A13,대상!$B:$AD,MATCH(F$1,대상!$1:$1,0)-1,FALSE),"") -> 0 | G13: =IFERROR(VLOOKUP($A13,집계!$B:$AD,MATCH(G$1,집계!$2:$2,0)-1,FALSE),"") -> 5 | H13: =IFERROR(VLOOKUP($A13,집계!$B:$AD,MATCH(H$1,집계!$2:$2,0)-1,FALSE),"") -> 73 | I13: =IFERROR(VLOOKUP($A13,집계!$B:$AD,MATCH(I$1,집계!$2:$2,0)-1,FALSE),"") -> 64 | J13: =IFERROR(VLOOKUP($A13,집계!$B:$AD,MATCH(J$1,집계!$2:$2,0)-1,FALSE),"") -> 77 | K13: =IFERROR(VLOOKUP($A13,집계!$B:$AD,MATCH(K$1,집계!$2:$2,0)-1,FALSE),"") -> 79 | L13: =IFERROR(VLOOKUP($A13,집계!$B:$AD,MATCH(L$1,집계!$2:$2,0)-1,FALSE),"") -> 71 | M13: =IFERROR(VLOOKUP($A13,집계!$B:$AD,MATCH(M$1,집계!$2:$2,0)-1,FALSE),"") -> 73.666667 | N13: =IFERROR(VLOOKUP($A13,집계!$B:$AD,MATCH(N$1,집계!$2:$2,0)-1,FALSE),"") -> 2 | ... P13: =IFERROR(VLOOKUP($A13,집계!$B:$AD,MATCH(P$1,집계!$2:$2,0)-1,FALSE),"")
... A202: 20416852 | B202: =IFERROR(VLOOKUP($A202,집계!$B:$AD,MATCH(B$1,집계!$2:$2,0)-1,FALSE),"") -> 138 | C202: =IFERROR(VLOOKUP($A202,집계!$B:$AD,MATCH(C$1,집계!$2:$2,0)-1,FALSE),"") -> 주진수 | D202: =IFERROR(VLOOKUP($A202,집계!$B:$AD,MATCH(D$1,집계!$2:$2,0)-1,FALSE),"") -> 20416852 | E202: =IFERROR(VLOOKUP($A202,집계!$B:$AD,MATCH(E$1,집계!$2:$2,0)-1,FALSE),"") -> 신규 아날로그 필름 제조 및 AI 플랫폼 구축 사업 | F202: =IFERROR(VLOOKUP($A202,대상!$B:$AD,MATCH(F$1,대상!$1:$1,0)-1,FALSE),"") -> 0 | G202: =IFERROR(VLOOKUP($A202,집계!$B:$AD,MATCH(G$1,집계!$2:$2,0)-1,FALSE),"") -> 5 | H202: =IFERROR(VLOOKUP($A202,집계!$B:$AD,MATCH(H$1,집계!$2:$2,0)-1,FALSE),"") -> 73 | I202: =IFERROR(VLOOKUP($A202,집계!$B:$AD,MATCH(I$1,집계!$2:$2,0)-1,FALSE),"") -> 68 | J202: =IFERROR(VLOOKUP($A202,집계!$B:$AD,MATCH(J$1,집계!$2:$2,0)-1,FALSE),"") -> 84 | K202: =IFERROR(VLOOKUP($A202,집계!$B:$AD,MATCH(K$1,집계!$2:$2,0)-1,FALSE),"") -> 66 | L202: =IFERROR(VLOOKUP($A202,집계!$B:$AD,MATCH(L$1,집계!$2:$2,0)-1,FALSE),"") -> 77 | M202: =IFERROR(VLOOKUP($A202,집계!$B:$AD,MATCH(M$1,집계!$2:$2,0)-1,FALSE),"") -> 72.666667 | N202: =IFERROR(VLOOKUP($A202,집계!$B:$AD,MATCH(N$1,집계!$2:$2,0)-1,FALSE),"") -> 0 | ... P202: =IFERROR(VLOOKUP($A202,집계!$B:$AD,MATCH(P$1,집계!$2:$2,0)-1,FALSE),"")
B203: =IFERROR(VLOOKUP($A203,집계!$B:$AD,MATCH(B$1,집계!$2:$2,0)-1,FALSE),"") | C203: =IFERROR(VLOOKUP($A203,집계!$B:$AD,MATCH(C$1,집계!$2:$2,0)-1,FALSE),"") | D203: =IFERROR(VLOOKUP($A203,집계!$B:$AD,MATCH(D$1,집계!$2:$2,0)-1,FALSE),"") | E203: =IFERROR(VLOOKUP($A203,집계!$B:$AD,MATCH(E$1,집계!$2:$2,0)-1,FALSE),"") | F203: =IFERROR(VLOOKUP($A203,대상!$B:$AD,MATCH(F$1,대상!$1:$1,0)-1,FALSE),"") | G203: =IFERROR(VLOOKUP($A203,집계!$B:$AD,MATCH(G$1,집계!$2:$2,0)-1,FALSE),"") | H203: =IFERROR(VLOOKUP($A203,집계!$B:$AD,MATCH(H$1,집계!$2:$2,0)-1,FALSE),"") | I203: =IFERROR(VLOOKUP($A203,집계!$B:$AD,MATCH(I$1,집계!$2:$2,0)-1,FALSE),"") | J203: =IFERROR(VLOOKUP($A203,집계!$B:$AD,MATCH(J$1,집계!$2:$2,0)-1,FALSE),"") | K203: =IFERROR(VLOOKUP($A203,집계!$B:$AD,MATCH(K$1,집계!$2:$2,0)-1,FALSE),"") | L203: =IFERROR(VLOOKUP($A203,집계!$B:$AD,MATCH(L$1,집계!$2:$2,0)-1,FALSE),"") | M203: =IFERROR(VLOOKUP($A203,집계!$B:$AD,MATCH(M$1,집계!$2:$2,0)-1,FALSE),"") | N203: =IFERROR(VLOOKUP($A203,집계!$B:$AD,MATCH(N$1,집계!$2:$2,0)-1,FALSE),"") | ... P203: =IFERROR(VLOOKUP($A203,집계!$B:$AD,MATCH(P$1,집계!$2:$2,0)-1,FALSE),"")
B204: =IFERROR(VLOOKUP($A204,집계!$B:$AD,MATCH(B$1,집계!$2:$2,0)-1,FALSE),"") | C204: =IFERROR(VLOOKUP($A204,집계!$B:$AD,MATCH(C$1,집계!$2:$2,0)-1,FALSE),"") | D204: =IFERROR(VLOOKUP($A204,집계!$B:$AD,MATCH(D$1,집계!$2:$2,0)-1,FALSE),"") | E204: =IFERROR(VLOOKUP($A204,집계!$B:$AD,MATCH(E$1,집계!$2:$2,0)-1,FALSE),"") | F204: =IFERROR(VLOOKUP($A204,대상!$B:$AD,MATCH(F$1,대상!$1:$1,0)-1,FALSE),"") | G204: =IFERROR(VLOOKUP($A204,집계!$B:$AD,MATCH(G$1,집계!$2:$2,0)-1,FALSE),"") | H204: =IFERROR(VLOOKUP($A204,집계!$B:$AD,MATCH(H$1,집계!$2:$2,0)-1,FALSE),"") | I204: =IFERROR(VLOOKUP($A204,집계!$B:$AD,MATCH(I$1,집계!$2:$2,0)-1,FALSE),"") | J204: =IFERROR(VLOOKUP($A204,집계!$B:$AD,MATCH(J$1,집계!$2:$2,0)-1,FALSE),"") | K204: =IFERROR(VLOOKUP($A204,집계!$B:$AD,MATCH(K$1,집계!$2:$2,0)-1,FALSE),"") | L204: =IFERROR(VLOOKUP($A204,집계!$B:$AD,MATCH(L$1,집계!$2:$2,0)-1,FALSE),"") | M204: =IFERROR(VLOOKUP($A204,집계!$B:$AD,MATCH(M$1,집계!$2:$2,0)-1,FALSE),"") | N204: =IFERROR(VLOOKUP($A204,집계!$B:$AD,MATCH(N$1,집계!$2:$2,0)-1,FALSE),"") | ... P204: =IFERROR(VLOOKUP($A204,집계!$B:$AD,MATCH(P$1,집계!$2:$2,0)-1,FALSE),"")
B205: =IFERROR(VLOOKUP($A205,집계!$B:$AD,MATCH(B$1,집계!$2:$2,0)-1,FALSE),"") | C205: =IFERROR(VLOOKUP($A205,집계!$B:$AD,MATCH(C$1,집계!$2:$2,0)-1,FALSE),"") | D205: =IFERROR(VLOOKUP($A205,집계!$B:$AD,MATCH(D$1,집계!$2:$2,0)-1,FALSE),"") | E205: =IFERROR(VLOOKUP($A205,집계!$B:$AD,MATCH(E$1,집계!$2:$2,0)-1,FALSE),"") | F205: =IFERROR(VLOOKUP($A205,대상!$B:$AD,MATCH(F$1,대상!$1:$1,0)-1,FALSE),"") | G205: =IFERROR(VLOOKUP($A205,집계!$B:$AD,MATCH(G$1,집계!$2:$2,0)-1,FALSE),"") | H205: =IFERROR(VLOOKUP($A205,집계!$B:$AD,MATCH(H$1,집계!$2:$2,0)-1,FALSE),"") | I205: =IFERROR(VLOOKUP($A205,집계!$B:$AD,MATCH(I$1,집계!$2:$2,0)-1,FALSE),"") | J205: =IFERROR(VLOOKUP($A205,집계!$B:$AD,MATCH(J$1,집계!$2:$2,0)-1,FALSE),"") | K205: =IFERROR(VLOOKUP($A205,집계!$B:$AD,MATCH(K$1,집계!$2:$2,0)-1,FALSE),"") | L205: =IFERROR(VLOOKUP($A205,집계!$B:$AD,MATCH(L$1,집계!$2:$2,0)-1,FALSE),"") | M205: =IFERROR(VLOOKUP($A205,집계!$B:$AD,MATCH(M$1,집계!$2:$2,0)-1,FALSE),"") | N205: =IFERROR(VLOOKUP($A205,집계!$B:$AD,MATCH(N$1,집계!$2:$2,0)-1,FALSE),"") | ... P205: =IFERROR(VLOOKUP($A205,집계!$B:$AD,MATCH(P$1,집계!$2:$2,0)-1,FALSE),"")
B206: =IFERROR(VLOOKUP($A206,집계!$B:$AD,MATCH(B$1,집계!$2:$2,0)-1,FALSE),"") | C206: =IFERROR(VLOOKUP($A206,집계!$B:$AD,MATCH(C$1,집계!$2:$2,0)-1,FALSE),"") | D206: =IFERROR(VLOOKUP($A206,집계!$B:$AD,MATCH(D$1,집계!$2:$2,0)-1,FALSE),"") | E206: =IFERROR(VLOOKUP($A206,집계!$B:$AD,MATCH(E$1,집계!$2:$2,0)-1,FALSE),"") | F206: =IFERROR(VLOOKUP($A206,대상!$B:$AD,MATCH(F$1,대상!$1:$1,0)-1,FALSE),"") | G206: =IFERROR(VLOOKUP($A206,집계!$B:$AD,MATCH(G$1,집계!$2:$2,0)-1,FALSE),"") | H206: =IFERROR(VLOOKUP($A206,집계!$B:$AD,MATCH(H$1,집계!$2:$2,0)-1,FALSE),"") | I206: =IFERROR(VLOOKUP($A206,집계!$B:$AD,MATCH(I$1,집계!$2:$2,0)-1,FALSE),"") | J206: =IFERROR(VLOOKUP($A206,집계!$B:$AD,MATCH(J$1,집계!$2:$2,0)-1,FALSE),"") | K206: =IFERROR(VLOOKUP($A206,집계!$B:$AD,MATCH(K$1,집계!$2:$2,0)-1,FALSE),"") | L206: =IFERROR(VLOOKUP($A206,집계!$B:$AD,MATCH(L$1,집계!$2:$2,0)-1,FALSE),"") | M206: =IFERROR(VLOOKUP($A206,집계!$B:$AD,MATCH(M$1,집계!$2:$2,0)-1,FALSE),"") | N206: =IFERROR(VLOOKUP($A206,집계!$B:$AD,MATCH(N$1,집계!$2:$2,0)-1,FALSE),"") | ... P206: =IFERROR(VLOOKUP($A206,집계!$B:$AD,MATCH(P$1,집계!$2:$2,0)-1,FALSE),"")
B207: =IFERROR(VLOOKUP($A207,집계!$B:$AD,MATCH(B$1,집계!$2:$2,0)-1,FALSE),"") | C207: =IFERROR(VLOOKUP($A207,집계!$B:$AD,MATCH(C$1,집계!$2:$2,0)-1,FALSE),"") | D207: =IFERROR(VLOOKUP($A207,집계!$B:$AD,MATCH(D$1,집계!$2:$2,0)-1,FALSE),"") | E207: =IFERROR(VLOOKUP($A207,집계!$B:$AD,MATCH(E$1,집계!$2:$2,0)-1,FALSE),"") | F207: =IFERROR(VLOOKUP($A207,대상!$B:$AD,MATCH(F$1,대상!$1:$1,0)-1,FALSE),"") | G207: =IFERROR(VLOOKUP($A207,집계!$B:$AD,MATCH(G$1,집계!$2:$2,0)-1,FALSE),"") | H207: =IFERROR(VLOOKUP($A207,집계!$B:$AD,MATCH(H$1,집계!$2:$2,0)-1,FALSE),"") | I207: =IFERROR(VLOOKUP($A207,집계!$B:$AD,MATCH(I$1,집계!$2:$2,0)-1,FALSE),"") | J207: =IFERROR(VLOOKUP($A207,집계!$B:$AD,MATCH(J$1,집계!$2:$2,0)-1,FALSE),"") | K207: =IFERROR(VLOOKUP($A207,집계!$B:$AD,MATCH(K$1,집계!$2:$2,0)-1,FALSE),"") | L207: =IFERROR(VLOOKUP($A207,집계!$B:$AD,MATCH(L$1,집계!$2:$2,0)-1,FALSE),"") | M207: =IFERROR(VLOOKUP($A207,집계!$B:$AD,MATCH(M$1,집계!$2:$2,0)-1,FALSE),"") | N207: =IFERROR(VLOOKUP($A207,집계!$B:$AD,MATCH(N$1,집계!$2:$2,0)-1,FALSE),"") | ... P207: =IFERROR(VLOOKUP($A207,집계!$B:$AD,MATCH(P$1,집계!$2:$2,0)-1,FALSE),"")
B208: =IFERROR(VLOOKUP($A208,집계!$B:$AD,MATCH(B$1,집계!$2:$2,0)-1,FALSE),"") | C208: =IFERROR(VLOOKUP($A208,집계!$B:$AD,MATCH(C$1,집계!$2:$2,0)-1,FALSE),"") | D208: =IFERROR(VLOOKUP($A208,집계!$B:$AD,MATCH(D$1,집계!$2:$2,0)-1,FALSE),"") | E208: =IFERROR(VLOOKUP($A208,집계!$B:$AD,MATCH(E$1,집계!$2:$2,0)-1,FALSE),"") | F208: =IFERROR(VLOOKUP($A208,대상!$B:$AD,MATCH(F$1,대상!$1:$1,0)-1,FALSE),"") | G208: =IFERROR(VLOOKUP($A208,집계!$B:$AD,MATCH(G$1,집계!$2:$2,0)-1,FALSE),"") | H208: =IFERROR(VLOOKUP($A208,집계!$B:$AD,MATCH(H$1,집계!$2:$2,0)-1,FALSE),"") | I208: =IFERROR(VLOOKUP($A208,집계!$B:$AD,MATCH(I$1,집계!$2:$2,0)-1,FALSE),"") | J208: =IFERROR(VLOOKUP($A208,집계!$B:$AD,MATCH(J$1,집계!$2:$2,0)-1,FALSE),"") | K208: =IFERROR(VLOOKUP($A208,집계!$B:$AD,MATCH(K$1,집계!$2:$2,0)-1,FALSE),"") | L208: =IFERROR(VLOOKUP($A208,집계!$B:$AD,MATCH(L$1,집계!$2:$2,0)-1,FALSE),"") | M208: =IFERROR(VLOOKUP($A208,집계!$B:$AD,MATCH(M$1,집계!$2:$2,0)-1,FALSE),"") | N208: =IFERROR(VLOOKUP($A208,집계!$B:$AD,MATCH(N$1,집계!$2:$2,0)-1,FALSE),"") | ... P208: =IFERROR(VLOOKUP($A208,집계!$B:$AD,MATCH(P$1,집계!$2:$2,0)-1,FALSE),"")
B209: =IFERROR(VLOOKUP($A209,집계!$B:$AD,MATCH(B$1,집계!$2:$2,0)-1,FALSE),"") | C209: =IFERROR(VLOOKUP($A209,집계!$B:$AD,MATCH(C$1,집계!$2:$2,0)-1,FALSE),"") | D209: =IFERROR(VLOOKUP($A209,집계!$B:$AD,MATCH(D$1,집계!$2:$2,0)-1,FALSE),"") | E209: =IFERROR(VLOOKUP($A209,집계!$B:$AD,MATCH(E$1,집계!$2:$2,0)-1,FALSE),"") | F209: =IFERROR(VLOOKUP($A209,대상!$B:$AD,MATCH(F$1,대상!$1:$1,0)-1,FALSE),"") | G209: =IFERROR(VLOOKUP($A209,집계!$B:$AD,MATCH(G$1,집계!$2:$2,0)-1,FALSE),"") | H209: =IFERROR(VLOOKUP($A209,집계!$B:$AD,MATCH(H$1,집계!$2:$2,0)-1,FALSE),"") | I209: =IFERROR(VLOOKUP($A209,집계!$B:$AD,MATCH(I$1,집계!$2:$2,0)-1,FALSE),"") | J209: =IFERROR(VLOOKUP($A209,집계!$B:$AD,MATCH(J$1,집계!$2:$2,0)-1,FALSE),"") | K209: =IFERROR(VLOOKUP($A209,집계!$B:$AD,MATCH(K$1,집계!$2:$2,0)-1,FALSE),"") | L209: =IFERROR(VLOOKUP($A209,집계!$B:$AD,MATCH(L$1,집계!$2:$2,0)-1,FALSE),"") | M209: =IFERROR(VLOOKUP($A209,집계!$B:$AD,MATCH(M$1,집계!$2:$2,0)-1,FALSE),"") | N209: =IFERROR(VLOOKUP($A209,집계!$B:$AD,MATCH(N$1,집계!$2:$2,0)-1,FALSE),"") | ... P209: =IFERROR(VLOOKUP($A209,집계!$B:$AD,MATCH(P$1,집계!$2:$2,0)-1,FALSE),"")
B210: =IFERROR(VLOOKUP($A210,집계!$B:$AD,MATCH(B$1,집계!$2:$2,0)-1,FALSE),"") | C210: =IFERROR(VLOOKUP($A210,집계!$B:$AD,MATCH(C$1,집계!$2:$2,0)-1,FALSE),"") | D210: =IFERROR(VLOOKUP($A210,집계!$B:$AD,MATCH(D$1,집계!$2:$2,0)-1,FALSE),"") | E210: =IFERROR(VLOOKUP($A210,집계!$B:$AD,MATCH(E$1,집계!$2:$2,0)-1,FALSE),"") | F210: =IFERROR(VLOOKUP($A210,대상!$B:$AD,MATCH(F$1,대상!$1:$1,0)-1,FALSE),"") | G210: =IFERROR(VLOOKUP($A210,집계!$B:$AD,MATCH(G$1,집계!$2:$2,0)-1,FALSE),"") | H210: =IFERROR(VLOOKUP($A210,집계!$B:$AD,MATCH(H$1,집계!$2:$2,0)-1,FALSE),"") | I210: =IFERROR(VLOOKUP($A210,집계!$B:$AD,MATCH(I$1,집계!$2:$2,0)-1,FALSE),"") | J210: =IFERROR(VLOOKUP($A210,집계!$B:$AD,MATCH(J$1,집계!$2:$2,0)-1,FALSE),"") | K210: =IFERROR(VLOOKUP($A210,집계!$B:$AD,MATCH(K$1,집계!$2:$2,0)-1,FALSE),"") | L210: =IFERROR(VLOOKUP($A210,집계!$B:$AD,MATCH(L$1,집계!$2:$2,0)-1,FALSE),"") | M210: =IFERROR(VLOOKUP($A210,집계!$B:$AD,MATCH(M$1,집계!$2:$2,0)-1,FALSE),"") | N210: =IFERROR(VLOOKUP($A210,집계!$B:$AD,MATCH(N$1,집계!$2:$2,0)-1,FALSE),"") | ... P210: =IFERROR(VLOOKUP($A210,집계!$B:$AD,MATCH(P$1,집계!$2:$2,0)-1,FALSE),"")
B211: =IFERROR(VLOOKUP($A211,집계!$B:$AD,MATCH(B$1,집계!$2:$2,0)-1,FALSE),"") | C211: =IFERROR(VLOOKUP($A211,집계!$B:$AD,MATCH(C$1,집계!$2:$2,0)-1,FALSE),"") | D211: =IFERROR(VLOOKUP($A211,집계!$B:$AD,MATCH(D$1,집계!$2:$2,0)-1,FALSE),"") | E211: =IFERROR(VLOOKUP($A211,집계!$B:$AD,MATCH(E$1,집계!$2:$2,0)-1,FALSE),"") | F211: =IFERROR(VLOOKUP($A211,대상!$B:$AD,MATCH(F$1,대상!$1:$1,0)-1,FALSE),"") | G211: =IFERROR(VLOOKUP($A211,집계!$B:$AD,MATCH(G$1,집계!$2:$2,0)-1,FALSE),"") | H211: =IFERROR(VLOOKUP($A211,집계!$B:$AD,MATCH(H$1,집계!$2:$2,0)-1,FALSE),"") | I211: =IFERROR(VLOOKUP($A211,집계!$B:$AD,MATCH(I$1,집계!$2:$2,0)-1,FALSE),"") | J211: =IFERROR(VLOOKUP($A211,집계!$B:$AD,MATCH(J$1,집계!$2:$2,0)-1,FALSE),"") | K211: =IFERROR(VLOOKUP($A211,집계!$B:$AD,MATCH(K$1,집계!$2:$2,0)-1,FALSE),"") | L211: =IFERROR(VLOOKUP($A211,집계!$B:$AD,MATCH(L$1,집계!$2:$2,0)-1,FALSE),"") | M211: =IFERROR(VLOOKUP($A211,집계!$B:$AD,MATCH(M$1,집계!$2:$2,0)-1,FALSE),"") | N211: =IFERROR(VLOOKUP($A211,집계!$B:$AD,MATCH(N$1,집계!$2:$2,0)-1,FALSE),"") | ... P211: =IFERROR(VLOOKUP($A211,집계!$B:$AD,MATCH(P$1,집계!$2:$2,0)-1,FALSE),"")
B212: =IFERROR(VLOOKUP($A212,집계!$B:$AD,MATCH(B$1,집계!$2:$2,0)-1,FALSE),"") | C212: =IFERROR(VLOOKUP($A212,집계!$B:$AD,MATCH(C$1,집계!$2:$2,0)-1,FALSE),"") | D212: =IFERROR(VLOOKUP($A212,집계!$B:$AD,MATCH(D$1,집계!$2:$2,0)-1,FALSE),"") | E212: =IFERROR(VLOOKUP($A212,집계!$B:$AD,MATCH(E$1,집계!$2:$2,0)-1,FALSE),"") | F212: =IFERROR(VLOOKUP($A212,대상!$B:$AD,MATCH(F$1,대상!$1:$1,0)-1,FALSE),"") | G212: =IFERROR(VLOOKUP($A212,집계!$B:$AD,MATCH(G$1,집계!$2:$2,0)-1,FALSE),"") | H212: =IFERROR(VLOOKUP($A212,집계!$B:$AD,MATCH(H$1,집계!$2:$2,0)-1,FALSE),"") | I212: =IFERROR(VLOOKUP($A212,집계!$B:$AD,MATCH(I$1,집계!$2:$2,0)-1,FALSE),"") | J212: =IFERROR(VLOOKUP($A212,집계!$B:$AD,MATCH(J$1,집계!$2:$2,0)-1,FALSE),"") | K212: =IFERROR(VLOOKUP($A212,집계!$B:$AD,MATCH(K$1,집계!$2:$2,0)-1,FALSE),"") | L212: =IFERROR(VLOOKUP($A212,집계!$B:$AD,MATCH(L$1,집계!$2:$2,0)-1,FALSE),"") | M212: =IFERROR(VLOOKUP($A212,집계!$B:$AD,MATCH(M$1,집계!$2:$2,0)-1,FALSE),"") | N212: =IFERROR(VLOOKUP($A212,집계!$B:$AD,MATCH(N$1,집계!$2:$2,0)-1,FALSE),"") | ... P212: =IFERROR(VLOOKUP($A212,집계!$B:$AD,MATCH(P$1,집계!$2:$2,0)-1,FALSE),"")
B213: =IFERROR(VLOOKUP($A213,집계!$B:$AD,MATCH(B$1,집계!$2:$2,0)-1,FALSE),"") | C213: =IFERROR(VLOOKUP($A213,집계!$B:$AD,MATCH(C$1,집계!$2:$2,0)-1,FALSE),"") | D213: =IFERROR(VLOOKUP($A213,집계!$B:$AD,MATCH(D$1,집계!$2:$2,0)-1,FALSE),"") | E213: =IFERROR(VLOOKUP($A213,집계!$B:$AD,MATCH(E$1,집계!$2:$2,0)-1,FALSE),"") | F213: =IFERROR(VLOOKUP($A213,대상!$B:$AD,MATCH(F$1,대상!$1:$1,0)-1,FALSE),"") | G213: =IFERROR(VLOOKUP($A213,집계!$B:$AD,MATCH(G$1,집계!$2:$2,0)-1,FALSE),"") | H213: =IFERROR(VLOOKUP($A213,집계!$B:$AD,MATCH(H$1,집계!$2:$2,0)-1,FALSE),"") | I213: =IFERROR(VLOOKUP($A213,집계!$B:$AD,MATCH(I$1,집계!$2:$2,0)-1,FALSE),"") | J213: =IFERROR(VLOOKUP($A213,집계!$B:$AD,MATCH(J$1,집계!$2:$2,0)-1,FALSE),"") | K213: =IFERROR(VLOOKUP($A213,집계!$B:$AD,MATCH(K$1,집계!$2:$2,0)-1,FALSE),"") | L213: =IFERROR(VLOOKUP($A213,집계!$B:$AD,MATCH(L$1,집계!$2:$2,0)-1,FALSE),"") | M213: =IFERROR(VLOOKUP($A213,집계!$B:$AD,MATCH(M$1,집계!$2:$2,0)-1,FALSE),"") | N213: =IFERROR(VLOOKUP($A213,집계!$B:$AD,MATCH(N$1,집계!$2:$2,0)-1,FALSE),"") | ... P213: =IFERROR(VLOOKUP($A213,집계!$B:$AD,MATCH(P$1,집계!$2:$2,0)-1,FALSE),"")
B214: =IFERROR(VLOOKUP($A214,집계!$B:$AD,MATCH(B$1,집계!$2:$2,0)-1,FALSE),"") | C214: =IFERROR(VLOOKUP($A214,집계!$B:$AD,MATCH(C$1,집계!$2:$2,0)-1,FALSE),"") | D214: =IFERROR(VLOOKUP($A214,집계!$B:$AD,MATCH(D$1,집계!$2:$2,0)-1,FALSE),"") | E214: =IFERROR(VLOOKUP($A214,집계!$B:$AD,MATCH(E$1,집계!$2:$2,0)-1,FALSE),"") | F214: =IFERROR(VLOOKUP($A214,대상!$B:$AD,MATCH(F$1,대상!$1:$1,0)-1,FALSE),"") | G214: =IFERROR(VLOOKUP($A214,집계!$B:$AD,MATCH(G$1,집계!$2:$2,0)-1,FALSE),"") | H214: =IFERROR(VLOOKUP($A214,집계!$B:$AD,MATCH(H$1,집계!$2:$2,0)-1,FALSE),"") | I214: =IFERROR(VLOOKUP($A214,집계!$B:$AD,MATCH(I$1,집계!$2:$2,0)-1,FALSE),"") | J214: =IFERROR(VLOOKUP($A214,집계!$B:$AD,MATCH(J$1,집계!$2:$2,0)-1,FALSE),"") | K214: =IFERROR(VLOOKUP($A214,집계!$B:$AD,MATCH(K$1,집계!$2:$2,0)-1,FALSE),"") | L214: =IFERROR(VLOOKUP($A214,집계!$B:$AD,MATCH(L$1,집계!$2:$2,0)-1,FALSE),"") | M214: =IFERROR(VLOOKUP($A214,집계!$B:$AD,MATCH(M$1,집계!$2:$2,0)-1,FALSE),"") | N214: =IFERROR(VLOOKUP($A214,집계!$B:$AD,MATCH(N$1,집계!$2:$2,0)-1,FALSE),"") | ... P214: =IFERROR(VLOOKUP($A214,집계!$B:$AD,MATCH(P$1,집계!$2:$2,0)-1,FALSE),"")
... B218: =IFERROR(VLOOKUP($A218,집계!$B:$AD,MATCH(B$1,집계!$2:$2,0)-1,FALSE),"") | C218: =IFERROR(VLOOKUP($A218,집계!$B:$AD,MATCH(C$1,집계!$2:$2,0)-1,FALSE),"") | D218: =IFERROR(VLOOKUP($A218,집계!$B:$AD,MATCH(D$1,집계!$2:$2,0)-1,FALSE),"") | E218: =IFERROR(VLOOKUP($A218,집계!$B:$AD,MATCH(E$1,집계!$2:$2,0)-1,FALSE),"") | F218: =IFERROR(VLOOKUP($A218,대상!$B:$AD,MATCH(F$1,대상!$1:$1,0)-1,FALSE),"") | G218: =IFERROR(VLOOKUP($A218,집계!$B:$AD,MATCH(G$1,집계!$2:$2,0)-1,FALSE),"") | H218: =IFERROR(VLOOKUP($A218,집계!$B:$AD,MATCH(H$1,집계!$2:$2,0)-1,FALSE),"") | I218: =IFERROR(VLOOKUP($A218,집계!$B:$AD,MATCH(I$1,집계!$2:$2,0)-1,FALSE),"") | J218: =IFERROR(VLOOKUP($A218,집계!$B:$AD,MATCH(J$1,집계!$2:$2,0)-1,FALSE),"") | K218: =IFERROR(VLOOKUP($A218,집계!$B:$AD,MATCH(K$1,집계!$2:$2,0)-1,FALSE),"") | L218: =IFERROR(VLOOKUP($A218,집계!$B:$AD,MATCH(L$1,집계!$2:$2,0)-1,FALSE),"") | M218: =IFERROR(VLOOKUP($A218,집계!$B:$AD,MATCH(M$1,집계!$2:$2,0)-1,FALSE),"") | N218: =IFERROR(VLOOKUP($A218,집계!$B:$AD,MATCH(N$1,집계!$2:$2,0)-1,FALSE),"") | ... P218: =IFERROR(VLOOKUP($A218,집계!$B:$AD,MATCH(P$1,집계!$2:$2,0)-1,FALSE),"")
